Workbook

Sheet mini_dashboard

Sheet products
A1: id | B1: item_type
A2: 2103 | B2: Cereal
A3: 7940 | B3: Household
A4: 2455 | B4: Clothes
A5: 1270 | B5: Beverages
A6: 8681 | B6: Office Supplies
A7: 4594 | B7: Fruits
A8: 5988 | B8: Vegetables
A9: 7331 | B9: Baby Food
A10: 8875 | B10: Meat
A11: 8293 | B11: Cosmetics
A12: 8969 | B12: Snacks
A13: 3127 | B13: Personal Care

Sheet countries
A1: name | B1: alpha-2 | C1: alpha-3 | D1: region | E1: sub-region
A2: Afghanistan | B2: AF | C2: AFG | D2: Asia | E2: Southern Asia
A3: Åland Islands | B3: AX | C3: ALA | D3: Europe | E3: Northern Europe
A4: Albania | B4: AL | C4: ALB | D4: Europe | E4: Southern Europe
A5: Algeria | B5: DZ | C5: DZA | D5: Africa | E5: Northern Africa
A6: American Samoa | B6: AS | C6: ASM | D6: Oceania | E6: Polynesia
A7: Andorra | B7: AD | C7: AND | D7: Europe | E7: Southern Europe
A8: Angola | B8: AO | C8: AGO | D8: Africa | E8: Sub-Saharan Africa
A9: Anguilla | B9: AI | C9: AIA | D9: Americas | E9: Latin America and the Caribbean
A10: Antarctica | B10: AQ | C10: ATA | D10: Antarctica | E10: Antarctica
A11: Antigua and Barbuda | B11: AG | C11: ATG | D11: Americas | E11: Latin America and the Caribbean
A12: Argentina | B12: AR | C12: ARG | D12: Americas | E12: Latin America and the Caribbean
... A250: Zimbabwe | B250: ZW | C250: ZWE | D250: Africa | E250: Sub-Saharan Africa

Sheet events
A1: Order ID | B1: Order Date | C1: mesOrder Date | D1: diaOrder Date | E1: anoOrder Date | F1: order date formatada | G1: Ship Date | H1: mesShip Date | I1: diaShip Date | J1: anoShip Date | K1: ship date formatada | L1: Order Priority | M1: Country Code | N1: Product ID | O1: Sales Channel | P1: Units Sold | Q1: Unit Price | R1: Unit Cost | S1: receita_total | T1: custo_total | U1: lucro_total | V1: item_type | W1: region | X1: sub-region | Y1: % margem | Z1: lead_time | AA1: dia da semana compra
A2: 100640618 | B2: 41861 | C2: =IFERROR(__xludf.DUMMYFUNCTION("split(B2,""/"")"),10.0) -> 10 | D2: =IFERROR(__xludf.DUMMYFUNCTION("""COMPUTED_VALUE"""),8.0) -> 8 | E2: =IFERROR(__xludf.DUMMYFUNCTION("""COMPUTED_VALUE"""),2014.0) -> 2014 | F2: =DATE(E2,C2,D2) -> 41920 | G2: 10/18/2014 | H2: =IFERROR(__xludf.DUMMYFUNCTION("split(G2,""/"")"),10.0) -> 10 | I2: =IFERROR(__xludf.DUMMYFUNCTION("""COMPUTED_VALUE"""),18.0) -> 18 | J2: =IFERROR(__xludf.DUMMYFUNCTION("""COMPUTED_VALUE"""),2014.0) -> 2014 | K2: =DATE(J2,H2,I2) -> 41930 | L2: M | M2: NOR | N2: 2103 | O2: Online | P2: 650 | Q2: 205.7 | R2: 117.11 | S2: =Q2*P2 -> 133705 | T2: =R2*P2 -> 76121.5 | U2: =S2-T2 -> 57583.5 | V2: =VLOOKUP(N2,products!A:B,2,0) -> Cereal | W2: Europe | X2: Northern Europe | Y2: =U2/S2 -> 0.43067574 | Z2: =K2-F2 -> 10 | AA2: =WEEKDAY(F2,1) -> 4 | AB2: margem total | AC2: =U1332/S1332 -> 0.29459244
A3: 100983083 | B3: 42682 | C3: =IFERROR(__xludf.DUMMYFUNCTION("split(B3,""/"")"),8.0) -> 8 | D3: =IFERROR(__xludf.DUMMYFUNCTION("""COMPUTED_VALUE"""),11.0) -> 11 | E3: =IFERROR(__xludf.DUMMYFUNCTION("""COMPUTED_VALUE"""),2016.0) -> 2016 | F3: =DATE(E3,C3,D3) -> 42593 | G3: 42682 | H3: =IFERROR(__xludf.DUMMYFUNCTION("split(G3,""/"")"),8.0) -> 8 | I3: =IFERROR(__xludf.DUMMYFUNCTION("""COMPUTED_VALUE"""),11.0) -> 11 | J3: =IFERROR(__xludf.DUMMYFUNCTION("""COMPUTED_VALUE"""),2016.0) -> 2016 | K3: =DATE(J3,H3,I3) -> 42593 | L3: C | M3: SRB | N3: 2103 | O3: Offline | P3: 1993 | Q3: 205.7 | R3: 117.11 | S3: =Q3*P3 -> 409960.1 | T3: =R3*P3 -> 233400.23 | U3: =S3-T3 -> 176559.87 | V3: =VLOOKUP(N3,products!A:B,2,0) -> Cereal | W3: Europe | X3: Southern Europe | Y3: =U3/S3 -> 0.43067574 | Z3: =K3-F3 -> 0 | AA3: =WEEKDAY(F3,1) -> 5 | AB3: margem media | AC3: =AVERAGE(Y2:Y1331) -> 0.34051759
A4: 101025998 | B4: 7/18/2014 | C4: =IFERROR(__xludf.DUMMYFUNCTION("split(B4,""/"")"),7.0) -> 7 | D4: =IFERROR(__xludf.DUMMYFUNCTION("""COMPUTED_VALUE"""),18.0) -> 18 | E4: =IFERROR(__xludf.DUMMYFUNCTION("""COMPUTED_VALUE"""),2014.0) -> 2014 | F4: =DATE(E4,C4,D4) -> 41838 | G4: 41951 | H4: =IFERROR(__xludf.DUMMYFUNCTION("split(G4,""/"")"),8.0) -> 8 | I4: =IFERROR(__xludf.DUMMYFUNCTION("""COMPUTED_VALUE"""),11.0) -> 11 | J4: =IFERROR(__xludf.DUMMYFUNCTION("""COMPUTED_VALUE"""),2014.0) -> 2014 | K4: =DATE(J4,H4,I4) -> 41862 | L4: M | M4: Desconhecido | N4: 7940 | O4: Online | P4: 4693 | Q4: 668.27 | R4: 502.54 | S4: =Q4*P4 -> 3136191.1 | T4: =R4*P4 -> 2358420.2 | U4: =S4-T4 -> 777770.89 | V4: =VLOOKUP(N4,products!A:B,2,0) -> Household | W4: Desconhecido | X4: Desconhecido | Y4: =U4/S4 -> 0.24799856 | Z4: =K4-F4 -> 24 | AA4: =WEEKDAY(F4,1) -> 6 | AB4: margem mediana | AC4: =MEDIAN(Y2:Y1331) -> 0.33003161
A5: 102230632 | B5: 5/13/2017 | C5: =IFERROR(__xludf.DUMMYFUNCTION("split(B5,""/"")"),5.0) -> 5 | D5: =IFERROR(__xludf.DUMMYFUNCTION("""COMPUTED_VALUE"""),13.0) -> 13 | E5: =IFERROR(__xludf.DUMMYFUNCTION("""COMPUTED_VALUE"""),2017.0) -> 2017 | F5: =DATE(E5,C5,D5) -> 42868 | G5: 6/13/2017 | H5: =IFERROR(__xludf.DUMMYFUNCTION("split(G5,""/"")"),6.0) -> 6 | I5: =IFERROR(__xludf.DUMMYFUNCTION("""COMPUTED_VALUE"""),13.0) -> 13 | J5: =IFERROR(__xludf.DUMMYFUNCTION("""COMPUTED_VALUE"""),2017.0) -> 2017 | K5: =DATE(J5,H5,I5) -> 42899 | L5: L | M5: MNE | N5: 2455 | O5: Online | P5: 1171 | Q5: 109.28 | R5: 35.84 | S5: =Q5*P5 -> 127966.88 | T5: =R5*P5 -> 41968.64 | U5: =S5-T5 -> 85998.24 | V5: =VLOOKUP(N5,products!A:B,2,0) -> Clothes | W5: Europe | X5: Southern Europe | Y5: =U5/S5 -> 0.67203514 | Z5: =K5-F5 -> 31 | AA5: =WEEKDAY(F5,1) -> 7
A6: 103435266 | B6: 41221 | C6: =IFERROR(__xludf.DUMMYFUNCTION("split(B6,""/"")"),8.0) -> 8 | D6: =IFERROR(__xludf.DUMMYFUNCTION("""COMPUTED_VALUE"""),11.0) -> 11 | E6: =IFERROR(__xludf.DUMMYFUNCTION("""COMPUTED_VALUE"""),2012.0) -> 2012 | F6: =DATE(E6,C6,D6) -> 41132 | G6: 9/18/2012 | H6: =IFERROR(__xludf.DUMMYFUNCTION("split(G6,""/"")"),9.0) -> 9 | I6: =IFERROR(__xludf.DUMMYFUNCTION("""COMPUTED_VALUE"""),18.0) -> 18 | J6: =IFERROR(__xludf.DUMMYFUNCTION("""COMPUTED_VALUE"""),2012.0) -> 2012 | K6: =DATE(J6,H6,I6) -> 41170 | L6: H | M6: SRB | N6: 1270 | O6: Offline | P6: 7648 | Q6: 47.45 | R6: 31.79 | S6: =Q6*P6 -> 362897.6 | T6: =R6*P6 -> 243129.92 | U6: =S6-T6 -> 119767.68 | V6: =VLOOKUP(N6,products!A:B,2,0) -> Beverages | W6: Europe | X6: Southern Europe | Y6: =U6/S6 -> 0.33003161 | Z6: =K6-F6 -> 38 | AA6: =WEEKDAY(F6,1) -> 7
A7: 103450715 | B7: 3/15/2015 | C7: =IFERROR(__xludf.DUMMYFUNCTION("split(B7,""/"")"),3.0) -> 3 | D7: =IFERROR(__xludf.DUMMYFUNCTION("""COMPUTED_VALUE"""),15.0) -> 15 | E7: =IFERROR(__xludf.DUMMYFUNCTION("""COMPUTED_VALUE"""),2015.0) -> 2015 | F7: =DATE(E7,C7,D7) -> 42078 | G7: 4/18/2015 | H7: =IFERROR(__xludf.DUMMYFUNCTION("split(G7,""/"")"),4.0) -> 4 | I7: =IFERROR(__xludf.DUMMYFUNCTION("""COMPUTED_VALUE"""),18.0) -> 18 | J7: =IFERROR(__xludf.DUMMYFUNCTION("""COMPUTED_VALUE"""),2015.0) -> 2015 | K7: =DATE(J7,H7,I7) -> 42112 | L7: H | M7: SVK | N7: 8681 | O7: Online | P7: 2220 | Q7: 651.21 | R7: 524.96 | S7: =Q7*P7 -> 1445686.2 | T7: =R7*P7 -> 1165411.2 | U7: =S7-T7 -> 280275 | V7: =VLOOKUP(N7,products!A:B,2,0) -> Office Supplies | W7: Europe | X7: Eastern Europe | Y7: =U7/S7 -> 0.19386987 | Z7: =K7-F7 -> 34 | AA7: =WEEKDAY(F7,1) -> 1
A8: 103499639 | B8: 4/20/2013 | C8: =IFERROR(__xludf.DUMMYFUNCTION("split(B8,""/"")"),4.0) -> 4 | D8: =IFERROR(__xludf.DUMMYFUNCTION("""COMPUTED_VALUE"""),20.0) -> 20 | E8: =IFERROR(__xludf.DUMMYFUNCTION("""COMPUTED_VALUE"""),2013.0) -> 2013 | F8: =DATE(E8,C8,D8) -> 41384 | G8: 41431 | H8: =IFERROR(__xludf.DUMMYFUNCTION("split(G8,""/"")"),6.0) -> 6 | I8: =IFERROR(__xludf.DUMMYFUNCTION("""COMPUTED_VALUE"""),6.0) -> 6 | J8: =IFERROR(__xludf.DUMMYFUNCTION("""COMPUTED_VALUE"""),2013.0) -> 2013 | K8: =DATE(J8,H8,I8) -> 41431 | L8: L | M8: FRA | N8: 4594 | O8: Online | P8: 6698 | Q8: 9.33 | R8: 6.92 | S8: =Q8*P8 -> 62492.34 | T8: =R8*P8 -> 46350.16 | U8: =S8-T8 -> 16142.18 | V8: =VLOOKUP(N8,products!A:B,2,0) -> Fruits | W8: Europe | X8: Western Europe | Y8: =U8/S8 -> 0.25830654 | Z8: =K8-F8 -> 47 | AA8: =WEEKDAY(F8,1) -> 7
A9: 103762280 | B9: 40888 | C9: =IFERROR(__xludf.DUMMYFUNCTION("split(B9,""/"")"),11.0) -> 11 | D9: =IFERROR(__xludf.DUMMYFUNCTION("""COMPUTED_VALUE"""),12.0) -> 12 | E9: =IFERROR(__xludf.DUMMYFUNCTION("""COMPUTED_VALUE"""),2011.0) -> 2011 | F9: =DATE(E9,C9,D9) -> 40859 | G9: 12/14/2011 | H9: =IFERROR(__xludf.DUMMYFUNCTION("split(G9,""/"")"),12.0) -> 12 | I9: =IFERROR(__xludf.DUMMYFUNCTION("""COMPUTED_VALUE"""),14.0) -> 14 | J9: =IFERROR(__xludf.DUMMYFUNCTION("""COMPUTED_VALUE"""),2011.0) -> 2011 | K9: =DATE(J9,H9,I9) -> 40891 | L9: M | M9: ESP | N9: 5988 | O9: Online | P9: 4419 | Q9: 154.06 | R9: 90.93 | S9: =Q9*P9 -> 680791.14 | T9: =R9*P9 -> 401819.67 | U9: =S9-T9 -> 278971.47 | V9: =VLOOKUP(N9,products!A:B,2,0) -> Vegetables | W9: Europe | X9: Southern Europe | Y9: =U9/S9 -> 0.40977541 | Z9: =K9-F9 -> 32 | AA9: =WEEKDAY(F9,1) -> 7
A10: 103832662 | B10: 9/19/2012 | C10: =IFERROR(__xludf.DUMMYFUNCTION("split(B10,""/"")"),9.0) -> 9 | D10: =IFERROR(__xludf.DUMMYFUNCTION("""COMPUTED_VALUE"""),19.0) -> 19 | E10: =IFERROR(__xludf.DUMMYFUNCTION("""COMPUTED_VALUE"""),2012.0) -> 2012 | F10: =DATE(E10,C10,D10) -> 41171 | G10: 10/20/2012 | H10: =IFERROR(__xludf.DUMMYFUNCTION("split(G10,""/"")"),10.0) -> 10 | I10: =IFERROR(__xludf.DUMMYFUNCTION("""COMPUTED_VALUE"""),20.0) -> 20 | J10: =IFERROR(__xludf.DUMMYFUNCTION("""COMPUTED_VALUE"""),2012.0) -> 2012 | K10: =DATE(J10,H10,I10) -> 41202 | L10: H | M10: HRV | N10: 7331 | O10: Offline | P10: 5247 | Q10: 255.28 | R10: 159.42 | S10: =Q10*P10 -> 1339454.2 | T10: =R10*P10 -> 836476.74 | U10: =S10-T10 -> 502977.42 | V10: =VLOOKUP(N10,products!A:B,2,0) -> Baby Food | W10: Europe | X10: Southern Europe | Y10: =U10/S10 -> 0.37550924 | Z10: =K10-F10 -> 31 | AA10: =WEEKDAY(F10,1) -> 4
A11: 104008615 | B11: 1/23/2011 | C11: =IFERROR(__xludf.DUMMYFUNCTION("split(B11,""/"")"),1.0) -> 1 | D11: =IFERROR(__xludf.DUMMYFUNCTION("""COMPUTED_VALUE"""),23.0) -> 23 | E11: =IFERROR(__xludf.DUMMYFUNCTION("""COMPUTED_VALUE"""),2011.0) -> 2011 | F11: =DATE(E11,C11,D11) -> 40566 | G11: 2/22/2011 | H11: =IFERROR(__xludf.DUMMYFUNCTION("split(G11,""/"")"),2.0) -> 2 | I11: =IFERROR(__xludf.DUMMYFUNCTION("""COMPUTED_VALUE"""),22.0) -> 22 | J11: =IFERROR(__xludf.DUMMYFUNCTION("""COMPUTED_VALUE"""),2011.0) -> 2011 | K11: =DATE(J11,H11,I11) -> 40596 | L11: M | M11: DEU | N11: 2103 | O11: Online | P11: 7315 | Q11: 205.7 | R11: 117.11 | S11: =Q11*P11 -> 1504695.5 | T11: =R11*P11 -> 856659.65 | U11: =S11-T11 -> 648035.85 | V11: =VLOOKUP(N11,products!A:B,2,0) -> Cereal | W11: Europe | X11: Western Europe | Y11: =U11/S11 -> 0.43067574 | Z11: =K11-F11 -> 30 | AA11: =WEEKDAY(F11,1) -> 1
A12: 104165685 | B12: 2/19/2012 | C12: =IFERROR(__xludf.DUMMYFUNCTION("split(B12,""/"")"),2.0) -> 2 | D12: =IFERROR(__xludf.DUMMYFUNCTION("""COMPUTED_VALUE"""),19.0) -> 19 | E12: =IFERROR(__xludf.DUMMYFUNCTION("""COMPUTED_VALUE"""),2012.0) -> 2012 | F12: =DATE(E12,C12,D12) -> 40958 | G12: 41063 | H12: =IFERROR(__xludf.DUMMYFUNCTION("split(G12,""/"")"),3.0) -> 3 | I12: =IFERROR(__xludf.DUMMYFUNCTION("""COMPUTED_VALUE"""),6.0) -> 6 | J12: =IFERROR(__xludf.DUMMYFUNCTION("""COMPUTED_VALUE"""),2012.0) -> 2012 | K12: =DATE(J12,H12,I12) -> 40974 | L12: L | M12: ARM | N12: 7940 | O12: Online | P12: 3796 | Q12: 668.27 | R12: 502.54 | S12: =Q12*P12 -> 2536752.9 | T12: =R12*P12 -> 1907641.8 | U12: =S12-T12 -> 629111.08 | V12: =VLOOKUP(N12,products!A:B,2,0) -> Household | W12: Asia | X12: Western Asia | Y12: =U12/S12 -> 0.24799856 | Z12: =K12-F12 -> 16 | AA12: =WEEKDAY(F12,1) -> 1
A13: 104190576 | B13: 2/22/2017 | C13: =IFERROR(__xludf.DUMMYFUNCTION("split(B13,""/"")"),2.0) -> 2 | D13: =IFERROR(__xludf.DUMMYFUNCTION("""COMPUTED_VALUE"""),22.0) -> 22 | E13: =IFERROR(__xludf.DUMMYFUNCTION("""COMPUTED_VALUE"""),2017.0) -> 2017 | F13: =DATE(E13,C13,D13) -> 42788 | G13: 43072 | H13: =IFERROR(__xludf.DUMMYFUNCTION("split(G13,""/"")"),3.0) -> 3 | I13: =IFERROR(__xludf.DUMMYFUNCTION("""COMPUTED_VALUE"""),12.0) -> 12 | J13: =IFERROR(__xludf.DUMMYFUNCTION("""COMPUTED_VALUE"""),2017.0) -> 2017 | K13: =DATE(J13,H13,I13) -> 42806 | L13: C | M13: GEO | N13: 8875 | O13: Offline | P13: 1162 | Q13: 421.89 | R13: 364.69 | S13: =Q13*P13 -> 490236.18 | T13: =R13*P13 -> 423769.78 | U13: =S13-T13 -> 66466.4 | V13: =VLOOKUP(N13,products!A:B,2,0) -> Meat | W13: Asia | X13: Western Asia | Y13: =U13/S13 -> 0.13558036 | Z13: =K13-F13 -> 18 | AA13: =WEEKDAY(F13,1) -> 4
A14: 104245078 | B14: 3/27/2013 | C14: =IFERROR(__xludf.DUMMYFUNCTION("split(B14,""/"")"),3.0) -> 3 | D14: =IFERROR(__xludf.DUMMYFUNCTION("""COMPUTED_VALUE"""),27.0) -> 27 | E14: =IFERROR(__xludf.DUMMYFUNCTION("""COMPUTED_VALUE"""),2013.0) -> 2013 | F14: =DATE(E14,C14,D14) -> 41360 | G14: 4/21/2013 | H14: =IFERROR(__xludf.DUMMYFUNCTION("split(G14,""/"")"),4.0) -> 4 | I14: =IFERROR(__xludf.DUMMYFUNCTION("""COMPUTED_VALUE"""),21.0) -> 21 | J14: =IFERROR(__xludf.DUMMYFUNCTION("""COMPUTED_VALUE"""),2013.0) -> 2013 | K14: =DATE(J14,H14,I14) -> 41385 | L14: M | M14: GBR | N14: 4594 | O14: Offline | P14: 7290 | Q14: 9.33 | R14: 6.92 | S14: =Q14*P14 -> 68015.7 | T14: =R14*P14 -> 50446.8 | U14: =S14-T14 -> 17568.9 | V14: =VLOOKUP(N14,products!A:B,2,0) -> Fruits | W14: Europe | X14: Northern Europe | Y14: =U14/S14 -> 0.25830654 | Z14: =K14-F14 -> 25 | AA14: =WEEKDAY(F14,1) -> 4
A15: 104548490 | B15: 41640 | C15: =IFERROR(__xludf.DUMMYFUNCTION("split(B15,""/"")"),1.0) -> 1 | D15: =IFERROR(__xludf.DUMMYFUNCTION("""COMPUTED_VALUE"""),1.0) -> 1 | E15: =IFERROR(__xludf.DUMMYFUNCTION("""COMPUTED_VALUE"""),2014.0) -> 2014 | F15: =DATE(E15,C15,D15) -> 41640 | G15: 41760 | H15: =IFERROR(__xludf.DUMMYFUNCTION("split(G15,""/"")"),1.0) -> 1 | I15: =IFERROR(__xludf.DUMMYFUNCTION("""COMPUTED_VALUE"""),5.0) -> 5 | J15: =IFERROR(__xludf.DUMMYFUNCTION("""COMPUTED_VALUE"""),2014.0) -> 2014 | K15: =DATE(J15,H15,I15) -> 41644 | L15: M | M15: Desconhecido | N15: 7331 | O15: Online | P15: 7076 | Q15: 255.28 | R15: 159.42 | S15: =Q15*P15 -> 1806361.3 | T15: =R15*P15 -> 1128055.9 | U15: =S15-T15 -> 678305.36 | V15: =VLOOKUP(N15,products!A:B,2,0) -> Baby Food | W15: Desconhecido | X15: Desconhecido | Y15: =U15/S15 -> 0.37550924 | Z15: =K15-F15 -> 4 | AA15: =WEEKDAY(F15,1) -> 4
A16: 105030000 | B16: 42406 | C16: =IFERROR(__xludf.DUMMYFUNCTION("split(B16,""/"")"),6.0) -> 6 | D16: =IFERROR(__xludf.DUMMYFUNCTION("""COMPUTED_VALUE"""),2.0) -> 2 | E16: =IFERROR(__xludf.DUMMYFUNCTION("""COMPUTED_VALUE"""),2016.0) -> 2016 | F16: =DATE(E16,C16,D16) -> 42523 | G16: 6/13/2016 | H16: =IFERROR(__xludf.DUMMYFUNCTION("split(G16,""/"")"),6.0) -> 6 | I16: =IFERROR(__xludf.DUMMYFUNCTION("""COMPUTED_VALUE"""),13.0) -> 13 | J16: =IFERROR(__xludf.DUMMYFUNCTION("""COMPUTED_VALUE"""),2016.0) -> 2016 | K16: =DATE(J16,H16,I16) -> 42534 | L16: C | M16: SVN | N16: 2455 | O16: Offline | P16: 9566 | Q16: 109.28 | R16: 35.84 | S16: =Q16*P16 -> 1045372.5 | T16: =R16*P16 -> 342845.44 | U16: =S16-T16 -> 702527.04 | V16: =VLOOKUP(N16,products!A:B,2,0) -> Clothes | W16: Europe | X16: Southern Europe | Y16: =U16/S16 -> 0.67203514 | Z16: =K16-F16 -> 11 | AA16: =WEEKDAY(F16,1) -> 5
A17: 107651269 | B17: 10/28/2013 | C17: =IFERROR(__xludf.DUMMYFUNCTION("split(B17,""/"")"),10.0) -> 10 | D17: =IFERROR(__xludf.DUMMYFUNCTION("""COMPUTED_VALUE"""),28.0) -> 28 | E17: =IFERROR(__xludf.DUMMYFUNCTION("""COMPUTED_VALUE"""),2013.0) -> 2013 | F17: =DATE(E17,C17,D17) -> 41575 | G17: 41589 | H17: =IFERROR(__xludf.DUMMYFUNCTION("split(G17,""/"")"),11.0) -> 11 | I17: =IFERROR(__xludf.DUMMYFUNCTION("""COMPUTED_VALUE"""),11.0) -> 11 | J17: =IFERROR(__xludf.DUMMYFUNCTION("""COMPUTED_VALUE"""),2013.0) -> 2013 | K17: =DATE(J17,H17,I17) -> 41589 | L17: M | M17: HRV | N17: 7940 | O17: Online | P17: 5258 | Q17: 668.27 | R17: 502.54 | S17: =Q17*P17 -> 3513763.7 | T17: =R17*P17 -> 2642355.3 | U17: =S17-T17 -> 871408.34 | V17: =VLOOKUP(N17,products!A:B,2,0) -> Household | W17: Europe | X17: Southern Europe | Y17: =U17/S17 -> 0.24799856 | Z17: =K17-F17 -> 14 | AA17: =WEEKDAY(F17,1) -> 2
A18: 108407437 | B18: 2/19/2015 | C18: =IFERROR(__xludf.DUMMYFUNCTION("split(B18,""/"")"),2.0) -> 2 | D18: =IFERROR(__xludf.DUMMYFUNCTION("""COMPUTED_VALUE"""),19.0) -> 19 | E18: =IFERROR(__xludf.DUMMYFUNCTION("""COMPUTED_VALUE"""),2015.0) -> 2015 | F18: =DATE(E18,C18,D18) -> 42054 | G18: 3/27/2015 | H18: =IFERROR(__xludf.DUMMYFUNCTION("split(G18,""/"")"),3.0) -> 3 | I18: =IFERROR(__xludf.DUMMYFUNCTION("""COMPUTED_VALUE"""),27.0) -> 27 | J18: =IFERROR(__xludf.DUMMYFUNCTION("""COMPUTED_VALUE"""),2015.0) -> 2015 | K18: =DATE(J18,H18,I18) -> 42090 | L18: C | M18: ROU | N18: 7331 | O18: Offline | P18: 9025 | Q18: 255.28 | R18: 159.42 | S18: =Q18*P18 -> 2303902 | T18: =R18*P18 -> 1438765.5 | U18: =S18-T18 -> 865136.5 | V18: =VLOOKUP(N18,products!A:B,2,0) -> Baby Food | W18: Europe | X18: Eastern Europe | Y18: =U18/S18 -> 0.37550924 | Z18: =K18-F18 -> 36 | AA18: =WEEKDAY(F18,1) -> 5
A19: 109914195 | B19: 41246 | C19: =IFERROR(__xludf.DUMMYFUNCTION("split(B19,""/"")"),3.0) -> 3 | D19: =IFERROR(__xludf.DUMMYFUNCTION("""COMPUTED_VALUE"""),12.0) -> 12 | E19: =IFERROR(__xludf.DUMMYFUNCTION("""COMPUTED_VALUE"""),2012.0) -> 2012 | F19: =DATE(E19,C19,D19) -> 40980 | G19: 4/16/2012 | H19: =IFERROR(__xludf.DUMMYFUNCTION("split(G19,""/"")"),4.0) -> 4 | I19: =IFERROR(__xludf.DUMMYFUNCTION("""COMPUTED_VALUE"""),16.0) -> 16 | J19: =IFERROR(__xludf.DUMMYFUNCTION("""COMPUTED_VALUE"""),2012.0) -> 2012 | K19: =DATE(J19,H19,I19) -> 41015 | L19: M | M19: POL | N19: 2455 | O19: Offline | P19: 4908 | Q19: 109.28 | R19: 35.84 | S19: =Q19*P19 -> 536346.24 | T19: =R19*P19 -> 175902.72 | U19: =S19-T19 -> 360443.52 | V19: =VLOOKUP(N19,products!A:B,2,0) -> Clothes | W19: Europe | X19: Eastern Europe | Y19: =U19/S19 -> 0.67203514 | Z19: =K19-F19 -> 35 | AA19: =WEEKDAY(F19,1) -> 2
A20: 111063039 | B20: 5/26/2012 | C20: =IFERROR(__xludf.DUMMYFUNCTION("split(B20,""/"")"),5.0) -> 5 | D20: =IFERROR(__xludf.DUMMYFUNCTION("""COMPUTED_VALUE"""),26.0) -> 26 | E20: =IFERROR(__xludf.DUMMYFUNCTION("""COMPUTED_VALUE"""),2012.0) -> 2012 | F20: =DATE(E20,C20,D20) -> 41055 | G20: 7/13/2012 | H20: =IFERROR(__xludf.DUMMYFUNCTION("split(G20,""/"")"),7.0) -> 7 | I20: =IFERROR(__xludf.DUMMYFUNCTION("""COMPUTED_VALUE"""),13.0) -> 13 | J20: =IFERROR(__xludf.DUMMYFUNCTION("""COMPUTED_VALUE"""),2012.0) -> 2012 | K20: =DATE(J20,H20,I20) -> 41103 | L20: L | M20: LUX | N20: 7331 | O20: Online | P20: 4876 | Q20: 255.28 | R20: 159.42 | S20: =Q20*P20 -> 1244745.3 | T20: =R20*P20 -> 777331.92 | U20: =S20-T20 -> 467413.36 | V20: =VLOOKUP(N20,products!A:B,2,0) -> Baby Food | W20: Europe | X20: Western Europe | Y20: =U20/S20 -> 0.37550924 | Z20: =K20-F20 -> 48 | AA20: =WEEKDAY(F20,1) -> 7
A21: 111246287 | B21: 42984 | C21: =IFERROR(__xludf.DUMMYFUNCTION("split(B21,""/"")"),6.0) -> 6 | D21: =IFERROR(__xludf.DUMMYFUNCTION("""COMPUTED_VALUE"""),9.0) -> 9 | E21: =IFERROR(__xludf.DUMMYFUNCTION("""COMPUTED_VALUE"""),2017.0) -> 2017 | F21: =DATE(E21,C21,D21) -> 42895 | G21: 42773 | H21: =IFERROR(__xludf.DUMMYFUNCTION("split(G21,""/"")"),7.0) -> 7 | I21: =IFERROR(__xludf.DUMMYFUNCTION("""COMPUTED_VALUE"""),2.0) -> 2 | J21: =IFERROR(__xludf.DUMMYFUNCTION("""COMPUTED_VALUE"""),2017.0) -> 2017 | K21: =DATE(J21,H21,I21) -> 42918 | L21: M | M21: CYP | N21: 8875 | O21: Offline | P21: 9103 | Q21: 421.89 | R21: 364.69 | S21: =Q21*P21 -> 3840464.7 | T21: =R21*P21 -> 3319773.1 | U21: =S21-T21 -> 520691.6 | V21: =VLOOKUP(N21,products!A:B,2,0) -> Meat | W21: Asia | X21: Western Asia | Y21: =U21/S21 -> 0.13558036 | Z21: =K21-F21 -> 23 | AA21: =WEEKDAY(F21,1) -> 6
A22: 111496055 | B22: 4/28/2011 | C22: =IFERROR(__xludf.DUMMYFUNCTION("split(B22,""/"")"),4.0) -> 4 | D22: =IFERROR(__xludf.DUMMYFUNCTION("""COMPUTED_VALUE"""),28.0) -> 28 | E22: =IFERROR(__xludf.DUMMYFUNCTION("""COMPUTED_VALUE"""),2011.0) -> 2011 | F22: =DATE(E22,C22,D22) -> 40661 | G22: 40639 | H22: =IFERROR(__xludf.DUMMYFUNCTION("split(G22,""/"")"),6.0) -> 6 | I22: =IFERROR(__xludf.DUMMYFUNCTION("""COMPUTED_VALUE"""),4.0) -> 4 | J22: =IFERROR(__xludf.DUMMYFUNCTION("""COMPUTED_VALUE"""),2011.0) -> 2011 | K22: =DATE(J22,H22,I22) -> 40698 | L22: M | M22: BEL | N22: 4594 | O22: Online | P22: 3015 | Q22: 9.33 | R22: 6.92 | S22: =Q22*P22 -> 28129.95 | T22: =R22*P22 -> 20863.8 | U22: =S22-T22 -> 7266.15 | V22: =VLOOKUP(N22,products!A:B,2,0) -> Fruits | W22: Europe | X22: Western Europe | Y22: =U22/S22 -> 0.25830654 | Z22: =K22-F22 -> 37 | AA22: =WEEKDAY(F22,1) -> 5
A23: 111893022 | B23: 10/28/2016 | C23: =IFERROR(__xludf.DUMMYFUNCTION("split(B23,""/"")"),10.0) -> 10 | D23: =IFERROR(__xludf.DUMMYFUNCTION("""COMPUTED_VALUE"""),28.0) -> 28 | E23: =IFERROR(__xludf.DUMMYFUNCTION("""COMPUTED_VALUE"""),2016.0) -> 2016 | F23: =DATE(E23,C23,D23) -> 42671 | G23: 42412 | H23: =IFERROR(__xludf.DUMMYFUNCTION("split(G23,""/"")"),12.0) -> 12 | I23: =IFERROR(__xludf.DUMMYFUNCTION("""COMPUTED_VALUE"""),2.0) -> 2 | J23: =IFERROR(__xludf.DUMMYFUNCTION("""COMPUTED_VALUE"""),2016.0) -> 2016 | K23: =DATE(J23,H23,I23) -> 42706 | L23: L | M23: SVN | N23: 7331 | O23: Online | P23: 486 | Q23: 255.28 | R23: 159.42 | S23: =Q23*P23 -> 124066.08 | T23: =R23*P23 -> 77478.12 | U23: =S23-T23 -> 46587.96 | V23: =VLOOKUP(N23,products!A:B,2,0) -> Baby Food | W23: Europe | X23: Southern Europe | Y23: =U23/S23 -> 0.37550924 | Z23: =K23-F23 -> 35 | AA23: =WEEKDAY(F23,1) -> 6
A24: 112330758 | B24: 12/15/2016 | C24: =IFERROR(__xludf.DUMMYFUNCTION("split(B24,""/"")"),12.0) -> 12 | D24: =IFERROR(__xludf.DUMMYFUNCTION("""COMPUTED_VALUE"""),15.0) -> 15 | E24: =IFERROR(__xludf.DUMMYFUNCTION("""COMPUTED_VALUE"""),2016.0) -> 2016 | F24: =DATE(E24,C24,D24) -> 42719 | G24: 43040 | H24: =IFERROR(__xludf.DUMMYFUNCTION("split(G24,""/"")"),1.0) -> 1 | I24: =IFERROR(__xludf.DUMMYFUNCTION("""COMPUTED_VALUE"""),11.0) -> 11 | J24: =IFERROR(__xludf.DUMMYFUNCTION("""COMPUTED_VALUE"""),2017.0) -> 2017 | K24: =DATE(J24,H24,I24) -> 42746 | L24: C | M24: LTU | N24: 8681 | O24: Offline | P24: 22 | Q24: 651.21 | R24: 524.96 | S24: =Q24*P24 -> 14326.62 | T24: =R24*P24 -> 11549.12 | U24: =S24-T24 -> 2777.5 | V24: =VLOOKUP(N24,products!A:B,2,0) -> Office Supplies | W24: Europe | X24: Northern Europe | Y24: =U24/S24 -> 0.19386987 | Z24: =K24-F24 -> 27 | AA24: =WEEKDAY(F24,1) -> 5
A25: 113524663 | B25: 10/29/2010 | C25: =IFERROR(__xludf.DUMMYFUNCTION("split(B25,""/"")"),10.0) -> 10 | D25: =IFERROR(__xludf.DUMMYFUNCTION("""COMPUTED_VALUE"""),29.0) -> 29 | E25: =IFERROR(__xludf.DUMMYFUNCTION("""COMPUTED_VALUE"""),2010.0) -> 2010 | F25: =DATE(E25,C25,D25) -> 40480 | G25: 40433 | H25: =IFERROR(__xludf.DUMMYFUNCTION("split(G25,""/"")"),12.0) -> 12 | I25: =IFERROR(__xludf.DUMMYFUNCTION("""COMPUTED_VALUE"""),9.0) -> 9 | J25: =IFERROR(__xludf.DUMMYFUNCTION("""COMPUTED_VALUE"""),2010.0) -> 2010 | K25: =DATE(J25,H25,I25) -> 40521 | L25: L | M25: RUS | N25: 8293 | O25: Online | P25: 3325 | Q25: 437.2 | R25: 263.33 | S25: =Q25*P25 -> 1453690 | T25: =R25*P25 -> 875572.25 | U25: =S25-T25 -> 578117.75 | V25: =VLOOKUP(N25,products!A:B,2,0) -> Cosmetics | W25: Europe | X25: Eastern Europe | Y25: =U25/S25 -> 0.39768984 | Z25: =K25-F25 -> 41 | AA25: =WEEKDAY(F25,1) -> 6
A26: 114954173 | B26: 40239 | C26: =IFERROR(__xludf.DUMMYFUNCTION("split(B26,""/"")"),2.0) -> 2 | D26: =IFERROR(__xludf.DUMMYFUNCTION("""COMPUTED_VALUE"""),3.0) -> 3 | E26: =IFERROR(__xludf.DUMMYFUNCTION("""COMPUTED_VALUE"""),2010.0) -> 2010 | F26: =DATE(E26,C26,D26) -> 40212 | G26: 40484 | H26: =IFERROR(__xludf.DUMMYFUNCTION("split(G26,""/"")"),2.0) -> 2 | I26: =IFERROR(__xludf.DUMMYFUNCTION("""COMPUTED_VALUE"""),11.0) -> 11 | J26: =IFERROR(__xludf.DUMMYFUNCTION("""COMPUTED_VALUE"""),2010.0) -> 2010 | K26: =DATE(J26,H26,I26) -> 40220 | L26: C | M26: MLT | N26: 4594 | O26: Offline | P26: 6349 | Q26: 9.33 | R26: 6.92 | S26: =Q26*P26 -> 59236.17 | T26: =R26*P26 -> 43935.08 | U26: =S26-T26 -> 15301.09 | V26: =VLOOKUP(N26,products!A:B,2,0) -> Fruits | W26: Europe | X26: Southern Europe | Y26: =U26/S26 -> 0.25830654 | Z26: =K26-F26 -> 8 | AA26: =WEEKDAY(F26,1) -> 4
A27: 115363156 | B27: 42106 | C27: =IFERROR(__xludf.DUMMYFUNCTION("split(B27,""/"")"),12.0) -> 12 | D27: =IFERROR(__xludf.DUMMYFUNCTION("""COMPUTED_VALUE"""),4.0) -> 4 | E27: =IFERROR(__xludf.DUMMYFUNCTION("""COMPUTED_VALUE"""),2015.0) -> 2015 | F27: =DATE(E27,C27,D27) -> 42342 | G27: 42644 | H27: =IFERROR(__xludf.DUMMYFUNCTION("split(G27,""/"")"),1.0) -> 1 | I27: =IFERROR(__xludf.DUMMYFUNCTION("""COMPUTED_VALUE"""),10.0) -> 10 | J27: =IFERROR(__xludf.DUMMYFUNCTION("""COMPUTED_VALUE"""),2016.0) -> 2016 | K27: =DATE(J27,H27,I27) -> 42379 | L27: H | M27: UKR | N27: 8681 | O27: Offline | P27: 7376 | Q27: 651.21 | R27: 524.96 | S27: =Q27*P27 -> 4803325 | T27: =R27*P27 -> 3872105 | U27: =S27-T27 -> 931220 | V27: =VLOOKUP(N27,products!A:B,2,0) -> Office Supplies | W27: Europe | X27: Eastern Europe | Y27: =U27/S27 -> 0.19386987 | Z27: =K27-F27 -> 37 | AA27: =WEEKDAY(F27,1) -> 6
A28: 117929494 | B28: 1/24/2015 | C28: =IFERROR(__xludf.DUMMYFUNCTION("split(B28,""/"")"),1.0) -> 1 | D28: =IFERROR(__xludf.DUMMYFUNCTION("""COMPUTED_VALUE"""),24.0) -> 24 | E28: =IFERROR(__xludf.DUMMYFUNCTION("""COMPUTED_VALUE"""),2015.0) -> 2015 | F28: =DATE(E28,C28,D28) -> 42028 | G28: 42038 | H28: =IFERROR(__xludf.DUMMYFUNCTION("split(G28,""/"")"),3.0) -> 3 | I28: =IFERROR(__xludf.DUMMYFUNCTION("""COMPUTED_VALUE"""),2.0) -> 2 | J28: =IFERROR(__xludf.DUMMYFUNCTION("""COMPUTED_VALUE"""),2015.0) -> 2015 | K28: =DATE(J28,H28,I28) -> 42065 | L28: H | M28: Desconhecido | N28: 4594 | O28: Offline | P28: 6813 | Q28: 9.33 | R28: 6.92 | S28: =Q28*P28 -> 63565.29 | T28: =R28*P28 -> 47145.96 | U28: =S28-T28 -> 16419.33 | V28: =VLOOKUP(N28,products!A:B,2,0) -> Fruits | W28: Desconhecido | X28: Desconhecido | Y28: =U28/S28 -> 0.25830654 | Z28: =K28-F28 -> 37 | AA28: =WEEKDAY(F28,1) -> 7
A29: 118086564 | B29: 2/19/2016 | C29: =IFERROR(__xludf.DUMMYFUNCTION("split(B29,""/"")"),2.0) -> 2 | D29: =IFERROR(__xludf.DUMMYFUNCTION("""COMPUTED_VALUE"""),19.0) -> 19 | E29: =IFERROR(__xludf.DUMMYFUNCTION("""COMPUTED_VALUE"""),2016.0) -> 2016 | F29: =DATE(E29,C29,D29) -> 42419 | G29: 3/13/2016 | H29: =IFERROR(__xludf.DUMMYFUNCTION("split(G29,""/"")"),3.0) -> 3 | I29: =IFERROR(__xludf.DUMMYFUNCTION("""COMPUTED_VALUE"""),13.0) -> 13 | J29: =IFERROR(__xludf.DUMMYFUNCTION("""COMPUTED_VALUE"""),2016.0) -> 2016 | K29: =DATE(J29,H29,I29) -> 42442 | L29: M | M29: NOR | N29: 8969 | O29: Online | P29: 3293 | Q29: 152.58 | R29: 97.44 | S29: =Q29*P29 -> 502445.94 | T29: =R29*P29 -> 320869.92 | U29: =S29-T29 -> 181576.02 | V29: =VLOOKUP(N29,products!A:B,2,0) -> Snacks | W29: Europe | X29: Northern Europe | Y29: =U29/S29 -> 0.36138419 | Z29: =K29-F29 -> 23 | AA29: =WEEKDAY(F29,1) -> 6
A30: 118659913 | B30: 41678 | C30: =IFERROR(__xludf.DUMMYFUNCTION("split(B30,""/"")"),8.0) -> 8 | D30: =IFERROR(__xludf.DUMMYFUNCTION("""COMPUTED_VALUE"""),2.0) -> 2 | E30: =IFERROR(__xludf.DUMMYFUNCTION("""COMPUTED_VALUE"""),2014.0) -> 2014 | F30: =DATE(E30,C30,D30) -> 41853 | G30: 8/17/2014 | H30: =IFERROR(__xludf.DUMMYFUNCTION("split(G30,""/"")"),8.0) -> 8 | I30: =IFERROR(__xludf.DUMMYFUNCTION("""COMPUTED_VALUE"""),17.0) -> 17 | J30: =IFERROR(__xludf.DUMMYFUNCTION("""COMPUTED_VALUE"""),2014.0) -> 2014 | K30: =DATE(J30,H30,I30) -> 41868 | L30: C | M30: CZE | N30: 2103 | O30: Online | P30: 2960 | Q30: 205.7 | R30: 117.11 | S30: =Q30*P30 -> 608872 | T30: =R30*P30 -> 346645.6 | U30: =S30-T30 -> 262226.4 | V30: =VLOOKUP(N30,products!A:B,2,0) -> Cereal | W30: Europe | X30: Eastern Europe | Y30: =U30/S30 -> 0.43067574 | Z30: =K30-F30 -> 15 | AA30: =WEEKDAY(F30,1) -> 7
A31: 118859469 | B31: 40580 | C31: =IFERROR(__xludf.DUMMYFUNCTION("split(B31,""/"")"),6.0) -> 6 | D31: =IFERROR(__xludf.DUMMYFUNCTION("""COMPUTED_VALUE"""),2.0) -> 2 | E31: =IFERROR(__xludf.DUMMYFUNCTION("""COMPUTED_VALUE"""),2011.0) -> 2011 | F31: =DATE(E31,C31,D31) -> 40696 | G31: 40550 | H31: =IFERROR(__xludf.DUMMYFUNCTION("split(G31,""/"")"),7.0) -> 7 | I31: =IFERROR(__xludf.DUMMYFUNCTION("""COMPUTED_VALUE"""),1.0) -> 1 | J31: =IFERROR(__xludf.DUMMYFUNCTION("""COMPUTED_VALUE"""),2011.0) -> 2011 | K31: =DATE(J31,H31,I31) -> 40725 | L31: L | M31: Desconhecido | N31: 8969 | O31: Offline | P31: 2013 | Q31: 152.58 | R31: 97.44 | S31: =Q31*P31 -> 307143.54 | T31: =R31*P31 -> 196146.72 | U31: =S31-T31 -> 110996.82 | V31: =VLOOKUP(N31,products!A:B,2,0) -> Snacks | W31: Desconhecido | X31: Desconhecido | Y31: =U31/S31 -> 0.36138419 | Z31: =K31-F31 -> 29 | AA31: =WEEKDAY(F31,1) -> 5
A32: 119935786 | B32: 1/14/2015 | C32: =IFERROR(__xludf.DUMMYFUNCTION("split(B32,""/"")"),1.0) -> 1 | D32: =IFERROR(__xludf.DUMMYFUNCTION("""COMPUTED_VALUE"""),14.0) -> 14 | E32: =IFERROR(__xludf.DUMMYFUNCTION("""COMPUTED_VALUE"""),2015.0) -> 2015 | F32: =DATE(E32,C32,D32) -> 42018 | G32: 1/27/2015 | H32: =IFERROR(__xludf.DUMMYFUNCTION("split(G32,""/"")"),1.0) -> 1 | I32: =IFERROR(__xludf.DUMMYFUNCTION("""COMPUTED_VALUE"""),27.0) -> 27 | J32: =IFERROR(__xludf.DUMMYFUNCTION("""COMPUTED_VALUE"""),2015.0) -> 2015 | K32: =DATE(J32,H32,I32) -> 42031 | L32: L | M32: ROU | N32: 3127 | O32: Offline | P32: 519 | Q32: 81.73 | R32: 56.67 | S32: =Q32*P32 -> 42417.87 | T32: =R32*P32 -> 29411.73 | U32: =S32-T32 -> 13006.14 | V32: =VLOOKUP(N32,products!A:B,2,0) -> Personal Care | W32: Europe | X32: Eastern Europe | Y32: =U32/S32 -> 0.30661936 | Z32: =K32-F32 -> 13 | AA32: =WEEKDAY(F32,1) -> 4
A33: 120419871 | B33: 5/13/2015 | C33: =IFERROR(__xludf.DUMMYFUNCTION("split(B33,""/"")"),5.0) -> 5 | D33: =IFERROR(__xludf.DUMMYFUNCTION("""COMPUTED_VALUE"""),13.0) -> 13 | E33: =IFERROR(__xludf.DUMMYFUNCTION("""COMPUTED_VALUE"""),2015.0) -> 2015 | F33: =DATE(E33,C33,D33) -> 42137 | G33: 6/26/2015 | H33: =IFERROR(__xludf.DUMMYFUNCTION("split(G33,""/"")"),6.0) -> 6 | I33: =IFERROR(__xludf.DUMMYFUNCTION("""COMPUTED_VALUE"""),26.0) -> 26 | J33: =IFERROR(__xludf.DUMMYFUNCTION("""COMPUTED_VALUE"""),2015.0) -> 2015 | K33: =DATE(J33,H33,I33) -> 42181 | L33: H | M33: LTU | N33: 3127 | O33: Online | P33: 3771 | Q33: 81.73 | R33: 56.67 | S33: =Q33*P33 -> 308203.83 | T33: =R33*P33 -> 213702.57 | U33: =S33-T33 -> 94501.26 | V33: =VLOOKUP(N33,products!A:B,2,0) -> Personal Care | W33: Europe | X33: Northern Europe | Y33: =U33/S33 -> 0.30661936 | Z33: =K33-F33 -> 44 | AA33: =WEEKDAY(F33,1) -> 4
A34: 120977771 | B34: 3/23/2011 | C34: =IFERROR(__xludf.DUMMYFUNCTION("split(B34,""/"")"),3.0) -> 3 | D34: =IFERROR(__xludf.DUMMYFUNCTION("""COMPUTED_VALUE"""),23.0) -> 23 | E34: =IFERROR(__xludf.DUMMYFUNCTION("""COMPUTED_VALUE"""),2011.0) -> 2011 | F34: =DATE(E34,C34,D34) -> 40625 | G34: 40579 | H34: =IFERROR(__xludf.DUMMYFUNCTION("split(G34,""/"")"),5.0) -> 5 | I34: =IFERROR(__xludf.DUMMYFUNCTION("""COMPUTED_VALUE"""),2.0) -> 2 | J34: =IFERROR(__xludf.DUMMYFUNCTION("""COMPUTED_VALUE"""),2011.0) -> 2011 | K34: =DATE(J34,H34,I34) -> 40665 | L34: M | M34: ARM | N34: 4594 | O34: Online | P34: 8866 | Q34: 9.33 | R34: 6.92 | S34: =Q34*P34 -> 82719.78 | T34: =R34*P34 -> 61352.72 | U34: =S34-T34 -> 21367.06 | V34: =VLOOKUP(N34,products!A:B,2,0) -> Fruits | W34: Asia | X34: Western Asia | Y34: =U34/S34 -> 0.25830654 | Z34: =K34-F34 -> 40 | AA34: =WEEKDAY(F34,1) -> 4
A35: 121380746 | B35: 11/21/2016 | C35: =IFERROR(__xludf.DUMMYFUNCTION("split(B35,""/"")"),11.0) -> 11 | D35: =IFERROR(__xludf.DUMMYFUNCTION("""COMPUTED_VALUE"""),21.0) -> 21 | E35: =IFERROR(__xludf.DUMMYFUNCTION("""COMPUTED_VALUE"""),2016.0) -> 2016 | F35: =DATE(E35,C35,D35) -> 42695 | G35: 12/18/2016 | H35: =IFERROR(__xludf.DUMMYFUNCTION("split(G35,""/"")"),12.0) -> 12 | I35: =IFERROR(__xludf.DUMMYFUNCTION("""COMPUTED_VALUE"""),18.0) -> 18 | J35: =IFERROR(__xludf.DUMMYFUNCTION("""COMPUTED_VALUE"""),2016.0) -> 2016 | K35: =DATE(J35,H35,I35) -> 42722 | L35: C | M35: MLT | N35: 4594 | O35: Online | P35: 8115 | Q35: 9.33 | R35: 6.92 | S35: =Q35*P35 -> 75712.95 | T35: =R35*P35 -> 56155.8 | U35: =S35-T35 -> 19557.15 | V35: =VLOOKUP(N35,products!A:B,2,0) -> Fruits | W35: Europe | X35: Southern Europe | Y35: =U35/S35 -> 0.25830654 | Z35: =K35-F35 -> 27 | AA35: =WEEKDAY(F35,1) -> 2
A36: 121945512 | B36: 42951 | C36: =IFERROR(__xludf.DUMMYFUNCTION("split(B36,""/"")"),4.0) -> 4 | D36: =IFERROR(__xludf.DUMMYFUNCTION("""COMPUTED_VALUE"""),8.0) -> 8 | E36: =IFERROR(__xludf.DUMMYFUNCTION("""COMPUTED_VALUE"""),2017.0) -> 2017 | F36: =DATE(E36,C36,D36) -> 42833 | G36: 43073 | H36: =IFERROR(__xludf.DUMMYFUNCTION("split(G36,""/"")"),4.0) -> 4 | I36: =IFERROR(__xludf.DUMMYFUNCTION("""COMPUTED_VALUE"""),12.0) -> 12 | J36: =IFERROR(__xludf.DUMMYFUNCTION("""COMPUTED_VALUE"""),2017.0) -> 2017 | K36: =DATE(J36,H36,I36) -> 42837 | L36: C | M36: GBR | N36: 1270 | O36: Online | P36: 5242 | Q36: 47.45 | R36: 31.79 | S36: =Q36*P36 -> 248732.9 | T36: =R36*P36 -> 166643.18 | U36: =S36-T36 -> 82089.72 | V36: =VLOOKUP(N36,products!A:B,2,0) -> Beverages | W36: Europe | X36: Northern Europe | Y36: =U36/S36 -> 0.33003161 | Z36: =K36-F36 -> 4 | AA36: =WEEKDAY(F36,1) -> 7
A37: 122144210 | B37: 4/27/2017 | C37: =IFERROR(__xludf.DUMMYFUNCTION("split(B37,""/"")"),4.0) -> 4 | D37: =IFERROR(__xludf.DUMMYFUNCTION("""COMPUTED_VALUE"""),27.0) -> 27 | E37: =IFERROR(__xludf.DUMMYFUNCTION("""COMPUTED_VALUE"""),2017.0) -> 2017 | F37: =DATE(E37,C37,D37) -> 42852 | G37: 5/24/2017 | H37: =IFERROR(__xludf.DUMMYFUNCTION("split(G37,""/"")"),5.0) -> 5 | I37: =IFERROR(__xludf.DUMMYFUNCTION("""COMPUTED_VALUE"""),24.0) -> 24 | J37: =IFERROR(__xludf.DUMMYFUNCTION("""COMPUTED_VALUE"""),2017.0) -> 2017 | K37: =DATE(J37,H37,I37) -> 42879 | L37: C | M37: MNE | N37: 1270 | O37: Offline | P37: 4041 | Q37: 47.45 | R37: 31.79 | S37: =Q37*P37 -> 191745.45 | T37: =R37*P37 -> 128463.39 | U37: =S37-T37 -> 63282.06 | V37: =VLOOKUP(N37,products!A:B,2,0) -> Beverages | W37: Europe | X37: Southern Europe | Y37: =U37/S37 -> 0.33003161 | Z37: =K37-F37 -> 27 | AA37: =WEEKDAY(F37,1) -> 5
A38: 122372519 | B38: 42644 | C38: =IFERROR(__xludf.DUMMYFUNCTION("split(B38,""/"")"),1.0) -> 1 | D38: =IFERROR(__xludf.DUMMYFUNCTION("""COMPUTED_VALUE"""),10.0) -> 10 | E38: =IFERROR(__xludf.DUMMYFUNCTION("""COMPUTED_VALUE"""),2016.0) -> 2016 | F38: =DATE(E38,C38,D38) -> 42379 | G38: 1/13/2016 | H38: =IFERROR(__xludf.DUMMYFUNCTION("split(G38,""/"")"),1.0) -> 1 | I38: =IFERROR(__xludf.DUMMYFUNCTION("""COMPUTED_VALUE"""),13.0) -> 13 | J38: =IFERROR(__xludf.DUMMYFUNCTION("""COMPUTED_VALUE"""),2016.0) -> 2016 | K38: =DATE(J38,H38,I38) -> 42382 | L38: L | M38: PRT | N38: 1270 | O38: Offline | P38: 1603 | Q38: 47.45 | R38: 31.79 | S38: =Q38*P38 -> 76062.35 | T38: =R38*P38 -> 50959.37 | U38: =S38-T38 -> 25102.98 | V38: =VLOOKUP(N38,products!A:B,2,0) -> Beverages | W38: Europe | X38: Southern Europe | Y38: =U38/S38 -> 0.33003161 | Z38: =K38-F38 -> 3 | AA38: =WEEKDAY(F38,1) -> 1
A39: 122967326 | B39: 3/24/2017 | C39: =IFERROR(__xludf.DUMMYFUNCTION("split(B39,""/"")"),3.0) -> 3 | D39: =IFERROR(__xludf.DUMMYFUNCTION("""COMPUTED_VALUE"""),24.0) -> 24 | E39: =IFERROR(__xludf.DUMMYFUNCTION("""COMPUTED_VALUE"""),2017.0) -> 2017 | F39: =DATE(E39,C39,D39) -> 42818 | G39: 4/25/2017 | H39: =IFERROR(__xludf.DUMMYFUNCTION("split(G39,""/"")"),4.0) -> 4 | I39: =IFERROR(__xludf.DUMMYFUNCTION("""COMPUTED_VALUE"""),25.0) -> 25 | J39: =IFERROR(__xludf.DUMMYFUNCTION("""COMPUTED_VALUE"""),2017.0) -> 2017 | K39: =DATE(J39,H39,I39) -> 42850 | L39: H | M39: BLR | N39: 1270 | O39: Online | P39: 7619 | Q39: 47.45 | R39: 31.79 | S39: =Q39*P39 -> 361521.55 | T39: =R39*P39 -> 242208.01 | U39: =S39-T39 -> 119313.54 | V39: =VLOOKUP(N39,products!A:B,2,0) -> Beverages | W39: Europe | X39: Eastern Europe | Y39: =U39/S39 -> 0.33003161 | Z39: =K39-F39 -> 32 | AA39: =WEEKDAY(F39,1) -> 6
A40: 123086202 | B40: 41671 | C40: =IFERROR(__xludf.DUMMYFUNCTION("split(B40,""/"")"),1.0) -> 1 | D40: =IFERROR(__xludf.DUMMYFUNCTION("""COMPUTED_VALUE"""),2.0) -> 2 | E40: =IFERROR(__xludf.DUMMYFUNCTION("""COMPUTED_VALUE"""),2014.0) -> 2014 | F40: =DATE(E40,C40,D40) -> 41641 | G40: 2/20/2014 | H40: =IFERROR(__xludf.DUMMYFUNCTION("split(G40,""/"")"),2.0) -> 2 | I40: =IFERROR(__xludf.DUMMYFUNCTION("""COMPUTED_VALUE"""),20.0) -> 20 | J40: =IFERROR(__xludf.DUMMYFUNCTION("""COMPUTED_VALUE"""),2014.0) -> 2014 | K40: =DATE(J40,H40,I40) -> 41690 | L40: M | M40: EST | N40: 7331 | O40: Offline | P40: 2797 | Q40: 255.28 | R40: 159.42 | S40: =Q40*P40 -> 714018.16 | T40: =R40*P40 -> 445897.74 | U40: =S40-T40 -> 268120.42 | V40: =VLOOKUP(N40,products!A:B,2,0) -> Baby Food | W40: Europe | X40: Northern Europe | Y40: =U40/S40 -> 0.37550924 | Z40: =K40-F40 -> 49 | AA40: =WEEKDAY(F40,1) -> 5
A41: 123544108 | B41: 5/13/2010 | C41: =IFERROR(__xludf.DUMMYFUNCTION("split(B41,""/"")"),5.0) -> 5 | D41: =IFERROR(__xludf.DUMMYFUNCTION("""COMPUTED_VALUE"""),13.0) -> 13 | E41: =IFERROR(__xludf.DUMMYFUNCTION("""COMPUTED_VALUE"""),2010.0) -> 2010 | F41: =DATE(E41,C41,D41) -> 40311 | G41: 6/22/2010 | H41: =IFERROR(__xludf.DUMMYFUNCTION("split(G41,""/"")"),6.0) -> 6 | I41: =IFERROR(__xludf.DUMMYFUNCTION("""COMPUTED_VALUE"""),22.0) -> 22 | J41: =IFERROR(__xludf.DUMMYFUNCTION("""COMPUTED_VALUE"""),2010.0) -> 2010 | K41: =DATE(J41,H41,I41) -> 40351 | L41: M | M41: AUT | N41: 2103 | O41: Online | P41: 8302 | Q41: 205.7 | R41: 117.11 | S41: =Q41*P41 -> 1707721.4 | T41: =R41*P41 -> 972247.22 | U41: =S41-T41 -> 735474.18 | V41: =VLOOKUP(N41,products!A:B,2,0) -> Cereal | W41: Europe | X41: Western Europe | Y41: =U41/S41 -> 0.43067574 | Z41: =K41-F41 -> 40 | AA41: =WEEKDAY(F41,1) -> 5
A42: 123938930 | B42: 7/24/2012 | C42: =IFERROR(__xludf.DUMMYFUNCTION("split(B42,""/"")"),7.0) -> 7 | D42: =IFERROR(__xludf.DUMMYFUNCTION("""COMPUTED_VALUE"""),24.0) -> 24 | E42: =IFERROR(__xludf.DUMMYFUNCTION("""COMPUTED_VALUE"""),2012.0) -> 2012 | F42: =DATE(E42,C42,D42) -> 41114 | G42: 40947 | H42: =IFERROR(__xludf.DUMMYFUNCTION("split(G42,""/"")"),8.0) -> 8 | I42: =IFERROR(__xludf.DUMMYFUNCTION("""COMPUTED_VALUE"""),2.0) -> 2 | J42: =IFERROR(__xludf.DUMMYFUNCTION("""COMPUTED_VALUE"""),2012.0) -> 2012 | K42: =DATE(J42,H42,I42) -> 41123 | L42: M | M42: BLR | N42: 1270 | O42: Online | P42: 5138 | Q42: 47.45 | R42: 31.79 | S42: =Q42*P42 -> 243798.1 | T42: =R42*P42 -> 163337.02 | U42: =S42-T42 -> 80461.08 | V42: =VLOOKUP(N42,products!A:B,2,0) -> Beverages | W42: Europe | X42: Eastern Europe | Y42: =U42/S42 -> 0.33003161 | Z42: =K42-F42 -> 9 | AA42: =WEEKDAY(F42,1) -> 3
A43: 125339686 | B43: 43046 | C43: =IFERROR(__xludf.DUMMYFUNCTION("split(B43,""/"")"),7.0) -> 7 | D43: =IFERROR(__xludf.DUMMYFUNCTION("""COMPUTED_VALUE"""),11.0) -> 11 | E43: =IFERROR(__xludf.DUMMYFUNCTION("""COMPUTED_VALUE"""),2017.0) -> 2017 | F43: =DATE(E43,C43,D43) -> 42927 | G43: 7/24/2017 | H43: =IFERROR(__xludf.DUMMYFUNCTION("split(G43,""/"")"),7.0) -> 7 | I43: =IFERROR(__xludf.DUMMYFUNCTION("""COMPUTED_VALUE"""),24.0) -> 24 | J43: =IFERROR(__xludf.DUMMYFUNCTION("""COMPUTED_VALUE"""),2017.0) -> 2017 | K43: =DATE(J43,H43,I43) -> 42940 | L43: L | M43: MKD | N43: 8969 | O43: Online | P43: 9653 | Q43: 152.58 | R43: 97.44 | S43: =Q43*P43 -> 1472854.7 | T43: =R43*P43 -> 940588.32 | U43: =S43-T43 -> 532266.42 | V43: =VLOOKUP(N43,products!A:B,2,0) -> Snacks | W43: Europe | X43: Southern Europe | Y43: =U43/S43 -> 0.36138419 | Z43: =K43-F43 -> 13 | AA43: =WEEKDAY(F43,1) -> 3
A44: 125349128 | B44: 5/18/2012 | C44: =IFERROR(__xludf.DUMMYFUNCTION("split(B44,""/"")"),5.0) -> 5 | D44: =IFERROR(__xludf.DUMMYFUNCTION("""COMPUTED_VALUE"""),18.0) -> 18 | E44: =IFERROR(__xludf.DUMMYFUNCTION("""COMPUTED_VALUE"""),2012.0) -> 2012 | F44: =DATE(E44,C44,D44) -> 41047 | G44: 41066 | H44: =IFERROR(__xludf.DUMMYFUNCTION("split(G44,""/"")"),6.0) -> 6 | I44: =IFERROR(__xludf.DUMMYFUNCTION("""COMPUTED_VALUE"""),6.0) -> 6 | J44: =IFERROR(__xludf.DUMMYFUNCTION("""COMPUTED_VALUE"""),2012.0) -> 2012 | K44: =DATE(J44,H44,I44) -> 41066 | L44: L | M44: SMR | N44: 2103 | O44: Offline | P44: 2447 | Q44: 205.7 | R44: 117.11 | S44: =Q44*P44 -> 503347.9 | T44: =R44*P44 -> 286568.17 | U44: =S44-T44 -> 216779.73 | V44: =VLOOKUP(N44,products!A:B,2,0) -> Cereal | W44: Europe | X44: Southern Europe | Y44: =U44/S44 -> 0.43067574 | Z44: =K44-F44 -> 19 | AA44: =WEEKDAY(F44,1) -> 6
A45: 126948583 | B45: 5/24/2017 | C45: =IFERROR(__xludf.DUMMYFUNCTION("split(B45,""/"")"),5.0) -> 5 | D45: =IFERROR(__xludf.DUMMYFUNCTION("""COMPUTED_VALUE"""),24.0) -> 24 | E45: =IFERROR(__xludf.DUMMYFUNCTION("""COMPUTED_VALUE"""),2017.0) -> 2017 | F45: =DATE(E45,C45,D45) -> 42879 | G45: 42985 | H45: =IFERROR(__xludf.DUMMYFUNCTION("split(G45,""/"")"),7.0) -> 7 | I45: =IFERROR(__xludf.DUMMYFUNCTION("""COMPUTED_VALUE"""),9.0) -> 9 | J45: =IFERROR(__xludf.DUMMYFUNCTION("""COMPUTED_VALUE"""),2017.0) -> 2017 | K45: =DATE(J45,H45,I45) -> 42925 | L45: C | M45: Desconhecido | N45: 7331 | O45: Online | P45: 5762 | Q45: 255.28 | R45: 159.42 | S45: =Q45*P45 -> 1470923.4 | T45: =R45*P45 -> 918578.04 | U45: =S45-T45 -> 552345.32 | V45: =VLOOKUP(N45,products!A:B,2,0) -> Baby Food | W45: Desconhecido | X45: Desconhecido | Y45: =U45/S45 -> 0.37550924 | Z45: =K45-F45 -> 46 | AA45: =WEEKDAY(F45,1) -> 4
A46: 127694451 | B46: 40736 | C46: =IFERROR(__xludf.DUMMYFUNCTION("split(B46,""/"")"),12.0) -> 12 | D46: =IFERROR(__xludf.DUMMYFUNCTION("""COMPUTED_VALUE"""),7.0) -> 7 | E46: =IFERROR(__xludf.DUMMYFUNCTION("""COMPUTED_VALUE"""),2011.0) -> 2011 | F46: =DATE(E46,C46,D46) -> 40884 | G46: 12/27/2011 | H46: =IFERROR(__xludf.DUMMYFUNCTION("split(G46,""/"")"),12.0) -> 12 | I46: =IFERROR(__xludf.DUMMYFUNCTION("""COMPUTED_VALUE"""),27.0) -> 27 | J46: =IFERROR(__xludf.DUMMYFUNCTION("""COMPUTED_VALUE"""),2011.0) -> 2011 | K46: =DATE(J46,H46,I46) -> 40904 | L46: L | M46: EST | N46: 5988 | O46: Offline | P46: 6481 | Q46: 154.06 | R46: 90.93 | S46: =Q46*P46 -> 998462.86 | T46: =R46*P46 -> 589317.33 | U46: =S46-T46 -> 409145.53 | V46: =VLOOKUP(N46,products!A:B,2,0) -> Vegetables | W46: Europe | X46: Northern Europe | Y46: =U46/S46 -> 0.40977541 | Z46: =K46-F46 -> 20 | AA46: =WEEKDAY(F46,1) -> 4
A47: 127838218 | B47: 9/20/2013 | C47: =IFERROR(__xludf.DUMMYFUNCTION("split(B47,""/"")"),9.0) -> 9 | D47: =IFERROR(__xludf.DUMMYFUNCTION("""COMPUTED_VALUE"""),20.0) -> 20 | E47: =IFERROR(__xludf.DUMMYFUNCTION("""COMPUTED_VALUE"""),2013.0) -> 2013 | F47: =DATE(E47,C47,D47) -> 41537 | G47: 10/29/2013 | H47: =IFERROR(__xludf.DUMMYFUNCTION("split(G47,""/"")"),10.0) -> 10 | I47: =IFERROR(__xludf.DUMMYFUNCTION("""COMPUTED_VALUE"""),29.0) -> 29 | J47: =IFERROR(__xludf.DUMMYFUNCTION("""COMPUTED_VALUE"""),2013.0) -> 2013 | K47: =DATE(J47,H47,I47) -> 41576 | L47: C | M47: NLD | N47: 4594 | O47: Offline | P47: 9024 | Q47: 9.33 | R47: 6.92 | S47: =Q47*P47 -> 84193.92 | T47: =R47*P47 -> 62446.08 | U47: =S47-T47 -> 21747.84 | V47: =VLOOKUP(N47,products!A:B,2,0) -> Fruits | W47: Europe | X47: Western Europe | Y47: =U47/S47 -> 0.25830654 | Z47: =K47-F47 -> 39 | AA47: =WEEKDAY(F47,1) -> 6
A48: 128003442 | B48: 40430 | C48: =IFERROR(__xludf.DUMMYFUNCTION("split(B48,""/"")"),9.0) -> 9 | D48: =IFERROR(__xludf.DUMMYFUNCTION("""COMPUTED_VALUE"""),9.0) -> 9 | E48: =IFERROR(__xludf.DUMMYFUNCTION("""COMPUTED_VALUE"""),2010.0) -> 2010 | F48: =DATE(E48,C48,D48) -> 40430 | G48: 10/23/2010 | H48: =IFERROR(__xludf.DUMMYFUNCTION("split(G48,""/"")"),10.0) -> 10 | I48: =IFERROR(__xludf.DUMMYFUNCTION("""COMPUTED_VALUE"""),23.0) -> 23 | J48: =IFERROR(__xludf.DUMMYFUNCTION("""COMPUTED_VALUE"""),2010.0) -> 2010 | K48: =DATE(J48,H48,I48) -> 40474 | L48: L | M48: CHE | N48: 7331 | O48: Online | P48: 7918 | Q48: 255.28 | R48: 159.42 | S48: =Q48*P48 -> 2021307 | T48: =R48*P48 -> 1262287.6 | U48: =S48-T48 -> 759019.48 | V48: =VLOOKUP(N48,products!A:B,2,0) -> Baby Food | W48: Europe | X48: Western Europe | Y48: =U48/S48 -> 0.37550924 | Z48: =K48-F48 -> 44 | AA48: =WEEKDAY(F48,1) -> 5
A49: 128686225 | B49: 1/25/2011 | C49: =IFERROR(__xludf.DUMMYFUNCTION("split(B49,""/"")"),1.0) -> 1 | D49: =IFERROR(__xludf.DUMMYFUNCTION("""COMPUTED_VALUE"""),25.0) -> 25 | E49: =IFERROR(__xludf.DUMMYFUNCTION("""COMPUTED_VALUE"""),2011.0) -> 2011 | F49: =DATE(E49,C49,D49) -> 40568 | G49: 3/13/2011 | H49: =IFERROR(__xludf.DUMMYFUNCTION("split(G49,""/"")"),3.0) -> 3 | I49: =IFERROR(__xludf.DUMMYFUNCTION("""COMPUTED_VALUE"""),13.0) -> 13 | J49: =IFERROR(__xludf.DUMMYFUNCTION("""COMPUTED_VALUE"""),2011.0) -> 2011 | K49: =DATE(J49,H49,I49) -> 40615 | L49: M | M49: HUN | N49: 7331 | O49: Online | P49: 9968 | Q49: 255.28 | R49: 159.42 | S49: =Q49*P49 -> 2544631 | T49: =R49*P49 -> 1589098.6 | U49: =S49-T49 -> 955532.48 | V49: =VLOOKUP(N49,products!A:B,2,0) -> Baby Food | W49: Europe | X49: Eastern Europe | Y49: =U49/S49 -> 0.37550924 | Z49: =K49-F49 -> 47 | AA49: =WEEKDAY(F49,1) -> 3
A50: 128766906 | B50: 2/13/2011 | C50: =IFERROR(__xludf.DUMMYFUNCTION("split(B50,""/"")"),2.0) -> 2 | D50: =IFERROR(__xludf.DUMMYFUNCTION("""COMPUTED_VALUE"""),13.0) -> 13 | E50: =IFERROR(__xludf.DUMMYFUNCTION("""COMPUTED_VALUE"""),2011.0) -> 2011 | F50: =DATE(E50,C50,D50) -> 40587 | G50: 3/28/2011 | H50: =IFERROR(__xludf.DUMMYFUNCTION("split(G50,""/"")"),3.0) -> 3 | I50: =IFERROR(__xludf.DUMMYFUNCTION("""COMPUTED_VALUE"""),28.0) -> 28 | J50: =IFERROR(__xludf.DUMMYFUNCTION("""COMPUTED_VALUE"""),2011.0) -> 2011 | K50: =DATE(J50,H50,I50) -> 40630 | L50: C | M50: Desconhecido | N50: 7940 | O50: Offline | P50: 3844 | Q50: 668.27 | R50: 502.54 | S50: =Q50*P50 -> 2568829.9 | T50: =R50*P50 -> 1931763.8 | U50: =S50-T50 -> 637066.12 | V50: =VLOOKUP(N50,products!A:B,2,0) -> Household | W50: Desconhecido | X50: Desconhecido | Y50: =U50/S50 -> 0.24799856 | Z50: =K50-F50 -> 43 | AA50: =WEEKDAY(F50,1) -> 1
A51: 129127395 | B51: 6/16/2013 | C51: =IFERROR(__xludf.DUMMYFUNCTION("split(B51,""/"")"),6.0) -> 6 | D51: =IFERROR(__xludf.DUMMYFUNCTION("""COMPUTED_VALUE"""),16.0) -> 16 | E51: =IFERROR(__xludf.DUMMYFUNCTION("""COMPUTED_VALUE"""),2013.0) -> 2013 | F51: =DATE(E51,C51,D51) -> 41441 | G51: 6/20/2013 | H51: =IFERROR(__xludf.DUMMYFUNCTION("split(G51,""/"")"),6.0) -> 6 | I51: =IFERROR(__xludf.DUMMYFUNCTION("""COMPUTED_VALUE"""),20.0) -> 20 | J51: =IFERROR(__xludf.DUMMYFUNCTION("""COMPUTED_VALUE"""),2013.0) -> 2013 | K51: =DATE(J51,H51,I51) -> 41445 | L51: L | M51: LVA | N51: 8681 | O51: Online | P51: 520 | Q51: 651.21 | R51: 524.96 | S51: =Q51*P51 -> 338629.2 | T51: =R51*P51 -> 272979.2 | U51: =S51-T51 -> 65650 | V51: =VLOOKUP(N51,products!A:B,2,0) -> Office Supplies | W51: Europe | X51: Northern Europe | Y51: =U51/S51 -> 0.19386987 | Z51: =K51-F51 -> 4 | AA51: =WEEKDAY(F51,1) -> 1
A52: 129169023 | B52: 41127 | C52: =IFERROR(__xludf.DUMMYFUNCTION("split(B52,""/"")"),6.0) -> 6 | D52: =IFERROR(__xludf.DUMMYFUNCTION("""COMPUTED_VALUE"""),8.0) -> 8 | E52: =IFERROR(__xludf.DUMMYFUNCTION("""COMPUTED_VALUE"""),2012.0) -> 2012 | F52: =DATE(E52,C52,D52) -> 41068 | G52: 7/18/2012 | H52: =IFERROR(__xludf.DUMMYFUNCTION("split(G52,""/"")"),7.0) -> 7 | I52: =IFERROR(__xludf.DUMMYFUNCTION("""COMPUTED_VALUE"""),18.0) -> 18 | J52: =IFERROR(__xludf.DUMMYFUNCTION("""COMPUTED_VALUE"""),2012.0) -> 2012 | K52: =DATE(J52,H52,I52) -> 41108 | L52: M | M52: Desconhecido | N52: 1270 | O52: Offline | P52: 2839 | Q52: 47.45 | R52: 31.79 | S52: =Q52*P52 -> 134710.55 | T52: =R52*P52 -> 90251.81 | U52: =S52-T52 -> 44458.74 | V52: =VLOOKUP(N52,products!A:B,2,0) -> Beverages | W52: Desconhecido | X52: Desconhecido | Y52: =U52/S52 -> 0.33003161 | Z52: =K52-F52 -> 40 | AA52: =WEEKDAY(F52,1) -> 6
A53: 129875409 | B53: 4/19/2011 | C53: =IFERROR(__xludf.DUMMYFUNCTION("split(B53,""/"")"),4.0) -> 4 | D53: =IFERROR(__xludf.DUMMYFUNCTION("""COMPUTED_VALUE"""),19.0) -> 19 | E53: =IFERROR(__xludf.DUMMYFUNCTION("""COMPUTED_VALUE"""),2011.0) -> 2011 | F53: =DATE(E53,C53,D53) -> 40652 | G53: 4/26/2011 | H53: =IFERROR(__xludf.DUMMYFUNCTION("split(G53,""/"")"),4.0) -> 4 | I53: =IFERROR(__xludf.DUMMYFUNCTION("""COMPUTED_VALUE"""),26.0) -> 26 | J53: =IFERROR(__xludf.DUMMYFUNCTION("""COMPUTED_VALUE"""),2011.0) -> 2011 | K53: =DATE(J53,H53,I53) -> 40659 | L53: L | M53: LTU | N53: 3127 | O53: Offline | P53: 1875 | Q53: 81.73 | R53: 56.67 | S53: =Q53*P53 -> 153243.75 | T53: =R53*P53 -> 106256.25 | U53: =S53-T53 -> 46987.5 | V53: =VLOOKUP(N53,products!A:B,2,0) -> Personal Care | W53: Europe | X53: Northern Europe | Y53: =U53/S53 -> 0.30661936 | Z53: =K53-F53 -> 7 | AA53: =WEEKDAY(F53,1) -> 3
A54: 129902875 | B54: 3/21/2014 | C54: =IFERROR(__xludf.DUMMYFUNCTION("split(B54,""/"")"),3.0) -> 3 | D54: =IFERROR(__xludf.DUMMYFUNCTION("""COMPUTED_VALUE"""),21.0) -> 21 | E54: =IFERROR(__xludf.DUMMYFUNCTION("""COMPUTED_VALUE"""),2014.0) -> 2014 | F54: =DATE(E54,C54,D54) -> 41719 | G54: 4/24/2014 | H54: =IFERROR(__xludf.DUMMYFUNCTION("split(G54,""/"")"),4.0) -> 4 | I54: =IFERROR(__xludf.DUMMYFUNCTION("""COMPUTED_VALUE"""),24.0) -> 24 | J54: =IFERROR(__xludf.DUMMYFUNCTION("""COMPUTED_VALUE"""),2014.0) -> 2014 | K54: =DATE(J54,H54,I54) -> 41753 | L54: C | M54: BGR | N54: 7940 | O54: Online | P54: 2 | Q54: 668.27 | R54: 502.54 | S54: =Q54*P54 -> 1336.54 | T54: =R54*P54 -> 1005.08 | U54: =S54-T54 -> 331.46 | V54: =VLOOKUP(N54,products!A:B,2,0) -> Household | W54: Europe | X54: Eastern Europe | Y54: =U54/S54 -> 0.24799856 | Z54: =K54-F54 -> 34 | AA54: =WEEKDAY(F54,1) -> 6
A55: 130356919 | B55: 9/18/2013 | C55: =IFERROR(__xludf.DUMMYFUNCTION("split(B55,""/"")"),9.0) -> 9 | D55: =IFERROR(__xludf.DUMMYFUNCTION("""COMPUTED_VALUE"""),18.0) -> 18 | E55: =IFERROR(__xludf.DUMMYFUNCTION("""COMPUTED_VALUE"""),2013.0) -> 2013 | F55: =DATE(E55,C55,D55) -> 41535 | G55: 41284 | H55: =IFERROR(__xludf.DUMMYFUNCTION("split(G55,""/"")"),10.0) -> 10 | I55: =IFERROR(__xludf.DUMMYFUNCTION("""COMPUTED_VALUE"""),1.0) -> 1 | J55: =IFERROR(__xludf.DUMMYFUNCTION("""COMPUTED_VALUE"""),2013.0) -> 2013 | K55: =DATE(J55,H55,I55) -> 41548 | L55: H | M55: CHE | N55: 5988 | O55: Online | P55: 4364 | Q55: 154.06 | R55: 90.93 | S55: =Q55*P55 -> 672317.84 | T55: =R55*P55 -> 396818.52 | U55: =S55-T55 -> 275499.32 | V55: =VLOOKUP(N55,products!A:B,2,0) -> Vegetables | W55: Europe | X55: Western Europe | Y55: =U55/S55 -> 0.40977541 | Z55: =K55-F55 -> 13 | AA55: =WEEKDAY(F55,1) -> 4
A56: 130754315 | B56: 10/27/2013 | C56: =IFERROR(__xludf.DUMMYFUNCTION("split(B56,""/"")"),10.0) -> 10 | D56: =IFERROR(__xludf.DUMMYFUNCTION("""COMPUTED_VALUE"""),27.0) -> 27 | E56: =IFERROR(__xludf.DUMMYFUNCTION("""COMPUTED_VALUE"""),2013.0) -> 2013 | F56: =DATE(E56,C56,D56) -> 41574 | G56: 41316 | H56: =IFERROR(__xludf.DUMMYFUNCTION("split(G56,""/"")"),11.0) -> 11 | I56: =IFERROR(__xludf.DUMMYFUNCTION("""COMPUTED_VALUE"""),2.0) -> 2 | J56: =IFERROR(__xludf.DUMMYFUNCTION("""COMPUTED_VALUE"""),2013.0) -> 2013 | K56: =DATE(J56,H56,I56) -> 41580 | L56: H | M56: FRA | N56: 8681 | O56: Online | P56: 1962 | Q56: 651.21 | R56: 524.96 | S56: =Q56*P56 -> 1277674 | T56: =R56*P56 -> 1029971.5 | U56: =S56-T56 -> 247702.5 | V56: =VLOOKUP(N56,products!A:B,2,0) -> Office Supplies | W56: Europe | X56: Western Europe | Y56: =U56/S56 -> 0.19386987 | Z56: =K56-F56 -> 6 | AA56: =WEEKDAY(F56,1) -> 1
A57: 131585586 | B57: 3/13/2017 | C57: =IFERROR(__xludf.DUMMYFUNCTION("split(B57,""/"")"),3.0) -> 3 | D57: =IFERROR(__xludf.DUMMYFUNCTION("""COMPUTED_VALUE"""),13.0) -> 13 | E57: =IFERROR(__xludf.DUMMYFUNCTION("""COMPUTED_VALUE"""),2017.0) -> 2017 | F57: =DATE(E57,C57,D57) -> 42807 | G57: 4/13/2017 | H57: =IFERROR(__xludf.DUMMYFUNCTION("split(G57,""/"")"),4.0) -> 4 | I57: =IFERROR(__xludf.DUMMYFUNCTION("""COMPUTED_VALUE"""),13.0) -> 13 | J57: =IFERROR(__xludf.DUMMYFUNCTION("""COMPUTED_VALUE"""),2017.0) -> 2017 | K57: =DATE(J57,H57,I57) -> 42838 | L57: C | M57: FRA | N57: 3127 | O57: Offline | P57: 7954 | Q57: 81.73 | R57: 56.67 | S57: =Q57*P57 -> 650080.42 | T57: =R57*P57 -> 450753.18 | U57: =S57-T57 -> 199327.24 | V57: =VLOOKUP(N57,products!A:B,2,0) -> Personal Care | W57: Europe | X57: Western Europe | Y57: =U57/S57 -> 0.30661936 | Z57: =K57-F57 -> 31 | AA57: =WEEKDAY(F57,1) -> 2
A58: 132069671 | B58: 42985 | C58: =IFERROR(__xludf.DUMMYFUNCTION("split(B58,""/"")"),7.0) -> 7 | D58: =IFERROR(__xludf.DUMMYFUNCTION("""COMPUTED_VALUE"""),9.0) -> 9 | E58: =IFERROR(__xludf.DUMMYFUNCTION("""COMPUTED_VALUE"""),2017.0) -> 2017 | F58: =DATE(E58,C58,D58) -> 42925 | G58: 7/20/2017 | H58: =IFERROR(__xludf.DUMMYFUNCTION("split(G58,""/"")"),7.0) -> 7 | I58: =IFERROR(__xludf.DUMMYFUNCTION("""COMPUTED_VALUE"""),20.0) -> 20 | J58: =IFERROR(__xludf.DUMMYFUNCTION("""COMPUTED_VALUE"""),2017.0) -> 2017 | K58: =DATE(J58,H58,I58) -> 42936 | L58: M | M58: AUT | N58: 3127 | O58: Online | P58: 1205 | Q58: 81.73 | R58: 56.67 | S58: =Q58*P58 -> 98484.65 | T58: =R58*P58 -> 68287.35 | U58: =S58-T58 -> 30197.3 | V58: =VLOOKUP(N58,products!A:B,2,0) -> Personal Care | W58: Europe | X58: Western Europe | Y58: =U58/S58 -> 0.30661936 | Z58: =K58-F58 -> 11 | AA58: =WEEKDAY(F58,1) -> 1
A59: 132603538 | B59: 9/20/2012 | C59: =IFERROR(__xludf.DUMMYFUNCTION("split(B59,""/"")"),9.0) -> 9 | D59: =IFERROR(__xludf.DUMMYFUNCTION("""COMPUTED_VALUE"""),20.0) -> 20 | E59: =IFERROR(__xludf.DUMMYFUNCTION("""COMPUTED_VALUE"""),2012.0) -> 2012 | F59: =DATE(E59,C59,D59) -> 41172 | G59: 41071 | H59: =IFERROR(__xludf.DUMMYFUNCTION("split(G59,""/"")"),11.0) -> 11 | I59: =IFERROR(__xludf.DUMMYFUNCTION("""COMPUTED_VALUE"""),6.0) -> 6 | J59: =IFERROR(__xludf.DUMMYFUNCTION("""COMPUTED_VALUE"""),2012.0) -> 2012 | K59: =DATE(J59,H59,I59) -> 41219 | L59: M | M59: HUN | N59: 8293 | O59: Online | P59: 9188 | Q59: 437.2 | R59: 263.33 | S59: =Q59*P59 -> 4016993.6 | T59: =R59*P59 -> 2419476 | U59: =S59-T59 -> 1597517.6 | V59: =VLOOKUP(N59,products!A:B,2,0) -> Cosmetics | W59: Europe | X59: Eastern Europe | Y59: =U59/S59 -> 0.39768984 | Z59: =K59-F59 -> 47 | AA59: =WEEKDAY(F59,1) -> 5
A60: 133276450 | B60: 1/27/2016 | C60: =IFERROR(__xludf.DUMMYFUNCTION("split(B60,""/"")"),1.0) -> 1 | D60: =IFERROR(__xludf.DUMMYFUNCTION("""COMPUTED_VALUE"""),27.0) -> 27 | E60: =IFERROR(__xludf.DUMMYFUNCTION("""COMPUTED_VALUE"""),2016.0) -> 2016 | F60: =DATE(E60,C60,D60) -> 42396 | G60: 3/15/2016 | H60: =IFERROR(__xludf.DUMMYFUNCTION("split(G60,""/"")"),3.0) -> 3 | I60: =IFERROR(__xludf.DUMMYFUNCTION("""COMPUTED_VALUE"""),15.0) -> 15 | J60: =IFERROR(__xludf.DUMMYFUNCTION("""COMPUTED_VALUE"""),2016.0) -> 2016 | K60: =DATE(J60,H60,I60) -> 42444 | L60: H | M60: Desconhecido | N60: 3127 | O60: Online | P60: 8318 | Q60: 81.73 | R60: 56.67 | S60: =Q60*P60 -> 679830.14 | T60: =R60*P60 -> 471381.06 | U60: =S60-T60 -> 208449.08 | V60: =VLOOKUP(N60,products!A:B,2,0) -> Personal Care | W60: Desconhecido | X60: Desconhecido | Y60: =U60/S60 -> 0.30661936 | Z60: =K60-F60 -> 48 | AA60: =WEEKDAY(F60,1) -> 4
A61: 134121024 | B61: 2/28/2011 | C61: =IFERROR(__xludf.DUMMYFUNCTION("split(B61,""/"")"),2.0) -> 2 | D61: =IFERROR(__xludf.DUMMYFUNCTION("""COMPUTED_VALUE"""),28.0) -> 28 | E61: =IFERROR(__xludf.DUMMYFUNCTION("""COMPUTED_VALUE"""),2011.0) -> 2011 | F61: =DATE(E61,C61,D61) -> 40602 | G61: 40759 | H61: =IFERROR(__xludf.DUMMYFUNCTION("split(G61,""/"")"),4.0) -> 4 | I61: =IFERROR(__xludf.DUMMYFUNCTION("""COMPUTED_VALUE"""),8.0) -> 8 | J61: =IFERROR(__xludf.DUMMYFUNCTION("""COMPUTED_VALUE"""),2011.0) -> 2011 | K61: =DATE(J61,H61,I61) -> 40641 | L61: L | M61: EST | N61: 5988 | O61: Online | P61: 8246 | Q61: 154.06 | R61: 90.93 | S61: =Q61*P61 -> 1270378.8 | T61: =R61*P61 -> 749808.78 | U61: =S61-T61 -> 520569.98 | V61: =VLOOKUP(N61,products!A:B,2,0) -> Vegetables | W61: Europe | X61: Northern Europe | Y61: =U61/S61 -> 0.40977541 | Z61: =K61-F61 -> 39 | AA61: =WEEKDAY(F61,1) -> 2
A62: 134790503 | B62: 40943 | C62: =IFERROR(__xludf.DUMMYFUNCTION("split(B62,""/"")"),4.0) -> 4 | D62: =IFERROR(__xludf.DUMMYFUNCTION("""COMPUTED_VALUE"""),2.0) -> 2 | E62: =IFERROR(__xludf.DUMMYFUNCTION("""COMPUTED_VALUE"""),2012.0) -> 2012 | F62: =DATE(E62,C62,D62) -> 41001 | G62: 4/26/2012 | H62: =IFERROR(__xludf.DUMMYFUNCTION("split(G62,""/"")"),4.0) -> 4 | I62: =IFERROR(__xludf.DUMMYFUNCTION("""COMPUTED_VALUE"""),26.0) -> 26 | J62: =IFERROR(__xludf.DUMMYFUNCTION("""COMPUTED_VALUE"""),2012.0) -> 2012 | K62: =DATE(J62,H62,I62) -> 41025 | L62: M | M62: ITA | N62: 2455 | O62: Online | P62: 6360 | Q62: 109.28 | R62: 35.84 | S62: =Q62*P62 -> 695020.8 | T62: =R62*P62 -> 227942.4 | U62: =S62-T62 -> 467078.4 | V62: =VLOOKUP(N62,products!A:B,2,0) -> Clothes | W62: Europe | X62: Southern Europe | Y62: =U62/S62 -> 0.67203514 | Z62: =K62-F62 -> 24 | AA62: =WEEKDAY(F62,1) -> 2
A63: 136624276 | B63: 2/20/2016 | C63: =IFERROR(__xludf.DUMMYFUNCTION("split(B63,""/"")"),2.0) -> 2 | D63: =IFERROR(__xludf.DUMMYFUNCTION("""COMPUTED_VALUE"""),20.0) -> 20 | E63: =IFERROR(__xludf.DUMMYFUNCTION("""COMPUTED_VALUE"""),2016.0) -> 2016 | F63: =DATE(E63,C63,D63) -> 42420 | G63: 42585 | H63: =IFERROR(__xludf.DUMMYFUNCTION("split(G63,""/"")"),3.0) -> 3 | I63: =IFERROR(__xludf.DUMMYFUNCTION("""COMPUTED_VALUE"""),8.0) -> 8 | J63: =IFERROR(__xludf.DUMMYFUNCTION("""COMPUTED_VALUE"""),2016.0) -> 2016 | K63: =DATE(J63,H63,I63) -> 42437 | L63: L | M63: LVA | N63: 1270 | O63: Offline | P63: 9014 | Q63: 47.45 | R63: 31.79 | S63: =Q63*P63 -> 427714.3 | T63: =R63*P63 -> 286555.06 | U63: =S63-T63 -> 141159.24 | V63: =VLOOKUP(N63,products!A:B,2,0) -> Beverages | W63: Europe | X63: Northern Europe | Y63: =U63/S63 -> 0.33003161 | Z63: =K63-F63 -> 17 | AA63: =WEEKDAY(F63,1) -> 7
A64: 138025033 | B64: 7/13/2013 | C64: =IFERROR(__xludf.DUMMYFUNCTION("split(B64,""/"")"),7.0) -> 7 | D64: =IFERROR(__xludf.DUMMYFUNCTION("""COMPUTED_VALUE"""),13.0) -> 13 | E64: =IFERROR(__xludf.DUMMYFUNCTION("""COMPUTED_VALUE"""),2013.0) -> 2013 | F64: =DATE(E64,C64,D64) -> 41468 | G64: 41341 | H64: =IFERROR(__xludf.DUMMYFUNCTION("split(G64,""/"")"),8.0) -> 8 | I64: =IFERROR(__xludf.DUMMYFUNCTION("""COMPUTED_VALUE"""),3.0) -> 3 | J64: =IFERROR(__xludf.DUMMYFUNCTION("""COMPUTED_VALUE"""),2013.0) -> 2013 | K64: =DATE(J64,H64,I64) -> 41489 | L64: L | M64: GBR | N64: 8969 | O64: Online | P64: 3529 | Q64: 152.58 | R64: 97.44 | S64: =Q64*P64 -> 538454.82 | T64: =R64*P64 -> 343865.76 | U64: =S64-T64 -> 194589.06 | V64: =VLOOKUP(N64,products!A:B,2,0) -> Snacks | W64: Europe | X64: Northern Europe | Y64: =U64/S64 -> 0.36138419 | Z64: =K64-F64 -> 21 | AA64: =WEEKDAY(F64,1) -> 7
A65: 138182103 | B65: 41890 | C65: =IFERROR(__xludf.DUMMYFUNCTION("split(B65,""/"")"),8.0) -> 8 | D65: =IFERROR(__xludf.DUMMYFUNCTION("""COMPUTED_VALUE"""),9.0) -> 9 | E65: =IFERROR(__xludf.DUMMYFUNCTION("""COMPUTED_VALUE"""),2014.0) -> 2014 | F65: =DATE(E65,C65,D65) -> 41860 | G65: 8/16/2014 | H65: =IFERROR(__xludf.DUMMYFUNCTION("split(G65,""/"")"),8.0) -> 8 | I65: =IFERROR(__xludf.DUMMYFUNCTION("""COMPUTED_VALUE"""),16.0) -> 16 | J65: =IFERROR(__xludf.DUMMYFUNCTION("""COMPUTED_VALUE"""),2014.0) -> 2014 | K65: =DATE(J65,H65,I65) -> 41867 | L65: C | M65: NLD | N65: 8681 | O65: Online | P65: 10 | Q65: 651.21 | R65: 524.96 | S65: =Q65*P65 -> 6512.1 | T65: =R65*P65 -> 5249.6 | U65: =S65-T65 -> 1262.5 | V65: =VLOOKUP(N65,products!A:B,2,0) -> Office Supplies | W65: Europe | X65: Western Europe | Y65: =U65/S65 -> 0.19386987 | Z65: =K65-F65 -> 7 | AA65: =WEEKDAY(F65,1) -> 7
A66: 138820683 | B66: 40428 | C66: =IFERROR(__xludf.DUMMYFUNCTION("split(B66,""/"")"),7.0) -> 7 | D66: =IFERROR(__xludf.DUMMYFUNCTION("""COMPUTED_VALUE"""),9.0) -> 9 | E66: =IFERROR(__xludf.DUMMYFUNCTION("""COMPUTED_VALUE"""),2010.0) -> 2010 | F66: =DATE(E66,C66,D66) -> 40368 | G66: 40428 | H66: =IFERROR(__xludf.DUMMYFUNCTION("split(G66,""/"")"),7.0) -> 7 | I66: =IFERROR(__xludf.DUMMYFUNCTION("""COMPUTED_VALUE"""),9.0) -> 9 | J66: =IFERROR(__xludf.DUMMYFUNCTION("""COMPUTED_VALUE"""),2010.0) -> 2010 | K66: =DATE(J66,H66,I66) -> 40368 | L66: L | M66: RUS | N66: 2455 | O66: Offline | P66: 8980 | Q66: 109.28 | R66: 35.84 | S66: =Q66*P66 -> 981334.4 | T66: =R66*P66 -> 321843.2 | U66: =S66-T66 -> 659491.2 | V66: =VLOOKUP(N66,products!A:B,2,0) -> Clothes | W66: Europe | X66: Eastern Europe | Y66: =U66/S66 -> 0.67203514 | Z66: =K66-F66 -> 0 | AA66: =WEEKDAY(F66,1) -> 6
A67: 139201343 | B67: 8/27/2016 | C67: =IFERROR(__xludf.DUMMYFUNCTION("split(B67,""/"")"),8.0) -> 8 | D67: =IFERROR(__xludf.DUMMYFUNCTION("""COMPUTED_VALUE"""),27.0) -> 27 | E67: =IFERROR(__xludf.DUMMYFUNCTION("""COMPUTED_VALUE"""),2016.0) -> 2016 | F67: =DATE(E67,C67,D67) -> 42609 | G67: 42530 | H67: =IFERROR(__xludf.DUMMYFUNCTION("split(G67,""/"")"),9.0) -> 9 | I67: =IFERROR(__xludf.DUMMYFUNCTION("""COMPUTED_VALUE"""),6.0) -> 6 | J67: =IFERROR(__xludf.DUMMYFUNCTION("""COMPUTED_VALUE"""),2016.0) -> 2016 | K67: =DATE(J67,H67,I67) -> 42619 | L67: H | M67: IRL | N67: 8293 | O67: Offline | P67: 1625 | Q67: 437.2 | R67: 263.33 | S67: =Q67*P67 -> 710450 | T67: =R67*P67 -> 427911.25 | U67: =S67-T67 -> 282538.75 | V67: =VLOOKUP(N67,products!A:B,2,0) -> Cosmetics | W67: Europe | X67: Northern Europe | Y67: =U67/S67 -> 0.39768984 | Z67: =K67-F67 -> 10 | AA67: =WEEKDAY(F67,1) -> 7
A68: 139949357 | B68: 41646 | C68: =IFERROR(__xludf.DUMMYFUNCTION("split(B68,""/"")"),7.0) -> 7 | D68: =IFERROR(__xludf.DUMMYFUNCTION("""COMPUTED_VALUE"""),1.0) -> 1 | E68: =IFERROR(__xludf.DUMMYFUNCTION("""COMPUTED_VALUE"""),2014.0) -> 2014 | F68: =DATE(E68,C68,D68) -> 41821 | G68: 7/14/2014 | H68: =IFERROR(__xludf.DUMMYFUNCTION("split(G68,""/"")"),7.0) -> 7 | I68: =IFERROR(__xludf.DUMMYFUNCTION("""COMPUTED_VALUE"""),14.0) -> 14 | J68: =IFERROR(__xludf.DUMMYFUNCTION("""COMPUTED_VALUE"""),2014.0) -> 2014 | K68: =DATE(J68,H68,I68) -> 41834 | L68: H | M68: Desconhecido | N68: 5988 | O68: Online | P68: 2980 | Q68: 154.06 | R68: 90.93 | S68: =Q68*P68 -> 459098.8 | T68: =R68*P68 -> 270971.4 | U68: =S68-T68 -> 188127.4 | V68: =VLOOKUP(N68,products!A:B,2,0) -> Vegetables | W68: Desconhecido | X68: Desconhecido | Y68: =U68/S68 -> 0.40977541 | Z68: =K68-F68 -> 13 | AA68: =WEEKDAY(F68,1) -> 3
A69: 140461766 | B69: 41858 | C69: =IFERROR(__xludf.DUMMYFUNCTION("split(B69,""/"")"),7.0) -> 7 | D69: =IFERROR(__xludf.DUMMYFUNCTION("""COMPUTED_VALUE"""),8.0) -> 8 | E69: =IFERROR(__xludf.DUMMYFUNCTION("""COMPUTED_VALUE"""),2014.0) -> 2014 | F69: =DATE(E69,C69,D69) -> 41828 | G69: 7/20/2014 | H69: =IFERROR(__xludf.DUMMYFUNCTION("split(G69,""/"")"),7.0) -> 7 | I69: =IFERROR(__xludf.DUMMYFUNCTION("""COMPUTED_VALUE"""),20.0) -> 20 | J69: =IFERROR(__xludf.DUMMYFUNCTION("""COMPUTED_VALUE"""),2014.0) -> 2014 | K69: =DATE(J69,H69,I69) -> 41840 | L69: C | M69: UKR | N69: 8293 | O69: Online | P69: 4613 | Q69: 437.2 | R69: 263.33 | S69: =Q69*P69 -> 2016803.6 | T69: =R69*P69 -> 1214741.3 | U69: =S69-T69 -> 802062.31 | V69: =VLOOKUP(N69,products!A:B,2,0) -> Cosmetics | W69: Europe | X69: Eastern Europe | Y69: =U69/S69 -> 0.39768984 | Z69: =K69-F69 -> 12 | AA69: =WEEKDAY(F69,1) -> 3
A70: 140499961 | B70: 3/29/2011 | C70: =IFERROR(__xludf.DUMMYFUNCTION("split(B70,""/"")"),3.0) -> 3 | D70: =IFERROR(__xludf.DUMMYFUNCTION("""COMPUTED_VALUE"""),29.0) -> 29 | E70: =IFERROR(__xludf.DUMMYFUNCTION("""COMPUTED_VALUE"""),2011.0) -> 2011 | F70: =DATE(E70,C70,D70) -> 40631 | G70: 4/30/2011 | H70: =IFERROR(__xludf.DUMMYFUNCTION("split(G70,""/"")"),4.0) -> 4 | I70: =IFERROR(__xludf.DUMMYFUNCTION("""COMPUTED_VALUE"""),30.0) -> 30 | J70: =IFERROR(__xludf.DUMMYFUNCTION("""COMPUTED_VALUE"""),2011.0) -> 2011 | K70: =DATE(J70,H70,I70) -> 40663 | L70: L | M70: LVA | N70: 3127 | O70: Online | P70: 5915 | Q70: 81.73 | R70: 56.67 | S70: =Q70*P70 -> 483432.95 | T70: =R70*P70 -> 335203.05 | U70: =S70-T70 -> 148229.9 | V70: =VLOOKUP(N70,products!A:B,2,0) -> Personal Care | W70: Europe | X70: Northern Europe | Y70: =U70/S70 -> 0.30661936 | Z70: =K70-F70 -> 32 | AA70: =WEEKDAY(F70,1) -> 3
A71: 141764247 | B71: 7/15/2013 | C71: =IFERROR(__xludf.DUMMYFUNCTION("split(B71,""/"")"),7.0) -> 7 | D71: =IFERROR(__xludf.DUMMYFUNCTION("""COMPUTED_VALUE"""),15.0) -> 15 | E71: =IFERROR(__xludf.DUMMYFUNCTION("""COMPUTED_VALUE"""),2013.0) -> 2013 | F71: =DATE(E71,C71,D71) -> 41470 | G71: 8/29/2013 | H71: =IFERROR(__xludf.DUMMYFUNCTION("split(G71,""/"")"),8.0) -> 8 | I71: =IFERROR(__xludf.DUMMYFUNCTION("""COMPUTED_VALUE"""),29.0) -> 29 | J71: =IFERROR(__xludf.DUMMYFUNCTION("""COMPUTED_VALUE"""),2013.0) -> 2013 | K71: =DATE(J71,H71,I71) -> 41515 | L71: H | M71: AND | N71: 7331 | O71: Offline | P71: 46 | Q71: 255.28 | R71: 159.42 | S71: =Q71*P71 -> 11742.88 | T71: =R71*P71 -> 7333.32 | U71: =S71-T71 -> 4409.56 | V71: =VLOOKUP(N71,products!A:B,2,0) -> Baby Food | W71: Europe | X71: Southern Europe | Y71: =U71/S71 -> 0.37550924 | Z71: =K71-F71 -> 45 | AA71: =WEEKDAY(F71,1) -> 2
A72: 141846215 | B72: 7/18/2012 | C72: =IFERROR(__xludf.DUMMYFUNCTION("split(B72,""/"")"),7.0) -> 7 | D72: =IFERROR(__xludf.DUMMYFUNCTION("""COMPUTED_VALUE"""),18.0) -> 18 | E72: =IFERROR(__xludf.DUMMYFUNCTION("""COMPUTED_VALUE"""),2012.0) -> 2012 | F72: =DATE(E72,C72,D72) -> 41108 | G72: 8/16/2012 | H72: =IFERROR(__xludf.DUMMYFUNCTION("split(G72,""/"")"),8.0) -> 8 | I72: =IFERROR(__xludf.DUMMYFUNCTION("""COMPUTED_VALUE"""),16.0) -> 16 | J72: =IFERROR(__xludf.DUMMYFUNCTION("""COMPUTED_VALUE"""),2012.0) -> 2012 | K72: =DATE(J72,H72,I72) -> 41137 | L72: H | M72: GEO | N72: 2455 | O72: Online | P72: 4302 | Q72: 109.28 | R72: 35.84 | S72: =Q72*P72 -> 470122.56 | T72: =R72*P72 -> 154183.68 | U72: =S72-T72 -> 315938.88 | V72: =VLOOKUP(N72,products!A:B,2,0) -> Clothes | W72: Asia | X72: Western Asia | Y72: =U72/S72 -> 0.67203514 | Z72: =K72-F72 -> 29 | AA72: =WEEKDAY(F72,1) -> 4
A73: 141875827 | B73: 3/13/2011 | C73: =IFERROR(__xludf.DUMMYFUNCTION("split(B73,""/"")"),3.0) -> 3 | D73: =IFERROR(__xludf.DUMMYFUNCTION("""COMPUTED_VALUE"""),13.0) -> 13 | E73: =IFERROR(__xludf.DUMMYFUNCTION("""COMPUTED_VALUE"""),2011.0) -> 2011 | F73: =DATE(E73,C73,D73) -> 40615 | G73: 4/16/2011 | H73: =IFERROR(__xludf.DUMMYFUNCTION("split(G73,""/"")"),4.0) -> 4 | I73: =IFERROR(__xludf.DUMMYFUNCTION("""COMPUTED_VALUE"""),16.0) -> 16 | J73: =IFERROR(__xludf.DUMMYFUNCTION("""COMPUTED_VALUE"""),2011.0) -> 2011 | K73: =DATE(J73,H73,I73) -> 40649 | L73: C | M73: POL | N73: 7940 | O73: Online | P73: 3065 | Q73: 668.27 | R73: 502.54 | S73: =Q73*P73 -> 2048247.6 | T73: =R73*P73 -> 1540285.1 | U73: =S73-T73 -> 507962.45 | V73: =VLOOKUP(N73,products!A:B,2,0) -> Household | W73: Europe | X73: Eastern Europe | Y73: =U73/S73 -> 0.24799856 | Z73: =K73-F73 -> 34 | AA73: =WEEKDAY(F73,1) -> 1
A74: 142375361 | B74: 41853 | C74: =IFERROR(__xludf.DUMMYFUNCTION("split(B74,""/"")"),2.0) -> 2 | D74: =IFERROR(__xludf.DUMMYFUNCTION("""COMPUTED_VALUE"""),8.0) -> 8 | E74: =IFERROR(__xludf.DUMMYFUNCTION("""COMPUTED_VALUE"""),2014.0) -> 2014 | F74: =DATE(E74,C74,D74) -> 41678 | G74: 2/19/2014 | H74: =IFERROR(__xludf.DUMMYFUNCTION("split(G74,""/"")"),2.0) -> 2 | I74: =IFERROR(__xludf.DUMMYFUNCTION("""COMPUTED_VALUE"""),19.0) -> 19 | J74: =IFERROR(__xludf.DUMMYFUNCTION("""COMPUTED_VALUE"""),2014.0) -> 2014 | K74: =DATE(J74,H74,I74) -> 41689 | L74: L | M74: LIE | N74: 4594 | O74: Online | P74: 888 | Q74: 9.33 | R74: 6.92 | S74: =Q74*P74 -> 8285.04 | T74: =R74*P74 -> 6144.96 | U74: =S74-T74 -> 2140.08 | V74: =VLOOKUP(N74,products!A:B,2,0) -> Fruits | W74: Europe | X74: Western Europe | Y74: =U74/S74 -> 0.25830654 | Z74: =K74-F74 -> 11 | AA74: =WEEKDAY(F74,1) -> 7
A75: 142987763 | B75: 8/18/2013 | C75: =IFERROR(__xludf.DUMMYFUNCTION("split(B75,""/"")"),8.0) -> 8 | D75: =IFERROR(__xludf.DUMMYFUNCTION("""COMPUTED_VALUE"""),18.0) -> 18 | E75: =IFERROR(__xludf.DUMMYFUNCTION("""COMPUTED_VALUE"""),2013.0) -> 2013 | F75: =DATE(E75,C75,D75) -> 41504 | G75: 41283 | H75: =IFERROR(__xludf.DUMMYFUNCTION("split(G75,""/"")"),9.0) -> 9 | I75: =IFERROR(__xludf.DUMMYFUNCTION("""COMPUTED_VALUE"""),1.0) -> 1 | J75: =IFERROR(__xludf.DUMMYFUNCTION("""COMPUTED_VALUE"""),2013.0) -> 2013 | K75: =DATE(J75,H75,I75) -> 41518 | L75: L | M75: NLD | N75: 7940 | O75: Offline | P75: 2112 | Q75: 668.27 | R75: 502.54 | S75: =Q75*P75 -> 1411386.2 | T75: =R75*P75 -> 1061364.5 | U75: =S75-T75 -> 350021.76 | V75: =VLOOKUP(N75,products!A:B,2,0) -> Household | W75: Europe | X75: Western Europe | Y75: =U75/S75 -> 0.24799856 | Z75: =K75-F75 -> 14 | AA75: =WEEKDAY(F75,1) -> 1
A76: 143414771 | B76: 5/21/2012 | C76: =IFERROR(__xludf.DUMMYFUNCTION("split(B76,""/"")"),5.0) -> 5 | D76: =IFERROR(__xludf.DUMMYFUNCTION("""COMPUTED_VALUE"""),21.0) -> 21 | E76: =IFERROR(__xludf.DUMMYFUNCTION("""COMPUTED_VALUE"""),2012.0) -> 2012 | F76: =DATE(E76,C76,D76) -> 41050 | G76: 40974 | H76: =IFERROR(__xludf.DUMMYFUNCTION("split(G76,""/"")"),6.0) -> 6 | I76: =IFERROR(__xludf.DUMMYFUNCTION("""COMPUTED_VALUE"""),3.0) -> 3 | J76: =IFERROR(__xludf.DUMMYFUNCTION("""COMPUTED_VALUE"""),2012.0) -> 2012 | K76: =DATE(J76,H76,I76) -> 41063 | L76: H | M76: IRL | N76: 7940 | O76: Offline | P76: 8473 | Q76: 668.27 | R76: 502.54 | S76: =Q76*P76 -> 5662251.7 | T76: =R76*P76 -> 4258021.4 | U76: =S76-T76 -> 1404230.3 | V76: =VLOOKUP(N76,products!A:B,2,0) -> Household | W76: Europe | X76: Northern Europe | Y76: =U76/S76 -> 0.24799856 | Z76: =K76-F76 -> 13 | AA76: =WEEKDAY(F76,1) -> 2
A77: 144282948 | B77: 7/13/2013 | C77: =IFERROR(__xludf.DUMMYFUNCTION("split(B77,""/"")"),7.0) -> 7 | D77: =IFERROR(__xludf.DUMMYFUNCTION("""COMPUTED_VALUE"""),13.0) -> 13 | E77: =IFERROR(__xludf.DUMMYFUNCTION("""COMPUTED_VALUE"""),2013.0) -> 2013 | F77: =DATE(E77,C77,D77) -> 41468 | G77: 41282 | H77: =IFERROR(__xludf.DUMMYFUNCTION("split(G77,""/"")"),8.0) -> 8 | I77: =IFERROR(__xludf.DUMMYFUNCTION("""COMPUTED_VALUE"""),1.0) -> 1 | J77: =IFERROR(__xludf.DUMMYFUNCTION("""COMPUTED_VALUE"""),2013.0) -> 2013 | K77: =DATE(J77,H77,I77) -> 41487 | L77: H | M77: FIN | N77: 2103 | O77: Online | P77: 5386 | Q77: 205.7 | R77: 117.11 | S77: =Q77*P77 -> 1107900.2 | T77: =R77*P77 -> 630754.46 | U77: =S77-T77 -> 477145.74 | V77: =VLOOKUP(N77,products!A:B,2,0) -> Cereal | W77: Europe | X77: Northern Europe | Y77: =U77/S77 -> 0.43067574 | Z77: =K77-F77 -> 19 | AA77: =WEEKDAY(F77,1) -> 7
A78: 144743001 | B78: 41611 | C78: =IFERROR(__xludf.DUMMYFUNCTION("split(B78,""/"")"),3.0) -> 3 | D78: =IFERROR(__xludf.DUMMYFUNCTION("""COMPUTED_VALUE"""),12.0) -> 12 | E78: =IFERROR(__xludf.DUMMYFUNCTION("""COMPUTED_VALUE"""),2013.0) -> 2013 | F78: =DATE(E78,C78,D78) -> 41345 | G78: 4/21/2013 | H78: =IFERROR(__xludf.DUMMYFUNCTION("split(G78,""/"")"),4.0) -> 4 | I78: =IFERROR(__xludf.DUMMYFUNCTION("""COMPUTED_VALUE"""),21.0) -> 21 | J78: =IFERROR(__xludf.DUMMYFUNCTION("""COMPUTED_VALUE"""),2013.0) -> 2013 | K78: =DATE(J78,H78,I78) -> 41385 | L78: M | M78: SVN | N78: 7331 | O78: Offline | P78: 1525 | Q78: 255.28 | R78: 159.42 | S78: =Q78*P78 -> 389302 | T78: =R78*P78 -> 243115.5 | U78: =S78-T78 -> 146186.5 | V78: =VLOOKUP(N78,products!A:B,2,0) -> Baby Food | W78: Europe | X78: Southern Europe | Y78: =U78/S78 -> 0.37550924 | Z78: =K78-F78 -> 40 | AA78: =WEEKDAY(F78,1) -> 3
A79: 144978606 | B79: 40695 | C79: =IFERROR(__xludf.DUMMYFUNCTION("split(B79,""/"")"),1.0) -> 1 | D79: =IFERROR(__xludf.DUMMYFUNCTION("""COMPUTED_VALUE"""),6.0) -> 6 | E79: =IFERROR(__xludf.DUMMYFUNCTION("""COMPUTED_VALUE"""),2011.0) -> 2011 | F79: =DATE(E79,C79,D79) -> 40549 | G79: 2/19/2011 | H79: =IFERROR(__xludf.DUMMYFUNCTION("split(G79,""/"")"),2.0) -> 2 | I79: =IFERROR(__xludf.DUMMYFUNCTION("""COMPUTED_VALUE"""),19.0) -> 19 | J79: =IFERROR(__xludf.DUMMYFUNCTION("""COMPUTED_VALUE"""),2011.0) -> 2011 | K79: =DATE(J79,H79,I79) -> 40593 | L79: C | M79: IRL | N79: 8681 | O79: Online | P79: 1246 | Q79: 651.21 | R79: 524.96 | S79: =Q79*P79 -> 811407.66 | T79: =R79*P79 -> 654100.16 | U79: =S79-T79 -> 157307.5 | V79: =VLOOKUP(N79,products!A:B,2,0) -> Office Supplies | W79: Europe | X79: Northern Europe | Y79: =U79/S79 -> 0.19386987 | Z79: =K79-F79 -> 44 | AA79: =WEEKDAY(F79,1) -> 5
A80: 146349751 | B80: 42740 | C80: =IFERROR(__xludf.DUMMYFUNCTION("split(B80,""/"")"),5.0) -> 5 | D80: =IFERROR(__xludf.DUMMYFUNCTION("""COMPUTED_VALUE"""),1.0) -> 1 | E80: =IFERROR(__xludf.DUMMYFUNCTION("""COMPUTED_VALUE"""),2017.0) -> 2017 | F80: =DATE(E80,C80,D80) -> 42856 | G80: 6/13/2017 | H80: =IFERROR(__xludf.DUMMYFUNCTION("split(G80,""/"")"),6.0) -> 6 | I80: =IFERROR(__xludf.DUMMYFUNCTION("""COMPUTED_VALUE"""),13.0) -> 13 | J80: =IFERROR(__xludf.DUMMYFUNCTION("""COMPUTED_VALUE"""),2017.0) -> 2017 | K80: =DATE(J80,H80,I80) -> 42899 | L80: M | M80: LTU | N80: 5988 | O80: Online | P80: 6999 | Q80: 154.06 | R80: 90.93 | S80: =Q80*P80 -> 1078265.9 | T80: =R80*P80 -> 636419.07 | U80: =S80-T80 -> 441846.87 | V80: =VLOOKUP(N80,products!A:B,2,0) -> Vegetables | W80: Europe | X80: Northern Europe | Y80: =U80/S80 -> 0.40977541 | Z80: =K80-F80 -> 43 | AA80: =WEEKDAY(F80,1) -> 2
A81: 146545875 | B81: 11/27/2011 | C81: =IFERROR(__xludf.DUMMYFUNCTION("split(B81,""/"")"),11.0) -> 11 | D81: =IFERROR(__xludf.DUMMYFUNCTION("""COMPUTED_VALUE"""),27.0) -> 27 | E81: =IFERROR(__xludf.DUMMYFUNCTION("""COMPUTED_VALUE"""),2011.0) -> 2011 | F81: =DATE(E81,C81,D81) -> 40874 | G81: 41091 | H81: =IFERROR(__xludf.DUMMYFUNCTION("split(G81,""/"")"),1.0) -> 1 | I81: =IFERROR(__xludf.DUMMYFUNCTION("""COMPUTED_VALUE"""),7.0) -> 7 | J81: =IFERROR(__xludf.DUMMYFUNCTION("""COMPUTED_VALUE"""),2012.0) -> 2012 | K81: =DATE(J81,H81,I81) -> 40915 | L81: M | M81: SVK | N81: 8293 | O81: Offline | P81: 5036 | Q81: 437.2 | R81: 263.33 | S81: =Q81*P81 -> 2201739.2 | T81: =R81*P81 -> 1326129.9 | U81: =S81-T81 -> 875609.32 | V81: =VLOOKUP(N81,products!A:B,2,0) -> Cosmetics | W81: Europe | X81: Eastern Europe | Y81: =U81/S81 -> 0.39768984 | Z81: =K81-F81 -> 41 | AA81: =WEEKDAY(F81,1) -> 1
A82: 147826898 | B82: 9/29/2015 | C82: =IFERROR(__xludf.DUMMYFUNCTION("split(B82,""/"")"),9.0) -> 9 | D82: =IFERROR(__xludf.DUMMYFUNCTION("""COMPUTED_VALUE"""),29.0) -> 29 | E82: =IFERROR(__xludf.DUMMYFUNCTION("""COMPUTED_VALUE"""),2015.0) -> 2015 | F82: =DATE(E82,C82,D82) -> 42276 | G82: 42135 | H82: =IFERROR(__xludf.DUMMYFUNCTION("split(G82,""/"")"),11.0) -> 11 | I82: =IFERROR(__xludf.DUMMYFUNCTION("""COMPUTED_VALUE"""),5.0) -> 5 | J82: =IFERROR(__xludf.DUMMYFUNCTION("""COMPUTED_VALUE"""),2015.0) -> 2015 | K82: =DATE(J82,H82,I82) -> 42313 | L82: M | M82: BEL | N82: 8293 | O82: Online | P82: 4119 | Q82: 437.2 | R82: 263.33 | S82: =Q82*P82 -> 1800826.8 | T82: =R82*P82 -> 1084656.3 | U82: =S82-T82 -> 716170.53 | V82: =VLOOKUP(N82,products!A:B,2,0) -> Cosmetics | W82: Europe | X82: Western Europe | Y82: =U82/S82 -> 0.39768984 | Z82: =K82-F82 -> 37 | AA82: =WEEKDAY(F82,1) -> 3
A83: 148894631 | B83: 9/19/2013 | C83: =IFERROR(__xludf.DUMMYFUNCTION("split(B83,""/"")"),9.0) -> 9 | D83: =IFERROR(__xludf.DUMMYFUNCTION("""COMPUTED_VALUE"""),19.0) -> 19 | E83: =IFERROR(__xludf.DUMMYFUNCTION("""COMPUTED_VALUE"""),2013.0) -> 2013 | F83: =DATE(E83,C83,D83) -> 41536 | G83: 9/25/2013 | H83: =IFERROR(__xludf.DUMMYFUNCTION("split(G83,""/"")"),9.0) -> 9 | I83: =IFERROR(__xludf.DUMMYFUNCTION("""COMPUTED_VALUE"""),25.0) -> 25 | J83: =IFERROR(__xludf.DUMMYFUNCTION("""COMPUTED_VALUE"""),2013.0) -> 2013 | K83: =DATE(J83,H83,I83) -> 41542 | L83: H | M83: POL | N83: 8681 | O83: Online | P83: 85 | Q83: 651.21 | R83: 524.96 | S83: =Q83*P83 -> 55352.85 | T83: =R83*P83 -> 44621.6 | U83: =S83-T83 -> 10731.25 | V83: =VLOOKUP(N83,products!A:B,2,0) -> Office Supplies | W83: Europe | X83: Eastern Europe | Y83: =U83/S83 -> 0.19386987 | Z83: =K83-F83 -> 6 | AA83: =WEEKDAY(F83,1) -> 5
A84: 149274003 | B84: 4/29/2013 | C84: =IFERROR(__xludf.DUMMYFUNCTION("split(B84,""/"")"),4.0) -> 4 | D84: =IFERROR(__xludf.DUMMYFUNCTION("""COMPUTED_VALUE"""),29.0) -> 29 | E84: =IFERROR(__xludf.DUMMYFUNCTION("""COMPUTED_VALUE"""),2013.0) -> 2013 | F84: =DATE(E84,C84,D84) -> 41393 | G84: 5/29/2013 | H84: =IFERROR(__xludf.DUMMYFUNCTION("split(G84,""/"")"),5.0) -> 5 | I84: =IFERROR(__xludf.DUMMYFUNCTION("""COMPUTED_VALUE"""),29.0) -> 29 | J84: =IFERROR(__xludf.DUMMYFUNCTION("""COMPUTED_VALUE"""),2013.0) -> 2013 | K84: =DATE(J84,H84,I84) -> 41423 | L84: C | M84: NOR | N84: 7940 | O84: Offline | P84: 2350 | Q84: 668.27 | R84: 502.54 | S84: =Q84*P84 -> 1570434.5 | T84: =R84*P84 -> 1180969 | U84: =S84-T84 -> 389465.5 | V84: =VLOOKUP(N84,products!A:B,2,0) -> Household | W84: Europe | X84: Northern Europe | Y84: =U84/S84 -> 0.24799856 | Z84: =K84-F84 -> 30 | AA84: =WEEKDAY(F84,1) -> 2
A85: 150293242 | B85: 5/19/2015 | C85: =IFERROR(__xludf.DUMMYFUNCTION("split(B85,""/"")"),5.0) -> 5 | D85: =IFERROR(__xludf.DUMMYFUNCTION("""COMPUTED_VALUE"""),19.0) -> 19 | E85: =IFERROR(__xludf.DUMMYFUNCTION("""COMPUTED_VALUE"""),2015.0) -> 2015 | F85: =DATE(E85,C85,D85) -> 42143 | G85: 6/21/2015 | H85: =IFERROR(__xludf.DUMMYFUNCTION("split(G85,""/"")"),6.0) -> 6 | I85: =IFERROR(__xludf.DUMMYFUNCTION("""COMPUTED_VALUE"""),21.0) -> 21 | J85: =IFERROR(__xludf.DUMMYFUNCTION("""COMPUTED_VALUE"""),2015.0) -> 2015 | K85: =DATE(J85,H85,I85) -> 42176 | L85: H | M85: Desconhecido | N85: 8681 | O85: Offline | P85: 3965 | Q85: 651.21 | R85: 524.96 | S85: =Q85*P85 -> 2582047.6 | T85: =R85*P85 -> 2081466.4 | U85: =S85-T85 -> 500581.25 | V85: =VLOOKUP(N85,products!A:B,2,0) -> Office Supplies | W85: Desconhecido | X85: Desconhecido | Y85: =U85/S85 -> 0.19386987 | Z85: =K85-F85 -> 33 | AA85: =WEEKDAY(F85,1) -> 3
A86: 151312482 | B86: 42892 | C86: =IFERROR(__xludf.DUMMYFUNCTION("split(B86,""/"")"),6.0) -> 6 | D86: =IFERROR(__xludf.DUMMYFUNCTION("""COMPUTED_VALUE"""),6.0) -> 6 | E86: =IFERROR(__xludf.DUMMYFUNCTION("""COMPUTED_VALUE"""),2017.0) -> 2017 | F86: =DATE(E86,C86,D86) -> 42892 | G86: 43076 | H86: =IFERROR(__xludf.DUMMYFUNCTION("split(G86,""/"")"),7.0) -> 7 | I86: =IFERROR(__xludf.DUMMYFUNCTION("""COMPUTED_VALUE"""),12.0) -> 12 | J86: =IFERROR(__xludf.DUMMYFUNCTION("""COMPUTED_VALUE"""),2017.0) -> 2017 | K86: =DATE(J86,H86,I86) -> 42928 | L86: H | M86: CZE | N86: 8293 | O86: Online | P86: 5581 | Q86: 437.2 | R86: 263.33 | S86: =Q86*P86 -> 2440013.2 | T86: =R86*P86 -> 1469644.7 | U86: =S86-T86 -> 970368.47 | V86: =VLOOKUP(N86,products!A:B,2,0) -> Cosmetics | W86: Europe | X86: Eastern Europe | Y86: =U86/S86 -> 0.39768984 | Z86: =K86-F86 -> 36 | AA86: =WEEKDAY(F86,1) -> 3
A87: 152191388 | B87: 5/18/2012 | C87: =IFERROR(__xludf.DUMMYFUNCTION("split(B87,""/"")"),5.0) -> 5 | D87: =IFERROR(__xludf.DUMMYFUNCTION("""COMPUTED_VALUE"""),18.0) -> 18 | E87: =IFERROR(__xludf.DUMMYFUNCTION("""COMPUTED_VALUE"""),2012.0) -> 2012 | F87: =DATE(E87,C87,D87) -> 41047 | G87: 6/22/2012 | H87: =IFERROR(__xludf.DUMMYFUNCTION("split(G87,""/"")"),6.0) -> 6 | I87: =IFERROR(__xludf.DUMMYFUNCTION("""COMPUTED_VALUE"""),22.0) -> 22 | J87: =IFERROR(__xludf.DUMMYFUNCTION("""COMPUTED_VALUE"""),2012.0) -> 2012 | K87: =DATE(J87,H87,I87) -> 41082 | L87: L | M87: ALB | N87: 7331 | O87: Offline | P87: 5669 | Q87: 255.28 | R87: 159.42 | S87: =Q87*P87 -> 1447182.3 | T87: =R87*P87 -> 903751.98 | U87: =S87-T87 -> 543430.34 | V87: =VLOOKUP(N87,products!A:B,2,0) -> Baby Food | W87: Europe | X87: Southern Europe | Y87: =U87/S87 -> 0.37550924 | Z87: =K87-F87 -> 35 | AA87: =WEEKDAY(F87,1) -> 6
A88: 152411115 | B88: 41365 | C88: =IFERROR(__xludf.DUMMYFUNCTION("split(B88,""/"")"),1.0) -> 1 | D88: =IFERROR(__xludf.DUMMYFUNCTION("""COMPUTED_VALUE"""),4.0) -> 4 | E88: =IFERROR(__xludf.DUMMYFUNCTION("""COMPUTED_VALUE"""),2013.0) -> 2013 | F88: =DATE(E88,C88,D88) -> 41278 | G88: 2/21/2013 | H88: =IFERROR(__xludf.DUMMYFUNCTION("split(G88,""/"")"),2.0) -> 2 | I88: =IFERROR(__xludf.DUMMYFUNCTION("""COMPUTED_VALUE"""),21.0) -> 21 | J88: =IFERROR(__xludf.DUMMYFUNCTION("""COMPUTED_VALUE"""),2013.0) -> 2013 | K88: =DATE(J88,H88,I88) -> 41326 | L88: H | M88: SWE | N88: 8875 | O88: Online | P88: 691 | Q88: 421.89 | R88: 364.69 | S88: =Q88*P88 -> 291525.99 | T88: =R88*P88 -> 252000.79 | U88: =S88-T88 -> 39525.2 | V88: =VLOOKUP(N88,products!A:B,2,0) -> Meat | W88: Europe | X88: Northern Europe | Y88: =U88/S88 -> 0.13558036 | Z88: =K88-F88 -> 48 | AA88: =WEEKDAY(F88,1) -> 6
A89: 152505099 | B89: 41095 | C89: =IFERROR(__xludf.DUMMYFUNCTION("split(B89,""/"")"),5.0) -> 5 | D89: =IFERROR(__xludf.DUMMYFUNCTION("""COMPUTED_VALUE"""),7.0) -> 7 | E89: =IFERROR(__xludf.DUMMYFUNCTION("""COMPUTED_VALUE"""),2012.0) -> 2012 | F89: =DATE(E89,C89,D89) -> 41036 | G89: 5/19/2012 | H89: =IFERROR(__xludf.DUMMYFUNCTION("split(G89,""/"")"),5.0) -> 5 | I89: =IFERROR(__xludf.DUMMYFUNCTION("""COMPUTED_VALUE"""),19.0) -> 19 | J89: =IFERROR(__xludf.DUMMYFUNCTION("""COMPUTED_VALUE"""),2012.0) -> 2012 | K89: =DATE(J89,H89,I89) -> 41048 | L89: M | M89: SMR | N89: 2455 | O89: Offline | P89: 8503 | Q89: 109.28 | R89: 35.84 | S89: =Q89*P89 -> 929207.84 | T89: =R89*P89 -> 304747.52 | U89: =S89-T89 -> 624460.32 | V89: =VLOOKUP(N89,products!A:B,2,0) -> Clothes | W89: Europe | X89: Southern Europe | Y89: =U89/S89 -> 0.67203514 | Z89: =K89-F89 -> 12 | AA89: =WEEKDAY(F89,1) -> 2
A90: 152746713 | B90: 40214 | C90: =IFERROR(__xludf.DUMMYFUNCTION("split(B90,""/"")"),5.0) -> 5 | D90: =IFERROR(__xludf.DUMMYFUNCTION("""COMPUTED_VALUE"""),2.0) -> 2 | E90: =IFERROR(__xludf.DUMMYFUNCTION("""COMPUTED_VALUE"""),2010.0) -> 2010 | F90: =DATE(E90,C90,D90) -> 40300 | G90: 40395 | H90: =IFERROR(__xludf.DUMMYFUNCTION("split(G90,""/"")"),5.0) -> 5 | I90: =IFERROR(__xludf.DUMMYFUNCTION("""COMPUTED_VALUE"""),8.0) -> 8 | J90: =IFERROR(__xludf.DUMMYFUNCTION("""COMPUTED_VALUE"""),2010.0) -> 2010 | K90: =DATE(J90,H90,I90) -> 40306 | L90: C | M90: BIH | N90: 8681 | O90: Offline | P90: 2 | Q90: 651.21 | R90: 524.96 | S90: =Q90*P90 -> 1302.42 | T90: =R90*P90 -> 1049.92 | U90: =S90-T90 -> 252.5 | V90: =VLOOKUP(N90,products!A:B,2,0) -> Office Supplies | W90: Europe | X90: Southern Europe | Y90: =U90/S90 -> 0.19386987 | Z90: =K90-F90 -> 6 | AA90: =WEEKDAY(F90,1) -> 1
A91: 153974950 | B91: 8/22/2011 | C91: =IFERROR(__xludf.DUMMYFUNCTION("split(B91,""/"")"),8.0) -> 8 | D91: =IFERROR(__xludf.DUMMYFUNCTION("""COMPUTED_VALUE"""),22.0) -> 22 | E91: =IFERROR(__xludf.DUMMYFUNCTION("""COMPUTED_VALUE"""),2011.0) -> 2011 | F91: =DATE(E91,C91,D91) -> 40777 | G91: 9/20/2011 | H91: =IFERROR(__xludf.DUMMYFUNCTION("split(G91,""/"")"),9.0) -> 9 | I91: =IFERROR(__xludf.DUMMYFUNCTION("""COMPUTED_VALUE"""),20.0) -> 20 | J91: =IFERROR(__xludf.DUMMYFUNCTION("""COMPUTED_VALUE"""),2011.0) -> 2011 | K91: =DATE(J91,H91,I91) -> 40806 | L91: L | M91: SWE | N91: 4594 | O91: Offline | P91: 3464 | Q91: 9.33 | R91: 6.92 | S91: =Q91*P91 -> 32319.12 | T91: =R91*P91 -> 23970.88 | U91: =S91-T91 -> 8348.24 | V91: =VLOOKUP(N91,products!A:B,2,0) -> Fruits | W91: Europe | X91: Northern Europe | Y91: =U91/S91 -> 0.25830654 | Z91: =K91-F91 -> 29 | AA91: =WEEKDAY(F91,1) -> 2
A92: 155086886 | B92: 1/28/2014 | C92: =IFERROR(__xludf.DUMMYFUNCTION("split(B92,""/"")"),1.0) -> 1 | D92: =IFERROR(__xludf.DUMMYFUNCTION("""COMPUTED_VALUE"""),28.0) -> 28 | E92: =IFERROR(__xludf.DUMMYFUNCTION("""COMPUTED_VALUE"""),2014.0) -> 2014 | F92: =DATE(E92,C92,D92) -> 41667 | G92: 41761 | H92: =IFERROR(__xludf.DUMMYFUNCTION("split(G92,""/"")"),2.0) -> 2 | I92: =IFERROR(__xludf.DUMMYFUNCTION("""COMPUTED_VALUE"""),5.0) -> 5 | J92: =IFERROR(__xludf.DUMMYFUNCTION("""COMPUTED_VALUE"""),2014.0) -> 2014 | K92: =DATE(J92,H92,I92) -> 41675 | L92: M | M92: SVN | N92: 8293 | O92: Offline | P92: 2511 | Q92: 437.2 | R92: 263.33 | S92: =Q92*P92 -> 1097809.2 | T92: =R92*P92 -> 661221.63 | U92: =S92-T92 -> 436587.57 | V92: =VLOOKUP(N92,products!A:B,2,0) -> Cosmetics | W92: Europe | X92: Southern Europe | Y92: =U92/S92 -> 0.39768984 | Z92: =K92-F92 -> 8 | AA92: =WEEKDAY(F92,1) -> 3
A93: 155914723 | B93: 42341 | C93: =IFERROR(__xludf.DUMMYFUNCTION("split(B93,""/"")"),3.0) -> 3 | D93: =IFERROR(__xludf.DUMMYFUNCTION("""COMPUTED_VALUE"""),12.0) -> 12 | E93: =IFERROR(__xludf.DUMMYFUNCTION("""COMPUTED_VALUE"""),2015.0) -> 2015 | F93: =DATE(E93,C93,D93) -> 42075 | G93: 3/29/2015 | H93: =IFERROR(__xludf.DUMMYFUNCTION("split(G93,""/"")"),3.0) -> 3 | I93: =IFERROR(__xludf.DUMMYFUNCTION("""COMPUTED_VALUE"""),29.0) -> 29 | J93: =IFERROR(__xludf.DUMMYFUNCTION("""COMPUTED_VALUE"""),2015.0) -> 2015 | K93: =DATE(J93,H93,I93) -> 42092 | L93: H | M93: IRL | N93: 4594 | O93: Offline | P93: 7486 | Q93: 9.33 | R93: 6.92 | S93: =Q93*P93 -> 69844.38 | T93: =R93*P93 -> 51803.12 | U93: =S93-T93 -> 18041.26 | V93: =VLOOKUP(N93,products!A:B,2,0) -> Fruits | W93: Europe | X93: Northern Europe | Y93: =U93/S93 -> 0.25830654 | Z93: =K93-F93 -> 17 | AA93: =WEEKDAY(F93,1) -> 5
A94: 156158483 | B94: 6/26/2016 | C94: =IFERROR(__xludf.DUMMYFUNCTION("split(B94,""/"")"),6.0) -> 6 | D94: =IFERROR(__xludf.DUMMYFUNCTION("""COMPUTED_VALUE"""),26.0) -> 26 | E94: =IFERROR(__xludf.DUMMYFUNCTION("""COMPUTED_VALUE"""),2016.0) -> 2016 | F94: =DATE(E94,C94,D94) -> 42547 | G94: 42498 | H94: =IFERROR(__xludf.DUMMYFUNCTION("split(G94,""/"")"),8.0) -> 8 | I94: =IFERROR(__xludf.DUMMYFUNCTION("""COMPUTED_VALUE"""),5.0) -> 5 | J94: =IFERROR(__xludf.DUMMYFUNCTION("""COMPUTED_VALUE"""),2016.0) -> 2016 | K94: =DATE(J94,H94,I94) -> 42587 | L94: C | M94: LTU | N94: 2455 | O94: Offline | P94: 9620 | Q94: 109.28 | R94: 35.84 | S94: =Q94*P94 -> 1051273.6 | T94: =R94*P94 -> 344780.8 | U94: =S94-T94 -> 706492.8 | V94: =VLOOKUP(N94,products!A:B,2,0) -> Clothes | W94: Europe | X94: Northern Europe | Y94: =U94/S94 -> 0.67203514 | Z94: =K94-F94 -> 40 | AA94: =WEEKDAY(F94,1) -> 1
A95: 158479773 | B95: 5/19/2015 | C95: =IFERROR(__xludf.DUMMYFUNCTION("split(B95,""/"")"),5.0) -> 5 | D95: =IFERROR(__xludf.DUMMYFUNCTION("""COMPUTED_VALUE"""),19.0) -> 19 | E95: =IFERROR(__xludf.DUMMYFUNCTION("""COMPUTED_VALUE"""),2015.0) -> 2015 | F95: =DATE(E95,C95,D95) -> 42143 | G95: 6/18/2015 | H95: =IFERROR(__xludf.DUMMYFUNCTION("split(G95,""/"")"),6.0) -> 6 | I95: =IFERROR(__xludf.DUMMYFUNCTION("""COMPUTED_VALUE"""),18.0) -> 18 | J95: =IFERROR(__xludf.DUMMYFUNCTION("""COMPUTED_VALUE"""),2015.0) -> 2015 | K95: =DATE(J95,H95,I95) -> 42173 | L95: L | M95: RUS | N95: 7331 | O95: Offline | P95: 6542 | Q95: 255.28 | R95: 159.42 | S95: =Q95*P95 -> 1670041.8 | T95: =R95*P95 -> 1042925.6 | U95: =S95-T95 -> 627116.12 | V95: =VLOOKUP(N95,products!A:B,2,0) -> Baby Food | W95: Europe | X95: Eastern Europe | Y95: =U95/S95 -> 0.37550924 | Z95: =K95-F95 -> 30 | AA95: =WEEKDAY(F95,1) -> 3
A96: 158673751 | B96: 3/22/2014 | C96: =IFERROR(__xludf.DUMMYFUNCTION("split(B96,""/"")"),3.0) -> 3 | D96: =IFERROR(__xludf.DUMMYFUNCTION("""COMPUTED_VALUE"""),22.0) -> 22 | E96: =IFERROR(__xludf.DUMMYFUNCTION("""COMPUTED_VALUE"""),2014.0) -> 2014 | F96: =DATE(E96,C96,D96) -> 41720 | G96: 41917 | H96: =IFERROR(__xludf.DUMMYFUNCTION("split(G96,""/"")"),5.0) -> 5 | I96: =IFERROR(__xludf.DUMMYFUNCTION("""COMPUTED_VALUE"""),10.0) -> 10 | J96: =IFERROR(__xludf.DUMMYFUNCTION("""COMPUTED_VALUE"""),2014.0) -> 2014 | K96: =DATE(J96,H96,I96) -> 41769 | L96: H | M96: DEU | N96: 8969 | O96: Online | P96: 3944 | Q96: 152.58 | R96: 97.44 | S96: =Q96*P96 -> 601775.52 | T96: =R96*P96 -> 384303.36 | U96: =S96-T96 -> 217472.16 | V96: =VLOOKUP(N96,products!A:B,2,0) -> Snacks | W96: Europe | X96: Western Europe | Y96: =U96/S96 -> 0.36138419 | Z96: =K96-F96 -> 49 | AA96: =WEEKDAY(F96,1) -> 7
A97: 159232509 | B97: 41857 | C97: =IFERROR(__xludf.DUMMYFUNCTION("split(B97,""/"")"),6.0) -> 6 | D97: =IFERROR(__xludf.DUMMYFUNCTION("""COMPUTED_VALUE"""),8.0) -> 8 | E97: =IFERROR(__xludf.DUMMYFUNCTION("""COMPUTED_VALUE"""),2014.0) -> 2014 | F97: =DATE(E97,C97,D97) -> 41798 | G97: 7/14/2014 | H97: =IFERROR(__xludf.DUMMYFUNCTION("split(G97,""/"")"),7.0) -> 7 | I97: =IFERROR(__xludf.DUMMYFUNCTION("""COMPUTED_VALUE"""),14.0) -> 14 | J97: =IFERROR(__xludf.DUMMYFUNCTION("""COMPUTED_VALUE"""),2014.0) -> 2014 | K97: =DATE(J97,H97,I97) -> 41834 | L97: H | M97: CHE | N97: 4594 | O97: Online | P97: 9293 | Q97: 9.33 | R97: 6.92 | S97: =Q97*P97 -> 86703.69 | T97: =R97*P97 -> 64307.56 | U97: =S97-T97 -> 22396.13 | V97: =VLOOKUP(N97,products!A:B,2,0) -> Fruits | W97: Europe | X97: Western Europe | Y97: =U97/S97 -> 0.25830654 | Z97: =K97-F97 -> 36 | AA97: =WEEKDAY(F97,1) -> 1
A98: 159805858 | B98: 11/19/2012 | C98: =IFERROR(__xludf.DUMMYFUNCTION("split(B98,""/"")"),11.0) -> 11 | D98: =IFERROR(__xludf.DUMMYFUNCTION("""COMPUTED_VALUE"""),19.0) -> 19 | E98: =IFERROR(__xludf.DUMMYFUNCTION("""COMPUTED_VALUE"""),2012.0) -> 2012 | F98: =DATE(E98,C98,D98) -> 41232 | G98: 12/17/2012 | H98: =IFERROR(__xludf.DUMMYFUNCTION("split(G98,""/"")"),12.0) -> 12 | I98: =IFERROR(__xludf.DUMMYFUNCTION("""COMPUTED_VALUE"""),17.0) -> 17 | J98: =IFERROR(__xludf.DUMMYFUNCTION("""COMPUTED_VALUE"""),2012.0) -> 2012 | K98: =DATE(J98,H98,I98) -> 41260 | L98: M | M98: Desconhecido | N98: 8875 | O98: Offline | P98: 8959 | Q98: 421.89 | R98: 364.69 | S98: =Q98*P98 -> 3779712.5 | T98: =R98*P98 -> 3267257.7 | U98: =S98-T98 -> 512454.8 | V98: =VLOOKUP(N98,products!A:B,2,0) -> Meat | W98: Desconhecido | X98: Desconhecido | Y98: =U98/S98 -> 0.13558036 | Z98: =K98-F98 -> 28 | AA98: =WEEKDAY(F98,1) -> 2
A99: 160578763 | B99: 9/27/2015 | C99: =IFERROR(__xludf.DUMMYFUNCTION("split(B99,""/"")"),9.0) -> 9 | D99: =IFERROR(__xludf.DUMMYFUNCTION("""COMPUTED_VALUE"""),27.0) -> 27 | E99: =IFERROR(__xludf.DUMMYFUNCTION("""COMPUTED_VALUE"""),2015.0) -> 2015 | F99: =DATE(E99,C99,D99) -> 42274 | G99: 10/30/2015 | H99: =IFERROR(__xludf.DUMMYFUNCTION("split(G99,""/"")"),10.0) -> 10 | I99: =IFERROR(__xludf.DUMMYFUNCTION("""COMPUTED_VALUE"""),30.0) -> 30 | J99: =IFERROR(__xludf.DUMMYFUNCTION("""COMPUTED_VALUE"""),2015.0) -> 2015 | K99: =DATE(J99,H99,I99) -> 42307 | L99: L | M99: ROU | N99: 8681 | O99: Online | P99: 7679 | Q99: 651.21 | R99: 524.96 | S99: =Q99*P99 -> 5000641.6 | T99: =R99*P99 -> 4031167.8 | U99: =S99-T99 -> 969473.75 | V99: =VLOOKUP(N99,products!A:B,2,0) -> Office Supplies | W99: Europe | X99: Eastern Europe | Y99: =U99/S99 -> 0.19386987 | Z99: =K99-F99 -> 33 | AA99: =WEEKDAY(F99,1) -> 1
A100: 160751283 | B100: 10/29/2011 | C100: =IFERROR(__xludf.DUMMYFUNCTION("split(B100,""/"")"),10.0) -> 10 | D100: =IFERROR(__xludf.DUMMYFUNCTION("""COMPUTED_VALUE"""),29.0) -> 29 | E100: =IFERROR(__xludf.DUMMYFUNCTION("""COMPUTED_VALUE"""),2011.0) -> 2011 | F100: =DATE(E100,C100,D100) -> 40845 | G100: 11/13/2011 | H100: =IFERROR(__xludf.DUMMYFUNCTION("split(G100,""/"")"),11.0) -> 11 | I100: =IFERROR(__xludf.DUMMYFUNCTION("""COMPUTED_VALUE"""),13.0) -> 13 | J100: =IFERROR(__xludf.DUMMYFUNCTION("""COMPUTED_VALUE"""),2011.0) -> 2011 | K100: =DATE(J100,H100,I100) -> 40860 | L100: C | M100: LVA | N100: 3127 | O100: Offline | P100: 8732 | Q100: 81.73 | R100: 56.67 | S100: =Q100*P100 -> 713666.36 | T100: =R100*P100 -> 494842.44 | U100: =S100-T100 -> 218823.92 | V100: =VLOOKUP(N100,products!A:B,2,0) -> Personal Care | W100: Europe | X100: Northern Europe | Y100: =U100/S100 -> 0.30661936 | Z100: =K100-F100 -> 15 | AA100: =WEEKDAY(F100,1) -> 7
...

Sheet PARETO
A1: Order ID | B1: Order Date | C1: mesOrder Date | D1: diaOrder Date | E1: anoOrder Date | F1: order date formatada | G1: Ship Date | H1: mesShip Date | I1: diaShip Date | J1: anoShip Date | K1: ship date formatada | L1: Order Priority | M1: Country Code | N1: Product ID | O1: Sales Channel | P1: Units Sold | Q1: Unit Price | R1: Unit Cost | S1: receita_total | T1: custo_total | U1: lucro_total | V1: item_type | W1: region | X1: sub-region | Y1: % margem | Z1: lead_time | AA1: dia da semana compra
A2: =IFERROR(__xludf.DUMMYFUNCTION("FILTER(events!A:AA, events!E:E = MAX(events!E:E))"),1.02230632E8) -> 102230632 | B2: =IFERROR(__xludf.DUMMYFUNCTION("""COMPUTED_VALUE"""),"5/13/2017") -> 5/13/2017 | C2: =IFERROR(__xludf.DUMMYFUNCTION("""COMPUTED_VALUE"""),5.0) -> 5 | D2: =IFERROR(__xludf.DUMMYFUNCTION("""COMPUTED_VALUE"""),13.0) -> 13 | E2: =IFERROR(__xludf.DUMMYFUNCTION("""COMPUTED_VALUE"""),2017.0) -> 2017 | F2: =IFERROR(__xludf.DUMMYFUNCTION("""COMPUTED_VALUE"""),42868.0) -> 42868 | G2: =IFERROR(__xludf.DUMMYFUNCTION("""COMPUTED_VALUE"""),"6/13/2017") -> 6/13/2017 | H2: =IFERROR(__xludf.DUMMYFUNCTION("""COMPUTED_VALUE"""),6.0) -> 6 | I2: =IFERROR(__xludf.DUMMYFUNCTION("""COMPUTED_VALUE"""),13.0) -> 13 | J2: =IFERROR(__xludf.DUMMYFUNCTION("""COMPUTED_VALUE"""),2017.0) -> 2017 | K2: =IFERROR(__xludf.DUMMYFUNCTION("""COMPUTED_VALUE"""),42899.0) -> 42899 | L2: =IFERROR(__xludf.DUMMYFUNCTION("""COMPUTED_VALUE"""),"L") -> L | M2: =IFERROR(__xludf.DUMMYFUNCTION("""COMPUTED_VALUE"""),"MNE") -> MNE | N2: =IFERROR(__xludf.DUMMYFUNCTION("""COMPUTED_VALUE"""),2455.0) -> 2455 | O2: =IFERROR(__xludf.DUMMYFUNCTION("""COMPUTED_VALUE"""),"Online") -> Online | P2: =IFERROR(__xludf.DUMMYFUNCTION("""COMPUTED_VALUE"""),1171.0) -> 1171 | Q2: =IFERROR(__xludf.DUMMYFUNCTION("""COMPUTED_VALUE"""),109.28) -> 109.28 | R2: =IFERROR(__xludf.DUMMYFUNCTION("""COMPUTED_VALUE"""),35.84) -> 35.84 | S2: =IFERROR(__xludf.DUMMYFUNCTION("""COMPUTED_VALUE"""),127966.88) -> 127966.88 | T2: =IFERROR(__xludf.DUMMYFUNCTION("""COMPUTED_VALUE"""),41968.64000000001) -> 41968.64 | U2: =IFERROR(__xludf.DUMMYFUNCTION("""COMPUTED_VALUE"""),85998.23999999999) -> 85998.24 | V2: =IFERROR(__xludf.DUMMYFUNCTION("""COMPUTED_VALUE"""),"Clothes") -> Clothes | W2: =IFERROR(__xludf.DUMMYFUNCTION("""COMPUTED_VALUE"""),"Europe") -> Europe | X2: =IFERROR(__xludf.DUMMYFUNCTION("""COMPUTED_VALUE"""),"Southern Europe") -> Southern Europe | Y2: =IFERROR(__xludf.DUMMYFUNCTION("""COMPUTED_VALUE"""),0.67203513909224) -> 0.67203514 | Z2: =IFERROR(__xludf.DUMMYFUNCTION("""COMPUTED_VALUE"""),31.0) -> 31 | AA2: =IFERROR(__xludf.DUMMYFUNCTION("""COMPUTED_VALUE"""),7.0) -> 7
A3: =IFERROR(__xludf.DUMMYFUNCTION("""COMPUTED_VALUE"""),1.04190576E8) -> 104190576 | B3: =IFERROR(__xludf.DUMMYFUNCTION("""COMPUTED_VALUE"""),"2/22/2017") -> 2/22/2017 | C3: =IFERROR(__xludf.DUMMYFUNCTION("""COMPUTED_VALUE"""),2.0) -> 2 | D3: =IFERROR(__xludf.DUMMYFUNCTION("""COMPUTED_VALUE"""),22.0) -> 22 | E3: =IFERROR(__xludf.DUMMYFUNCTION("""COMPUTED_VALUE"""),2017.0) -> 2017 | F3: =IFERROR(__xludf.DUMMYFUNCTION("""COMPUTED_VALUE"""),42788.0) -> 42788 | G3: =IFERROR(__xludf.DUMMYFUNCTION("""COMPUTED_VALUE"""),43072.0) -> 43072 | H3: =IFERROR(__xludf.DUMMYFUNCTION("""COMPUTED_VALUE"""),3.0) -> 3 | I3: =IFERROR(__xludf.DUMMYFUNCTION("""COMPUTED_VALUE"""),12.0) -> 12 | J3: =IFERROR(__xludf.DUMMYFUNCTION("""COMPUTED_VALUE"""),2017.0) -> 2017 | K3: =IFERROR(__xludf.DUMMYFUNCTION("""COMPUTED_VALUE"""),42806.0) -> 42806 | L3: =IFERROR(__xludf.DUMMYFUNCTION("""COMPUTED_VALUE"""),"C") -> C | M3: =IFERROR(__xludf.DUMMYFUNCTION("""COMPUTED_VALUE"""),"GEO") -> GEO | N3: =IFERROR(__xludf.DUMMYFUNCTION("""COMPUTED_VALUE"""),8875.0) -> 8875 | O3: =IFERROR(__xludf.DUMMYFUNCTION("""COMPUTED_VALUE"""),"Offline") -> Offline | P3: =IFERROR(__xludf.DUMMYFUNCTION("""COMPUTED_VALUE"""),1162.0) -> 1162 | Q3: =IFERROR(__xludf.DUMMYFUNCTION("""COMPUTED_VALUE"""),421.89) -> 421.89 | R3: =IFERROR(__xludf.DUMMYFUNCTION("""COMPUTED_VALUE"""),364.69) -> 364.69 | S3: =IFERROR(__xludf.DUMMYFUNCTION("""COMPUTED_VALUE"""),490236.18) -> 490236.18 | T3: =IFERROR(__xludf.DUMMYFUNCTION("""COMPUTED_VALUE"""),423769.77999999997) -> 423769.78 | U3: =IFERROR(__xludf.DUMMYFUNCTION("""COMPUTED_VALUE"""),66466.40000000002) -> 66466.4 | V3: =IFERROR(__xludf.DUMMYFUNCTION("""COMPUTED_VALUE"""),"Meat") -> Meat | W3: =IFERROR(__xludf.DUMMYFUNCTION("""COMPUTED_VALUE"""),"Asia") -> Asia | X3: =IFERROR(__xludf.DUMMYFUNCTION("""COMPUTED_VALUE"""),"Western Asia") -> Western Asia | Y3: =IFERROR(__xludf.DUMMYFUNCTION("""COMPUTED_VALUE"""),0.13558036455000125) -> 0.13558036 | Z3: =IFERROR(__xludf.DUMMYFUNCTION("""COMPUTED_VALUE"""),18.0) -> 18 | AA3: =IFERROR(__xludf.DUMMYFUNCTION("""COMPUTED_VALUE"""),4.0) -> 4
A4: =IFERROR(__xludf.DUMMYFUNCTION("""COMPUTED_VALUE"""),1.11246287E8) -> 111246287 | B4: =IFERROR(__xludf.DUMMYFUNCTION("""COMPUTED_VALUE"""),42984.0) -> 42984 | C4: =IFERROR(__xludf.DUMMYFUNCTION("""COMPUTED_VALUE"""),6.0) -> 6 | D4: =IFERROR(__xludf.DUMMYFUNCTION("""COMPUTED_VALUE"""),9.0) -> 9 | E4: =IFERROR(__xludf.DUMMYFUNCTION("""COMPUTED_VALUE"""),2017.0) -> 2017 | F4: =IFERROR(__xludf.DUMMYFUNCTION("""COMPUTED_VALUE"""),42895.0) -> 42895 | G4: =IFERROR(__xludf.DUMMYFUNCTION("""COMPUTED_VALUE"""),42773.0) -> 42773 | H4: =IFERROR(__xludf.DUMMYFUNCTION("""COMPUTED_VALUE"""),7.0) -> 7 | I4: =IFERROR(__xludf.DUMMYFUNCTION("""COMPUTED_VALUE"""),2.0) -> 2 | J4: =IFERROR(__xludf.DUMMYFUNCTION("""COMPUTED_VALUE"""),2017.0) -> 2017 | K4: =IFERROR(__xludf.DUMMYFUNCTION("""COMPUTED_VALUE"""),42918.0) -> 42918 | L4: =IFERROR(__xludf.DUMMYFUNCTION("""COMPUTED_VALUE"""),"M") -> M | M4: =IFERROR(__xludf.DUMMYFUNCTION("""COMPUTED_VALUE"""),"CYP") -> CYP | N4: =IFERROR(__xludf.DUMMYFUNCTION("""COMPUTED_VALUE"""),8875.0) -> 8875 | O4: =IFERROR(__xludf.DUMMYFUNCTION("""COMPUTED_VALUE"""),"Offline") -> Offline | P4: =IFERROR(__xludf.DUMMYFUNCTION("""COMPUTED_VALUE"""),9103.0) -> 9103 | Q4: =IFERROR(__xludf.DUMMYFUNCTION("""COMPUTED_VALUE"""),421.89) -> 421.89 | R4: =IFERROR(__xludf.DUMMYFUNCTION("""COMPUTED_VALUE"""),364.69) -> 364.69 | S4: =IFERROR(__xludf.DUMMYFUNCTION("""COMPUTED_VALUE"""),3840464.67) -> 3840464.7 | T4: =IFERROR(__xludf.DUMMYFUNCTION("""COMPUTED_VALUE"""),3319773.07) -> 3319773.1 | U4: =IFERROR(__xludf.DUMMYFUNCTION("""COMPUTED_VALUE"""),520691.6000000001) -> 520691.6 | V4: =IFERROR(__xludf.DUMMYFUNCTION("""COMPUTED_VALUE"""),"Meat") -> Meat | W4: =IFERROR(__xludf.DUMMYFUNCTION("""COMPUTED_VALUE"""),"Asia") -> Asia | X4: =IFERROR(__xludf.DUMMYFUNCTION("""COMPUTED_VALUE"""),"Western Asia") -> Western Asia | Y4: =IFERROR(__xludf.DUMMYFUNCTION("""COMPUTED_VALUE"""),0.13558036455000122) -> 0.13558036 | Z4: =IFERROR(__xludf.DUMMYFUNCTION("""COMPUTED_VALUE"""),23.0) -> 23 | AA4: =IFERROR(__xludf.DUMMYFUNCTION("""COMPUTED_VALUE"""),6.0) -> 6
A5: =IFERROR(__xludf.DUMMYFUNCTION("""COMPUTED_VALUE"""),1.21945512E8) -> 121945512 | B5: =IFERROR(__xludf.DUMMYFUNCTION("""COMPUTED_VALUE"""),42951.0) -> 42951 | C5: =IFERROR(__xludf.DUMMYFUNCTION("""COMPUTED_VALUE"""),4.0) -> 4 | D5: =IFERROR(__xludf.DUMMYFUNCTION("""COMPUTED_VALUE"""),8.0) -> 8 | E5: =IFERROR(__xludf.DUMMYFUNCTION("""COMPUTED_VALUE"""),2017.0) -> 2017 | F5: =IFERROR(__xludf.DUMMYFUNCTION("""COMPUTED_VALUE"""),42833.0) -> 42833 | G5: =IFERROR(__xludf.DUMMYFUNCTION("""COMPUTED_VALUE"""),43073.0) -> 43073 | H5: =IFERROR(__xludf.DUMMYFUNCTION("""COMPUTED_VALUE"""),4.0) -> 4 | I5: =IFERROR(__xludf.DUMMYFUNCTION("""COMPUTED_VALUE"""),12.0) -> 12 | J5: =IFERROR(__xludf.DUMMYFUNCTION("""COMPUTED_VALUE"""),2017.0) -> 2017 | K5: =IFERROR(__xludf.DUMMYFUNCTION("""COMPUTED_VALUE"""),42837.0) -> 42837 | L5: =IFERROR(__xludf.DUMMYFUNCTION("""COMPUTED_VALUE"""),"C") -> C | M5: =IFERROR(__xludf.DUMMYFUNCTION("""COMPUTED_VALUE"""),"GBR") -> GBR | N5: =IFERROR(__xludf.DUMMYFUNCTION("""COMPUTED_VALUE"""),1270.0) -> 1270 | O5: =IFERROR(__xludf.DUMMYFUNCTION("""COMPUTED_VALUE"""),"Online") -> Online | P5: =IFERROR(__xludf.DUMMYFUNCTION("""COMPUTED_VALUE"""),5242.0) -> 5242 | Q5: =IFERROR(__xludf.DUMMYFUNCTION("""COMPUTED_VALUE"""),47.45) -> 47.45 | R5: =IFERROR(__xludf.DUMMYFUNCTION("""COMPUTED_VALUE"""),31.79) -> 31.79 | S5: =IFERROR(__xludf.DUMMYFUNCTION("""COMPUTED_VALUE"""),248732.90000000002) -> 248732.9 | T5: =IFERROR(__xludf.DUMMYFUNCTION("""COMPUTED_VALUE"""),166643.18) -> 166643.18 | U5: =IFERROR(__xludf.DUMMYFUNCTION("""COMPUTED_VALUE"""),82089.72000000003) -> 82089.72 | V5: =IFERROR(__xludf.DUMMYFUNCTION("""COMPUTED_VALUE"""),"Beverages") -> Beverages | W5: =IFERROR(__xludf.DUMMYFUNCTION("""COMPUTED_VALUE"""),"Europe") -> Europe | X5: =IFERROR(__xludf.DUMMYFUNCTION("""COMPUTED_VALUE"""),"Northern Europe") -> Northern Europe | Y5: =IFERROR(__xludf.DUMMYFUNCTION("""COMPUTED_VALUE"""),0.3300316122233931) -> 0.33003161 | Z5: =IFERROR(__xludf.DUMMYFUNCTION("""COMPUTED_VALUE"""),4.0) -> 4 | AA5: =IFERROR(__xludf.DUMMYFUNCTION("""COMPUTED_VALUE"""),7.0) -> 7
A6: =IFERROR(__xludf.DUMMYFUNCTION("""COMPUTED_VALUE"""),1.2214421E8) -> 122144210 | B6: =IFERROR(__xludf.DUMMYFUNCTION("""COMPUTED_VALUE"""),"4/27/2017") -> 4/27/2017 | C6: =IFERROR(__xludf.DUMMYFUNCTION("""COMPUTED_VALUE"""),4.0) -> 4 | D6: =IFERROR(__xludf.DUMMYFUNCTION("""COMPUTED_VALUE"""),27.0) -> 27 | E6: =IFERROR(__xludf.DUMMYFUNCTION("""COMPUTED_VALUE"""),2017.0) -> 2017 | F6: =IFERROR(__xludf.DUMMYFUNCTION("""COMPUTED_VALUE"""),42852.0) -> 42852 | G6: =IFERROR(__xludf.DUMMYFUNCTION("""COMPUTED_VALUE"""),"5/24/2017") -> 5/24/2017 | H6: =IFERROR(__xludf.DUMMYFUNCTION("""COMPUTED_VALUE"""),5.0) -> 5 | I6: =IFERROR(__xludf.DUMMYFUNCTION("""COMPUTED_VALUE"""),24.0) -> 24 | J6: =IFERROR(__xludf.DUMMYFUNCTION("""COMPUTED_VALUE"""),2017.0) -> 2017 | K6: =IFERROR(__xludf.DUMMYFUNCTION("""COMPUTED_VALUE"""),42879.0) -> 42879 | L6: =IFERROR(__xludf.DUMMYFUNCTION("""COMPUTED_VALUE"""),"C") -> C | M6: =IFERROR(__xludf.DUMMYFUNCTION("""COMPUTED_VALUE"""),"MNE") -> MNE | N6: =IFERROR(__xludf.DUMMYFUNCTION("""COMPUTED_VALUE"""),1270.0) -> 1270 | O6: =IFERROR(__xludf.DUMMYFUNCTION("""COMPUTED_VALUE"""),"Offline") -> Offline | P6: =IFERROR(__xludf.DUMMYFUNCTION("""COMPUTED_VALUE"""),4041.0) -> 4041 | Q6: =IFERROR(__xludf.DUMMYFUNCTION("""COMPUTED_VALUE"""),47.45) -> 47.45 | R6: =IFERROR(__xludf.DUMMYFUNCTION("""COMPUTED_VALUE"""),31.79) -> 31.79 | S6: =IFERROR(__xludf.DUMMYFUNCTION("""COMPUTED_VALUE"""),191745.45) -> 191745.45 | T6: =IFERROR(__xludf.DUMMYFUNCTION("""COMPUTED_VALUE"""),128463.39) -> 128463.39 | U6: =IFERROR(__xludf.DUMMYFUNCTION("""COMPUTED_VALUE"""),63282.06000000001) -> 63282.06 | V6: =IFERROR(__xludf.DUMMYFUNCTION("""COMPUTED_VALUE"""),"Beverages") -> Beverages | W6: =IFERROR(__xludf.DUMMYFUNCTION("""COMPUTED_VALUE"""),"Europe") -> Europe | X6: =IFERROR(__xludf.DUMMYFUNCTION("""COMPUTED_VALUE"""),"Southern Europe") -> Southern Europe | Y6: =IFERROR(__xludf.DUMMYFUNCTION("""COMPUTED_VALUE"""),0.3300316122233931) -> 0.33003161 | Z6: =IFERROR(__xludf.DUMMYFUNCTION("""COMPUTED_VALUE"""),27.0) -> 27 | AA6: =IFERROR(__xludf.DUMMYFUNCTION("""COMPUTED_VALUE"""),5.0) -> 5
A7: =IFERROR(__xludf.DUMMYFUNCTION("""COMPUTED_VALUE"""),1.22967326E8) -> 122967326 | B7: =IFERROR(__xludf.DUMMYFUNCTION("""COMPUTED_VALUE"""),"3/24/2017") -> 3/24/2017 | C7: =IFERROR(__xludf.DUMMYFUNCTION("""COMPUTED_VALUE"""),3.0) -> 3 | D7: =IFERROR(__xludf.DUMMYFUNCTION("""COMPUTED_VALUE"""),24.0) -> 24 | E7: =IFERROR(__xludf.DUMMYFUNCTION("""COMPUTED_VALUE"""),2017.0) -> 2017 | F7: =IFERROR(__xludf.DUMMYFUNCTION("""COMPUTED_VALUE"""),42818.0) -> 42818 | G7: =IFERROR(__xludf.DUMMYFUNCTION("""COMPUTED_VALUE"""),"4/25/2017") -> 4/25/2017 | H7: =IFERROR(__xludf.DUMMYFUNCTION("""COMPUTED_VALUE"""),4.0) -> 4 | I7: =IFERROR(__xludf.DUMMYFUNCTION("""COMPUTED_VALUE"""),25.0) -> 25 | J7: =IFERROR(__xludf.DUMMYFUNCTION("""COMPUTED_VALUE"""),2017.0) -> 2017 | K7: =IFERROR(__xludf.DUMMYFUNCTION("""COMPUTED_VALUE"""),42850.0) -> 42850 | L7: =IFERROR(__xludf.DUMMYFUNCTION("""COMPUTED_VALUE"""),"H") -> H | M7: =IFERROR(__xludf.DUMMYFUNCTION("""COMPUTED_VALUE"""),"BLR") -> BLR | N7: =IFERROR(__xludf.DUMMYFUNCTION("""COMPUTED_VALUE"""),1270.0) -> 1270 | O7: =IFERROR(__xludf.DUMMYFUNCTION("""COMPUTED_VALUE"""),"Online") -> Online | P7: =IFERROR(__xludf.DUMMYFUNCTION("""COMPUTED_VALUE"""),7619.0) -> 7619 | Q7: =IFERROR(__xludf.DUMMYFUNCTION("""COMPUTED_VALUE"""),47.45) -> 47.45 | R7: =IFERROR(__xludf.DUMMYFUNCTION("""COMPUTED_VALUE"""),31.79) -> 31.79 | S7: =IFERROR(__xludf.DUMMYFUNCTION("""COMPUTED_VALUE"""),361521.55000000005) -> 361521.55 | T7: =IFERROR(__xludf.DUMMYFUNCTION("""COMPUTED_VALUE"""),242208.00999999998) -> 242208.01 | U7: =IFERROR(__xludf.DUMMYFUNCTION("""COMPUTED_VALUE"""),119313.54000000007) -> 119313.54 | V7: =IFERROR(__xludf.DUMMYFUNCTION("""COMPUTED_VALUE"""),"Beverages") -> Beverages | W7: =IFERROR(__xludf.DUMMYFUNCTION("""COMPUTED_VALUE"""),"Europe") -> Europe | X7: =IFERROR(__xludf.DUMMYFUNCTION("""COMPUTED_VALUE"""),"Eastern Europe") -> Eastern Europe | Y7: =IFERROR(__xludf.DUMMYFUNCTION("""COMPUTED_VALUE"""),0.33003161222339317) -> 0.33003161 | Z7: =IFERROR(__xludf.DUMMYFUNCTION("""COMPUTED_VALUE"""),32.0) -> 32 | AA7: =IFERROR(__xludf.DUMMYFUNCTION("""COMPUTED_VALUE"""),6.0) -> 6
A8: =IFERROR(__xludf.DUMMYFUNCTION("""COMPUTED_VALUE"""),1.25339686E8) -> 125339686 | B8: =IFERROR(__xludf.DUMMYFUNCTION("""COMPUTED_VALUE"""),43046.0) -> 43046 | C8: =IFERROR(__xludf.DUMMYFUNCTION("""COMPUTED_VALUE"""),7.0) -> 7 | D8: =IFERROR(__xludf.DUMMYFUNCTION("""COMPUTED_VALUE"""),11.0) -> 11 | E8: =IFERROR(__xludf.DUMMYFUNCTION("""COMPUTED_VALUE"""),2017.0) -> 2017 | F8: =IFERROR(__xludf.DUMMYFUNCTION("""COMPUTED_VALUE"""),42927.0) -> 42927 | G8: =IFERROR(__xludf.DUMMYFUNCTION("""COMPUTED_VALUE"""),"7/24/2017") -> 7/24/2017 | H8: =IFERROR(__xludf.DUMMYFUNCTION("""COMPUTED_VALUE"""),7.0) -> 7 | I8: =IFERROR(__xludf.DUMMYFUNCTION("""COMPUTED_VALUE"""),24.0) -> 24 | J8: =IFERROR(__xludf.DUMMYFUNCTION("""COMPUTED_VALUE"""),2017.0) -> 2017 | K8: =IFERROR(__xludf.DUMMYFUNCTION("""COMPUTED_VALUE"""),42940.0) -> 42940 | L8: =IFERROR(__xludf.DUMMYFUNCTION("""COMPUTED_VALUE"""),"L") -> L | M8: =IFERROR(__xludf.DUMMYFUNCTION("""COMPUTED_VALUE"""),"MKD") -> MKD | N8: =IFERROR(__xludf.DUMMYFUNCTION("""COMPUTED_VALUE"""),8969.0) -> 8969 | O8: =IFERROR(__xludf.DUMMYFUNCTION("""COMPUTED_VALUE"""),"Online") -> Online | P8: =IFERROR(__xludf.DUMMYFUNCTION("""COMPUTED_VALUE"""),9653.0) -> 9653 | Q8: =IFERROR(__xludf.DUMMYFUNCTION("""COMPUTED_VALUE"""),152.58) -> 152.58 | R8: =IFERROR(__xludf.DUMMYFUNCTION("""COMPUTED_VALUE"""),97.44) -> 97.44 | S8: =IFERROR(__xludf.DUMMYFUNCTION("""COMPUTED_VALUE"""),1472854.7400000002) -> 1472854.7 | T8: =IFERROR(__xludf.DUMMYFUNCTION("""COMPUTED_VALUE"""),940588.32) -> 940588.32 | U8: =IFERROR(__xludf.DUMMYFUNCTION("""COMPUTED_VALUE"""),532266.4200000003) -> 532266.42 | V8: =IFERROR(__xludf.DUMMYFUNCTION("""COMPUTED_VALUE"""),"Snacks") -> Snacks | W8: =IFERROR(__xludf.DUMMYFUNCTION("""COMPUTED_VALUE"""),"Europe") -> Europe | X8: =IFERROR(__xludf.DUMMYFUNCTION("""COMPUTED_VALUE"""),"Southern Europe") -> Southern Europe | Y8: =IFERROR(__xludf.DUMMYFUNCTION("""COMPUTED_VALUE"""),0.36138419189933163) -> 0.36138419 | Z8: =IFERROR(__xludf.DUMMYFUNCTION("""COMPUTED_VALUE"""),13.0) -> 13 | AA8: =IFERROR(__xludf.DUMMYFUNCTION("""COMPUTED_VALUE"""),3.0) -> 3
A9: =IFERROR(__xludf.DUMMYFUNCTION("""COMPUTED_VALUE"""),1.26948583E8) -> 126948583 | B9: =IFERROR(__xludf.DUMMYFUNCTION("""COMPUTED_VALUE"""),"5/24/2017") -> 5/24/2017 | C9: =IFERROR(__xludf.DUMMYFUNCTION("""COMPUTED_VALUE"""),5.0) -> 5 | D9: =IFERROR(__xludf.DUMMYFUNCTION("""COMPUTED_VALUE"""),24.0) -> 24 | E9: =IFERROR(__xludf.DUMMYFUNCTION("""COMPUTED_VALUE"""),2017.0) -> 2017 | F9: =IFERROR(__xludf.DUMMYFUNCTION("""COMPUTED_VALUE"""),42879.0) -> 42879 | G9: =IFERROR(__xludf.DUMMYFUNCTION("""COMPUTED_VALUE"""),42985.0) -> 42985 | H9: =IFERROR(__xludf.DUMMYFUNCTION("""COMPUTED_VALUE"""),7.0) -> 7 | I9: =IFERROR(__xludf.DUMMYFUNCTION("""COMPUTED_VALUE"""),9.0) -> 9 | J9: =IFERROR(__xludf.DUMMYFUNCTION("""COMPUTED_VALUE"""),2017.0) -> 2017 | K9: =IFERROR(__xludf.DUMMYFUNCTION("""COMPUTED_VALUE"""),42925.0) -> 42925 | L9: =IFERROR(__xludf.DUMMYFUNCTION("""COMPUTED_VALUE"""),"C") -> C | M9: =IFERROR(__xludf.DUMMYFUNCTION("""COMPUTED_VALUE"""),"Desconhecido") -> Desconhecido | N9: =IFERROR(__xludf.DUMMYFUNCTION("""COMPUTED_VALUE"""),7331.0) -> 7331 | O9: =IFERROR(__xludf.DUMMYFUNCTION("""COMPUTED_VALUE"""),"Online") -> Online | P9: =IFERROR(__xludf.DUMMYFUNCTION("""COMPUTED_VALUE"""),5762.0) -> 5762 | Q9: =IFERROR(__xludf.DUMMYFUNCTION("""COMPUTED_VALUE"""),255.28) -> 255.28 | R9: =IFERROR(__xludf.DUMMYFUNCTION("""COMPUTED_VALUE"""),159.42) -> 159.42 | S9: =IFERROR(__xludf.DUMMYFUNCTION("""COMPUTED_VALUE"""),1470923.36) -> 1470923.4 | T9: =IFERROR(__xludf.DUMMYFUNCTION("""COMPUTED_VALUE"""),918578.0399999999) -> 918578.04 | U9: =IFERROR(__xludf.DUMMYFUNCTION("""COMPUTED_VALUE"""),552345.3200000002) -> 552345.32 | V9: =IFERROR(__xludf.DUMMYFUNCTION("""COMPUTED_VALUE"""),"Baby Food") -> Baby Food | W9: =IFERROR(__xludf.DUMMYFUNCTION("""COMPUTED_VALUE"""),"Desconhecido") -> Desconhecido | X9: =IFERROR(__xludf.DUMMYFUNCTION("""COMPUTED_VALUE"""),"Desconhecido") -> Desconhecido | Y9: =IFERROR(__xludf.DUMMYFUNCTION("""COMPUTED_VALUE"""),0.3755092447508619) -> 0.37550924 | Z9: =IFERROR(__xludf.DUMMYFUNCTION("""COMPUTED_VALUE"""),46.0) -> 46 | AA9: =IFERROR(__xludf.DUMMYFUNCTION("""COMPUTED_VALUE"""),4.0) -> 4
A10: =IFERROR(__xludf.DUMMYFUNCTION("""COMPUTED_VALUE"""),1.31585586E8) -> 131585586 | B10: =IFERROR(__xludf.DUMMYFUNCTION("""COMPUTED_VALUE"""),"3/13/2017") -> 3/13/2017 | C10: =IFERROR(__xludf.DUMMYFUNCTION("""COMPUTED_VALUE"""),3.0) -> 3 | D10: =IFERROR(__xludf.DUMMYFUNCTION("""COMPUTED_VALUE"""),13.0) -> 13 | E10: =IFERROR(__xludf.DUMMYFUNCTION("""COMPUTED_VALUE"""),2017.0) -> 2017 | F10: =IFERROR(__xludf.DUMMYFUNCTION("""COMPUTED_VALUE"""),42807.0) -> 42807 | G10: =IFERROR(__xludf.DUMMYFUNCTION("""COMPUTED_VALUE"""),"4/13/2017") -> 4/13/2017 | H10: =IFERROR(__xludf.DUMMYFUNCTION("""COMPUTED_VALUE"""),4.0) -> 4 | I10: =IFERROR(__xludf.DUMMYFUNCTION("""COMPUTED_VALUE"""),13.0) -> 13 | J10: =IFERROR(__xludf.DUMMYFUNCTION("""COMPUTED_VALUE"""),2017.0) -> 2017 | K10: =IFERROR(__xludf.DUMMYFUNCTION("""COMPUTED_VALUE"""),42838.0) -> 42838 | L10: =IFERROR(__xludf.DUMMYFUNCTION("""COMPUTED_VALUE"""),"C") -> C | M10: =IFERROR(__xludf.DUMMYFUNCTION("""COMPUTED_VALUE"""),"FRA") -> FRA | N10: =IFERROR(__xludf.DUMMYFUNCTION("""COMPUTED_VALUE"""),3127.0) -> 3127 | O10: =IFERROR(__xludf.DUMMYFUNCTION("""COMPUTED_VALUE"""),"Offline") -> Offline | P10: =IFERROR(__xludf.DUMMYFUNCTION("""COMPUTED_VALUE"""),7954.0) -> 7954 | Q10: =IFERROR(__xludf.DUMMYFUNCTION("""COMPUTED_VALUE"""),81.73) -> 81.73 | R10: =IFERROR(__xludf.DUMMYFUNCTION("""COMPUTED_VALUE"""),56.67) -> 56.67 | S10: =IFERROR(__xludf.DUMMYFUNCTION("""COMPUTED_VALUE"""),650080.42) -> 650080.42 | T10: =IFERROR(__xludf.DUMMYFUNCTION("""COMPUTED_VALUE"""),450753.18) -> 450753.18 | U10: =IFERROR(__xludf.DUMMYFUNCTION("""COMPUTED_VALUE"""),199327.24000000005) -> 199327.24 | V10: =IFERROR(__xludf.DUMMYFUNCTION("""COMPUTED_VALUE"""),"Personal Care") -> Personal Care | W10: =IFERROR(__xludf.DUMMYFUNCTION("""COMPUTED_VALUE"""),"Europe") -> Europe | X10: =IFERROR(__xludf.DUMMYFUNCTION("""COMPUTED_VALUE"""),"Western Europe") -> Western Europe | Y10: =IFERROR(__xludf.DUMMYFUNCTION("""COMPUTED_VALUE"""),0.30661935641747223) -> 0.30661936 | Z10: =IFERROR(__xludf.DUMMYFUNCTION("""COMPUTED_VALUE"""),31.0) -> 31 | AA10: =IFERROR(__xludf.DUMMYFUNCTION("""COMPUTED_VALUE"""),2.0) -> 2
A11: =IFERROR(__xludf.DUMMYFUNCTION("""COMPUTED_VALUE"""),1.32069671E8) -> 132069671 | B11: =IFERROR(__xludf.DUMMYFUNCTION("""COMPUTED_VALUE"""),42985.0) -> 42985 | C11: =IFERROR(__xludf.DUMMYFUNCTION("""COMPUTED_VALUE"""),7.0) -> 7 | D11: =IFERROR(__xludf.DUMMYFUNCTION("""COMPUTED_VALUE"""),9.0) -> 9 | E11: =IFERROR(__xludf.DUMMYFUNCTION("""COMPUTED_VALUE"""),2017.0) -> 2017 | F11: =IFERROR(__xludf.DUMMYFUNCTION("""COMPUTED_VALUE"""),42925.0) -> 42925 | G11: =IFERROR(__xludf.DUMMYFUNCTION("""COMPUTED_VALUE"""),"7/20/2017") -> 7/20/2017 | H11: =IFERROR(__xludf.DUMMYFUNCTION("""COMPUTED_VALUE"""),7.0) -> 7 | I11: =IFERROR(__xludf.DUMMYFUNCTION("""COMPUTED_VALUE"""),20.0) -> 20 | J11: =IFERROR(__xludf.DUMMYFUNCTION("""COMPUTED_VALUE"""),2017.0) -> 2017 | K11: =IFERROR(__xludf.DUMMYFUNCTION("""COMPUTED_VALUE"""),42936.0) -> 42936 | L11: =IFERROR(__xludf.DUMMYFUNCTION("""COMPUTED_VALUE"""),"M") -> M | M11: =IFERROR(__xludf.DUMMYFUNCTION("""COMPUTED_VALUE"""),"AUT") -> AUT | N11: =IFERROR(__xludf.DUMMYFUNCTION("""COMPUTED_VALUE"""),3127.0) -> 3127 | O11: =IFERROR(__xludf.DUMMYFUNCTION("""COMPUTED_VALUE"""),"Online") -> Online | P11: =IFERROR(__xludf.DUMMYFUNCTION("""COMPUTED_VALUE"""),1205.0) -> 1205 | Q11: =IFERROR(__xludf.DUMMYFUNCTION("""COMPUTED_VALUE"""),81.73) -> 81.73 | R11: =IFERROR(__xludf.DUMMYFUNCTION("""COMPUTED_VALUE"""),56.67) -> 56.67 | S11: =IFERROR(__xludf.DUMMYFUNCTION("""COMPUTED_VALUE"""),98484.65000000001) -> 98484.65 | T11: =IFERROR(__xludf.DUMMYFUNCTION("""COMPUTED_VALUE"""),68287.35) -> 68287.35 | U11: =IFERROR(__xludf.DUMMYFUNCTION("""COMPUTED_VALUE"""),30197.300000000003) -> 30197.3 | V11: =IFERROR(__xludf.DUMMYFUNCTION("""COMPUTED_VALUE"""),"Personal Care") -> Personal Care | W11: =IFERROR(__xludf.DUMMYFUNCTION("""COMPUTED_VALUE"""),"Europe") -> Europe | X11: =IFERROR(__xludf.DUMMYFUNCTION("""COMPUTED_VALUE"""),"Western Europe") -> Western Europe | Y11: =IFERROR(__xludf.DUMMYFUNCTION("""COMPUTED_VALUE"""),0.3066193564174722) -> 0.30661936 | Z11: =IFERROR(__xludf.DUMMYFUNCTION("""COMPUTED_VALUE"""),11.0) -> 11 | AA11: =IFERROR(__xludf.DUMMYFUNCTION("""COMPUTED_VALUE"""),1.0) -> 1
A12: =IFERROR(__xludf.DUMMYFUNCTION("""COMPUTED_VALUE"""),1.46349751E8) -> 146349751 | B12: =IFERROR(__xludf.DUMMYFUNCTION("""COMPUTED_VALUE"""),42740.0) -> 42740 | C12: =IFERROR(__xludf.DUMMYFUNCTION("""COMPUTED_VALUE"""),5.0) -> 5 | D12: =IFERROR(__xludf.DUMMYFUNCTION("""COMPUTED_VALUE"""),1.0) -> 1 | E12: =IFERROR(__xludf.DUMMYFUNCTION("""COMPUTED_VALUE"""),2017.0) -> 2017 | F12: =IFERROR(__xludf.DUMMYFUNCTION("""COMPUTED_VALUE"""),42856.0) -> 42856 | G12: =IFERROR(__xludf.DUMMYFUNCTION("""COMPUTED_VALUE"""),"6/13/2017") -> 6/13/2017 | H12: =IFERROR(__xludf.DUMMYFUNCTION("""COMPUTED_VALUE"""),6.0) -> 6 | I12: =IFERROR(__xludf.DUMMYFUNCTION("""COMPUTED_VALUE"""),13.0) -> 13 | J12: =IFERROR(__xludf.DUMMYFUNCTION("""COMPUTED_VALUE"""),2017.0) -> 2017 | K12: =IFERROR(__xludf.DUMMYFUNCTION("""COMPUTED_VALUE"""),42899.0) -> 42899 | L12: =IFERROR(__xludf.DUMMYFUNCTION("""COMPUTED_VALUE"""),"M") -> M | M12: =IFERROR(__xludf.DUMMYFUNCTION("""COMPUTED_VALUE"""),"LTU") -> LTU | N12: =IFERROR(__xludf.DUMMYFUNCTION("""COMPUTED_VALUE"""),5988.0) -> 5988 | O12: =IFERROR(__xludf.DUMMYFUNCTION("""COMPUTED_VALUE"""),"Online") -> Online | P12: =IFERROR(__xludf.DUMMYFUNCTION("""COMPUTED_VALUE"""),6999.0) -> 6999 | Q12: =IFERROR(__xludf.DUMMYFUNCTION("""COMPUTED_VALUE"""),154.06) -> 154.06 | R12: =IFERROR(__xludf.DUMMYFUNCTION("""COMPUTED_VALUE"""),90.93) -> 90.93 | S12: =IFERROR(__xludf.DUMMYFUNCTION("""COMPUTED_VALUE"""),1078265.94) -> 1078265.9 | T12: =IFERROR(__xludf.DUMMYFUNCTION("""COMPUTED_VALUE"""),636419.0700000001) -> 636419.07 | U12: =IFERROR(__xludf.DUMMYFUNCTION("""COMPUTED_VALUE"""),441846.8699999999) -> 441846.87 | V12: =IFERROR(__xludf.DUMMYFUNCTION("""COMPUTED_VALUE"""),"Vegetables") -> Vegetables | W12: =IFERROR(__xludf.DUMMYFUNCTION("""COMPUTED_VALUE"""),"Europe") -> Europe | X12: =IFERROR(__xludf.DUMMYFUNCTION("""COMPUTED_VALUE"""),"Northern Europe") -> Northern Europe | Y12: =IFERROR(__xludf.DUMMYFUNCTION("""COMPUTED_VALUE"""),0.40977541217707375) -> 0.40977541 | Z12: =IFERROR(__xludf.DUMMYFUNCTION("""COMPUTED_VALUE"""),43.0) -> 43 | AA12: =IFERROR(__xludf.DUMMYFUNCTION("""COMPUTED_VALUE"""),2.0) -> 2
A13: =IFERROR(__xludf.DUMMYFUNCTION("""COMPUTED_VALUE"""),1.51312482E8) -> 151312482 | B13: =IFERROR(__xludf.DUMMYFUNCTION("""COMPUTED_VALUE"""),42892.0) -> 42892 | C13: =IFERROR(__xludf.DUMMYFUNCTION("""COMPUTED_VALUE"""),6.0) -> 6 | D13: =IFERROR(__xludf.DUMMYFUNCTION("""COMPUTED_VALUE"""),6.0) -> 6 | E13: =IFERROR(__xludf.DUMMYFUNCTION("""COMPUTED_VALUE"""),2017.0) -> 2017 | F13: =IFERROR(__xludf.DUMMYFUNCTION("""COMPUTED_VALUE"""),42892.0) -> 42892 | G13: =IFERROR(__xludf.DUMMYFUNCTION("""COMPUTED_VALUE"""),43076.0) -> 43076 | H13: =IFERROR(__xludf.DUMMYFUNCTION("""COMPUTED_VALUE"""),7.0) -> 7 | I13: =IFERROR(__xludf.DUMMYFUNCTION("""COMPUTED_VALUE"""),12.0) -> 12 | J13: =IFERROR(__xludf.DUMMYFUNCTION("""COMPUTED_VALUE"""),2017.0) -> 2017 | K13: =IFERROR(__xludf.DUMMYFUNCTION("""COMPUTED_VALUE"""),42928.0) -> 42928 | L13: =IFERROR(__xludf.DUMMYFUNCTION("""COMPUTED_VALUE"""),"H") -> H | M13: =IFERROR(__xludf.DUMMYFUNCTION("""COMPUTED_VALUE"""),"CZE") -> CZE | N13: =IFERROR(__xludf.DUMMYFUNCTION("""COMPUTED_VALUE"""),8293.0) -> 8293 | O13: =IFERROR(__xludf.DUMMYFUNCTION("""COMPUTED_VALUE"""),"Online") -> Online | P13: =IFERROR(__xludf.DUMMYFUNCTION("""COMPUTED_VALUE"""),5581.0) -> 5581 | Q13: =IFERROR(__xludf.DUMMYFUNCTION("""COMPUTED_VALUE"""),437.2) -> 437.2 | R13: =IFERROR(__xludf.DUMMYFUNCTION("""COMPUTED_VALUE"""),263.33) -> 263.33 | S13: =IFERROR(__xludf.DUMMYFUNCTION("""COMPUTED_VALUE"""),2440013.1999999997) -> 2440013.2 | T13: =IFERROR(__xludf.DUMMYFUNCTION("""COMPUTED_VALUE"""),1469644.73) -> 1469644.7 | U13: =IFERROR(__xludf.DUMMYFUNCTION("""COMPUTED_VALUE"""),970368.4699999997) -> 970368.47 | V13: =IFERROR(__xludf.DUMMYFUNCTION("""COMPUTED_VALUE"""),"Cosmetics") -> Cosmetics | W13: =IFERROR(__xludf.DUMMYFUNCTION("""COMPUTED_VALUE"""),"Europe") -> Europe | X13: =IFERROR(__xludf.DUMMYFUNCTION("""COMPUTED_VALUE"""),"Eastern Europe") -> Eastern Europe | Y13: =IFERROR(__xludf.DUMMYFUNCTION("""COMPUTED_VALUE"""),0.3976898444647758) -> 0.39768984 | Z13: =IFERROR(__xludf.DUMMYFUNCTION("""COMPUTED_VALUE"""),36.0) -> 36 | AA13: =IFERROR(__xludf.DUMMYFUNCTION("""COMPUTED_VALUE"""),3.0) -> 3
A14: =IFERROR(__xludf.DUMMYFUNCTION("""COMPUTED_VALUE"""),1.63744628E8) -> 163744628 | B14: =IFERROR(__xludf.DUMMYFUNCTION("""COMPUTED_VALUE"""),"4/17/2017") -> 4/17/2017 | C14: =IFERROR(__xludf.DUMMYFUNCTION("""COMPUTED_VALUE"""),4.0) -> 4 | D14: =IFERROR(__xludf.DUMMYFUNCTION("""COMPUTED_VALUE"""),17.0) -> 17 | E14: =IFERROR(__xludf.DUMMYFUNCTION("""COMPUTED_VALUE"""),2017.0) -> 2017 | F14: =IFERROR(__xludf.DUMMYFUNCTION("""COMPUTED_VALUE"""),42842.0) -> 42842 | G14: =IFERROR(__xludf.DUMMYFUNCTION("""COMPUTED_VALUE"""),42740.0) -> 42740 | H14: =IFERROR(__xludf.DUMMYFUNCTION("""COMPUTED_VALUE"""),5.0) -> 5 | I14: =IFERROR(__xludf.DUMMYFUNCTION("""COMPUTED_VALUE"""),1.0) -> 1 | J14: =IFERROR(__xludf.DUMMYFUNCTION("""COMPUTED_VALUE"""),2017.0) -> 2017 | K14: =IFERROR(__xludf.DUMMYFUNCTION("""COMPUTED_VALUE"""),42856.0) -> 42856 | L14: =IFERROR(__xludf.DUMMYFUNCTION("""COMPUTED_VALUE"""),"L") -> L | M14: =IFERROR(__xludf.DUMMYFUNCTION("""COMPUTED_VALUE"""),"FIN") -> FIN | N14: =IFERROR(__xludf.DUMMYFUNCTION("""COMPUTED_VALUE"""),8681.0) -> 8681 | O14: =IFERROR(__xludf.DUMMYFUNCTION("""COMPUTED_VALUE"""),"Offline") -> Offline | P14: =IFERROR(__xludf.DUMMYFUNCTION("""COMPUTED_VALUE"""),4529.0) -> 4529 | Q14: =IFERROR(__xludf.DUMMYFUNCTION("""COMPUTED_VALUE"""),651.21) -> 651.21 | R14: =IFERROR(__xludf.DUMMYFUNCTION("""COMPUTED_VALUE"""),524.96) -> 524.96 | S14: =IFERROR(__xludf.DUMMYFUNCTION("""COMPUTED_VALUE"""),2949330.0900000003) -> 2949330.1 | T14: =IFERROR(__xludf.DUMMYFUNCTION("""COMPUTED_VALUE"""),2377543.8400000003) -> 2377543.8 | U14: =IFERROR(__xludf.DUMMYFUNCTION("""COMPUTED_VALUE"""),571786.25) -> 571786.25 | V14: =IFERROR(__xludf.DUMMYFUNCTION("""COMPUTED_VALUE"""),"Office Supplies") -> Office Supplies | W14: =IFERROR(__xludf.DUMMYFUNCTION("""COMPUTED_VALUE"""),"Europe") -> Europe | X14: =IFERROR(__xludf.DUMMYFUNCTION("""COMPUTED_VALUE"""),"Northern Europe") -> Northern Europe | Y14: =IFERROR(__xludf.DUMMYFUNCTION("""COMPUTED_VALUE"""),0.19386987300563563) -> 0.19386987 | Z14: =IFERROR(__xludf.DUMMYFUNCTION("""COMPUTED_VALUE"""),14.0) -> 14 | AA14: =IFERROR(__xludf.DUMMYFUNCTION("""COMPUTED_VALUE"""),2.0) -> 2
A15: =IFERROR(__xludf.DUMMYFUNCTION("""COMPUTED_VALUE"""),1.74614226E8) -> 174614226 | B15: =IFERROR(__xludf.DUMMYFUNCTION("""COMPUTED_VALUE"""),"6/24/2017") -> 6/24/2017 | C15: =IFERROR(__xludf.DUMMYFUNCTION("""COMPUTED_VALUE"""),6.0) -> 6 | D15: =IFERROR(__xludf.DUMMYFUNCTION("""COMPUTED_VALUE"""),24.0) -> 24 | E15: =IFERROR(__xludf.DUMMYFUNCTION("""COMPUTED_VALUE"""),2017.0) -> 2017 | F15: =IFERROR(__xludf.DUMMYFUNCTION("""COMPUTED_VALUE"""),42910.0) -> 42910 | G15: =IFERROR(__xludf.DUMMYFUNCTION("""COMPUTED_VALUE"""),"8/13/2017") -> 8/13/2017 | H15: =IFERROR(__xludf.DUMMYFUNCTION("""COMPUTED_VALUE"""),8.0) -> 8 | I15: =IFERROR(__xludf.DUMMYFUNCTION("""COMPUTED_VALUE"""),13.0) -> 13 | J15: =IFERROR(__xludf.DUMMYFUNCTION("""COMPUTED_VALUE"""),2017.0) -> 2017 | K15: =IFERROR(__xludf.DUMMYFUNCTION("""COMPUTED_VALUE"""),42960.0) -> 42960 | L15: =IFERROR(__xludf.DUMMYFUNCTION("""COMPUTED_VALUE"""),"C") -> C | M15: =IFERROR(__xludf.DUMMYFUNCTION("""COMPUTED_VALUE"""),"AND") -> AND | N15: =IFERROR(__xludf.DUMMYFUNCTION("""COMPUTED_VALUE"""),7331.0) -> 7331 | O15: =IFERROR(__xludf.DUMMYFUNCTION("""COMPUTED_VALUE"""),"Offline") -> Offline | P15: =IFERROR(__xludf.DUMMYFUNCTION("""COMPUTED_VALUE"""),1085.0) -> 1085 | Q15: =IFERROR(__xludf.DUMMYFUNCTION("""COMPUTED_VALUE"""),255.28) -> 255.28 | R15: =IFERROR(__xludf.DUMMYFUNCTION("""COMPUTED_VALUE"""),159.42) -> 159.42 | S15: =IFERROR(__xludf.DUMMYFUNCTION("""COMPUTED_VALUE"""),276978.8) -> 276978.8 | T15: =IFERROR(__xludf.DUMMYFUNCTION("""COMPUTED_VALUE"""),172970.69999999998) -> 172970.7 | U15: =IFERROR(__xludf.DUMMYFUNCTION("""COMPUTED_VALUE"""),104008.1) -> 104008.1 | V15: =IFERROR(__xludf.DUMMYFUNCTION("""COMPUTED_VALUE"""),"Baby Food") -> Baby Food | W15: =IFERROR(__xludf.DUMMYFUNCTION("""COMPUTED_VALUE"""),"Europe") -> Europe | X15: =IFERROR(__xludf.DUMMYFUNCTION("""COMPUTED_VALUE"""),"Southern Europe") -> Southern Europe | Y15: =IFERROR(__xludf.DUMMYFUNCTION("""COMPUTED_VALUE"""),0.37550924475086184) -> 0.37550924 | Z15: =IFERROR(__xludf.DUMMYFUNCTION("""COMPUTED_VALUE"""),50.0) -> 50 | AA15: =IFERROR(__xludf.DUMMYFUNCTION("""COMPUTED_VALUE"""),7.0) -> 7
A16: =IFERROR(__xludf.DUMMYFUNCTION("""COMPUTED_VALUE"""),1.81260526E8) -> 181260526 | B16: =IFERROR(__xludf.DUMMYFUNCTION("""COMPUTED_VALUE"""),42799.0) -> 42799 | C16: =IFERROR(__xludf.DUMMYFUNCTION("""COMPUTED_VALUE"""),5.0) -> 5 | D16: =IFERROR(__xludf.DUMMYFUNCTION("""COMPUTED_VALUE"""),3.0) -> 3 | E16: =IFERROR(__xludf.DUMMYFUNCTION("""COMPUTED_VALUE"""),2017.0) -> 2017 | F16: =IFERROR(__xludf.DUMMYFUNCTION("""COMPUTED_VALUE"""),42858.0) -> 42858 | G16: =IFERROR(__xludf.DUMMYFUNCTION("""COMPUTED_VALUE"""),42800.0) -> 42800 | H16: =IFERROR(__xludf.DUMMYFUNCTION("""COMPUTED_VALUE"""),6.0) -> 6 | I16: =IFERROR(__xludf.DUMMYFUNCTION("""COMPUTED_VALUE"""),3.0) -> 3 | J16: =IFERROR(__xludf.DUMMYFUNCTION("""COMPUTED_VALUE"""),2017.0) -> 2017 | K16: =IFERROR(__xludf.DUMMYFUNCTION("""COMPUTED_VALUE"""),42889.0) -> 42889 | L16: =IFERROR(__xludf.DUMMYFUNCTION("""COMPUTED_VALUE"""),"M") -> M | M16: =IFERROR(__xludf.DUMMYFUNCTION("""COMPUTED_VALUE"""),"UKR") -> UKR | N16: =IFERROR(__xludf.DUMMYFUNCTION("""COMPUTED_VALUE"""),8681.0) -> 8681 | O16: =IFERROR(__xludf.DUMMYFUNCTION("""COMPUTED_VALUE"""),"Offline") -> Offline | P16: =IFERROR(__xludf.DUMMYFUNCTION("""COMPUTED_VALUE"""),7872.0) -> 7872 | Q16: =IFERROR(__xludf.DUMMYFUNCTION("""COMPUTED_VALUE"""),651.21) -> 651.21 | R16: =IFERROR(__xludf.DUMMYFUNCTION("""COMPUTED_VALUE"""),524.96) -> 524.96 | S16: =IFERROR(__xludf.DUMMYFUNCTION("""COMPUTED_VALUE"""),5126325.12) -> 5126325.1 | T16: =IFERROR(__xludf.DUMMYFUNCTION("""COMPUTED_VALUE"""),4132485.12) -> 4132485.1 | U16: =IFERROR(__xludf.DUMMYFUNCTION("""COMPUTED_VALUE"""),993840.0) -> 993840 | V16: =IFERROR(__xludf.DUMMYFUNCTION("""COMPUTED_VALUE"""),"Office Supplies") -> Office Supplies | W16: =IFERROR(__xludf.DUMMYFUNCTION("""COMPUTED_VALUE"""),"Europe") -> Europe | X16: =IFERROR(__xludf.DUMMYFUNCTION("""COMPUTED_VALUE"""),"Eastern Europe") -> Eastern Europe | Y16: =IFERROR(__xludf.DUMMYFUNCTION("""COMPUTED_VALUE"""),0.19386987300563566) -> 0.19386987 | Z16: =IFERROR(__xludf.DUMMYFUNCTION("""COMPUTED_VALUE"""),31.0) -> 31 | AA16: =IFERROR(__xludf.DUMMYFUNCTION("""COMPUTED_VALUE"""),4.0) -> 4
A17: =IFERROR(__xludf.DUMMYFUNCTION("""COMPUTED_VALUE"""),1.86847674E8) -> 186847674 | B17: =IFERROR(__xludf.DUMMYFUNCTION("""COMPUTED_VALUE"""),"4/16/2017") -> 4/16/2017 | C17: =IFERROR(__xludf.DUMMYFUNCTION("""COMPUTED_VALUE"""),4.0) -> 4 | D17: =IFERROR(__xludf.DUMMYFUNCTION("""COMPUTED_VALUE"""),16.0) -> 16 | E17: =IFERROR(__xludf.DUMMYFUNCTION("""COMPUTED_VALUE"""),2017.0) -> 2017 | F17: =IFERROR(__xludf.DUMMYFUNCTION("""COMPUTED_VALUE"""),42841.0) -> 42841 | G17: =IFERROR(__xludf.DUMMYFUNCTION("""COMPUTED_VALUE"""),"4/23/2017") -> 4/23/2017 | H17: =IFERROR(__xludf.DUMMYFUNCTION("""COMPUTED_VALUE"""),4.0) -> 4 | I17: =IFERROR(__xludf.DUMMYFUNCTION("""COMPUTED_VALUE"""),23.0) -> 23 | J17: =IFERROR(__xludf.DUMMYFUNCTION("""COMPUTED_VALUE"""),2017.0) -> 2017 | K17: =IFERROR(__xludf.DUMMYFUNCTION("""COMPUTED_VALUE"""),42848.0) -> 42848 | L17: =IFERROR(__xludf.DUMMYFUNCTION("""COMPUTED_VALUE"""),"M") -> M | M17: =IFERROR(__xludf.DUMMYFUNCTION("""COMPUTED_VALUE"""),"ISL") -> ISL | N17: =IFERROR(__xludf.DUMMYFUNCTION("""COMPUTED_VALUE"""),8293.0) -> 8293 | O17: =IFERROR(__xludf.DUMMYFUNCTION("""COMPUTED_VALUE"""),"Online") -> Online | P17: =IFERROR(__xludf.DUMMYFUNCTION("""COMPUTED_VALUE"""),1234.0) -> 1234 | Q17: =IFERROR(__xludf.DUMMYFUNCTION("""COMPUTED_VALUE"""),437.2) -> 437.2 | R17: =IFERROR(__xludf.DUMMYFUNCTION("""COMPUTED_VALUE"""),263.33) -> 263.33 | S17: =IFERROR(__xludf.DUMMYFUNCTION("""COMPUTED_VALUE"""),539504.7999999999) -> 539504.8 | T17: =IFERROR(__xludf.DUMMYFUNCTION("""COMPUTED_VALUE"""),324949.22) -> 324949.22 | U17: =IFERROR(__xludf.DUMMYFUNCTION("""COMPUTED_VALUE"""),214555.57999999996) -> 214555.58 | V17: =IFERROR(__xludf.DUMMYFUNCTION("""COMPUTED_VALUE"""),"Cosmetics") -> Cosmetics | W17: =IFERROR(__xludf.DUMMYFUNCTION("""COMPUTED_VALUE"""),"Europe") -> Europe | X17: =IFERROR(__xludf.DUMMYFUNCTION("""COMPUTED_VALUE"""),"Northern Europe") -> Northern Europe | Y17: =IFERROR(__xludf.DUMMYFUNCTION("""COMPUTED_VALUE"""),0.39768984446477584) -> 0.39768984 | Z17: =IFERROR(__xludf.DUMMYFUNCTION("""COMPUTED_VALUE"""),7.0) -> 7 | AA17: =IFERROR(__xludf.DUMMYFUNCTION("""COMPUTED_VALUE"""),1.0) -> 1
A18: =IFERROR(__xludf.DUMMYFUNCTION("""COMPUTED_VALUE"""),1.9000281E8) -> 190002810 | B18: =IFERROR(__xludf.DUMMYFUNCTION("""COMPUTED_VALUE"""),"6/20/2017") -> 6/20/2017 | C18: =IFERROR(__xludf.DUMMYFUNCTION("""COMPUTED_VALUE"""),6.0) -> 6 | D18: =IFERROR(__xludf.DUMMYFUNCTION("""COMPUTED_VALUE"""),20.0) -> 20 | E18: =IFERROR(__xludf.DUMMYFUNCTION("""COMPUTED_VALUE"""),2017.0) -> 2017 | F18: =IFERROR(__xludf.DUMMYFUNCTION("""COMPUTED_VALUE"""),42906.0) -> 42906 | G18: =IFERROR(__xludf.DUMMYFUNCTION("""COMPUTED_VALUE"""),42863.0) -> 42863 | H18: =IFERROR(__xludf.DUMMYFUNCTION("""COMPUTED_VALUE"""),8.0) -> 8 | I18: =IFERROR(__xludf.DUMMYFUNCTION("""COMPUTED_VALUE"""),5.0) -> 5 | J18: =IFERROR(__xludf.DUMMYFUNCTION("""COMPUTED_VALUE"""),2017.0) -> 2017 | K18: =IFERROR(__xludf.DUMMYFUNCTION("""COMPUTED_VALUE"""),42952.0) -> 42952 | L18: =IFERROR(__xludf.DUMMYFUNCTION("""COMPUTED_VALUE"""),"C") -> C | M18: =IFERROR(__xludf.DUMMYFUNCTION("""COMPUTED_VALUE"""),"AND") -> AND | N18: =IFERROR(__xludf.DUMMYFUNCTION("""COMPUTED_VALUE"""),2455.0) -> 2455 | O18: =IFERROR(__xludf.DUMMYFUNCTION("""COMPUTED_VALUE"""),"Online") -> Online | P18: =IFERROR(__xludf.DUMMYFUNCTION("""COMPUTED_VALUE"""),4909.0) -> 4909 | Q18: =IFERROR(__xludf.DUMMYFUNCTION("""COMPUTED_VALUE"""),109.28) -> 109.28 | R18: =IFERROR(__xludf.DUMMYFUNCTION("""COMPUTED_VALUE"""),35.84) -> 35.84 | S18: =IFERROR(__xludf.DUMMYFUNCTION("""COMPUTED_VALUE"""),536455.52) -> 536455.52 | T18: =IFERROR(__xludf.DUMMYFUNCTION("""COMPUTED_VALUE"""),175938.56000000003) -> 175938.56 | U18: =IFERROR(__xludf.DUMMYFUNCTION("""COMPUTED_VALUE"""),360516.95999999996) -> 360516.96 | V18: =IFERROR(__xludf.DUMMYFUNCTION("""COMPUTED_VALUE"""),"Clothes") -> Clothes | W18: =IFERROR(__xludf.DUMMYFUNCTION("""COMPUTED_VALUE"""),"Europe") -> Europe | X18: =IFERROR(__xludf.DUMMYFUNCTION("""COMPUTED_VALUE"""),"Southern Europe") -> Southern Europe | Y18: =IFERROR(__xludf.DUMMYFUNCTION("""COMPUTED_VALUE"""),0.67203513909224) -> 0.67203514 | Z18: =IFERROR(__xludf.DUMMYFUNCTION("""COMPUTED_VALUE"""),46.0) -> 46 | AA18: =IFERROR(__xludf.DUMMYFUNCTION("""COMPUTED_VALUE"""),3.0) -> 3
A19: =IFERROR(__xludf.DUMMYFUNCTION("""COMPUTED_VALUE"""),1.92236125E8) -> 192236125 | B19: =IFERROR(__xludf.DUMMYFUNCTION("""COMPUTED_VALUE"""),43042.0) -> 43042 | C19: =IFERROR(__xludf.DUMMYFUNCTION("""COMPUTED_VALUE"""),3.0) -> 3 | D19: =IFERROR(__xludf.DUMMYFUNCTION("""COMPUTED_VALUE"""),11.0) -> 11 | E19: =IFERROR(__xludf.DUMMYFUNCTION("""COMPUTED_VALUE"""),2017.0) -> 2017 | F19: =IFERROR(__xludf.DUMMYFUNCTION("""COMPUTED_VALUE"""),42805.0) -> 42805 | G19: =IFERROR(__xludf.DUMMYFUNCTION("""COMPUTED_VALUE"""),"3/22/2017") -> 3/22/2017 | H19: =IFERROR(__xludf.DUMMYFUNCTION("""COMPUTED_VALUE"""),3.0) -> 3 | I19: =IFERROR(__xludf.DUMMYFUNCTION("""COMPUTED_VALUE"""),22.0) -> 22 | J19: =IFERROR(__xludf.DUMMYFUNCTION("""COMPUTED_VALUE"""),2017.0) -> 2017 | K19: =IFERROR(__xludf.DUMMYFUNCTION("""COMPUTED_VALUE"""),42816.0) -> 42816 | L19: =IFERROR(__xludf.DUMMYFUNCTION("""COMPUTED_VALUE"""),"H") -> H | M19: =IFERROR(__xludf.DUMMYFUNCTION("""COMPUTED_VALUE"""),"HRV") -> HRV | N19: =IFERROR(__xludf.DUMMYFUNCTION("""COMPUTED_VALUE"""),1270.0) -> 1270 | O19: =IFERROR(__xludf.DUMMYFUNCTION("""COMPUTED_VALUE"""),"Offline") -> Offline | P19: =IFERROR(__xludf.DUMMYFUNCTION("""COMPUTED_VALUE"""),5796.0) -> 5796 | Q19: =IFERROR(__xludf.DUMMYFUNCTION("""COMPUTED_VALUE"""),47.45) -> 47.45 | R19: =IFERROR(__xludf.DUMMYFUNCTION("""COMPUTED_VALUE"""),31.79) -> 31.79 | S19: =IFERROR(__xludf.DUMMYFUNCTION("""COMPUTED_VALUE"""),275020.2) -> 275020.2 | T19: =IFERROR(__xludf.DUMMYFUNCTION("""COMPUTED_VALUE"""),184254.84) -> 184254.84 | U19: =IFERROR(__xludf.DUMMYFUNCTION("""COMPUTED_VALUE"""),90765.36000000002) -> 90765.36 | V19: =IFERROR(__xludf.DUMMYFUNCTION("""COMPUTED_VALUE"""),"Beverages") -> Beverages | W19: =IFERROR(__xludf.DUMMYFUNCTION("""COMPUTED_VALUE"""),"Europe") -> Europe | X19: =IFERROR(__xludf.DUMMYFUNCTION("""COMPUTED_VALUE"""),"Southern Europe") -> Southern Europe | Y19: =IFERROR(__xludf.DUMMYFUNCTION("""COMPUTED_VALUE"""),0.3300316122233931) -> 0.33003161 | Z19: =IFERROR(__xludf.DUMMYFUNCTION("""COMPUTED_VALUE"""),11.0) -> 11 | AA19: =IFERROR(__xludf.DUMMYFUNCTION("""COMPUTED_VALUE"""),7.0) -> 7
A20: =IFERROR(__xludf.DUMMYFUNCTION("""COMPUTED_VALUE"""),1.94176757E8) -> 194176757 | B20: =IFERROR(__xludf.DUMMYFUNCTION("""COMPUTED_VALUE"""),43015.0) -> 43015 | C20: =IFERROR(__xludf.DUMMYFUNCTION("""COMPUTED_VALUE"""),7.0) -> 7 | D20: =IFERROR(__xludf.DUMMYFUNCTION("""COMPUTED_VALUE"""),10.0) -> 10 | E20: =IFERROR(__xludf.DUMMYFUNCTION("""COMPUTED_VALUE"""),2017.0) -> 2017 | F20: =IFERROR(__xludf.DUMMYFUNCTION("""COMPUTED_VALUE"""),42926.0) -> 42926 | G20: =IFERROR(__xludf.DUMMYFUNCTION("""COMPUTED_VALUE"""),"8/20/2017") -> 8/20/2017 | H20: =IFERROR(__xludf.DUMMYFUNCTION("""COMPUTED_VALUE"""),8.0) -> 8 | I20: =IFERROR(__xludf.DUMMYFUNCTION("""COMPUTED_VALUE"""),20.0) -> 20 | J20: =IFERROR(__xludf.DUMMYFUNCTION("""COMPUTED_VALUE"""),2017.0) -> 2017 | K20: =IFERROR(__xludf.DUMMYFUNCTION("""COMPUTED_VALUE"""),42967.0) -> 42967 | L20: =IFERROR(__xludf.DUMMYFUNCTION("""COMPUTED_VALUE"""),"M") -> M | M20: =IFERROR(__xludf.DUMMYFUNCTION("""COMPUTED_VALUE"""),"RUS") -> RUS | N20: =IFERROR(__xludf.DUMMYFUNCTION("""COMPUTED_VALUE"""),7940.0) -> 7940 | O20: =IFERROR(__xludf.DUMMYFUNCTION("""COMPUTED_VALUE"""),"Online") -> Online | P20: =IFERROR(__xludf.DUMMYFUNCTION("""COMPUTED_VALUE"""),72.0) -> 72 | Q20: =IFERROR(__xludf.DUMMYFUNCTION("""COMPUTED_VALUE"""),668.27) -> 668.27 | R20: =IFERROR(__xludf.DUMMYFUNCTION("""COMPUTED_VALUE"""),502.54) -> 502.54 | S20: =IFERROR(__xludf.DUMMYFUNCTION("""COMPUTED_VALUE"""),48115.44) -> 48115.44 | T20: =IFERROR(__xludf.DUMMYFUNCTION("""COMPUTED_VALUE"""),36182.880000000005) -> 36182.88 | U20: =IFERROR(__xludf.DUMMYFUNCTION("""COMPUTED_VALUE"""),11932.559999999998) -> 11932.56 | V20: =IFERROR(__xludf.DUMMYFUNCTION("""COMPUTED_VALUE"""),"Household") -> Household | W20: =IFERROR(__xludf.DUMMYFUNCTION("""COMPUTED_VALUE"""),"Europe") -> Europe | X20: =IFERROR(__xludf.DUMMYFUNCTION("""COMPUTED_VALUE"""),"Eastern Europe") -> Eastern Europe | Y20: =IFERROR(__xludf.DUMMYFUNCTION("""COMPUTED_VALUE"""),0.24799856345489094) -> 0.24799856 | Z20: =IFERROR(__xludf.DUMMYFUNCTION("""COMPUTED_VALUE"""),41.0) -> 41 | AA20: =IFERROR(__xludf.DUMMYFUNCTION("""COMPUTED_VALUE"""),2.0) -> 2
A21: =IFERROR(__xludf.DUMMYFUNCTION("""COMPUTED_VALUE"""),2.15584218E8) -> 215584218 | B21: =IFERROR(__xludf.DUMMYFUNCTION("""COMPUTED_VALUE"""),42922.0) -> 42922 | C21: =IFERROR(__xludf.DUMMYFUNCTION("""COMPUTED_VALUE"""),6.0) -> 6 | D21: =IFERROR(__xludf.DUMMYFUNCTION("""COMPUTED_VALUE"""),7.0) -> 7 | E21: =IFERROR(__xludf.DUMMYFUNCTION("""COMPUTED_VALUE"""),2017.0) -> 2017 | F21: =IFERROR(__xludf.DUMMYFUNCTION("""COMPUTED_VALUE"""),42893.0) -> 42893 | G21: =IFERROR(__xludf.DUMMYFUNCTION("""COMPUTED_VALUE"""),"6/21/2017") -> 6/21/2017 | H21: =IFERROR(__xludf.DUMMYFUNCTION("""COMPUTED_VALUE"""),6.0) -> 6 | I21: =IFERROR(__xludf.DUMMYFUNCTION("""COMPUTED_VALUE"""),21.0) -> 21 | J21: =IFERROR(__xludf.DUMMYFUNCTION("""COMPUTED_VALUE"""),2017.0) -> 2017 | K21: =IFERROR(__xludf.DUMMYFUNCTION("""COMPUTED_VALUE"""),42907.0) -> 42907 | L21: =IFERROR(__xludf.DUMMYFUNCTION("""COMPUTED_VALUE"""),"M") -> M | M21: =IFERROR(__xludf.DUMMYFUNCTION("""COMPUTED_VALUE"""),"BLR") -> BLR | N21: =IFERROR(__xludf.DUMMYFUNCTION("""COMPUTED_VALUE"""),5988.0) -> 5988 | O21: =IFERROR(__xludf.DUMMYFUNCTION("""COMPUTED_VALUE"""),"Offline") -> Offline | P21: =IFERROR(__xludf.DUMMYFUNCTION("""COMPUTED_VALUE"""),5016.0) -> 5016 | Q21: =IFERROR(__xludf.DUMMYFUNCTION("""COMPUTED_VALUE"""),154.06) -> 154.06 | R21: =IFERROR(__xludf.DUMMYFUNCTION("""COMPUTED_VALUE"""),90.93) -> 90.93 | S21: =IFERROR(__xludf.DUMMYFUNCTION("""COMPUTED_VALUE"""),772764.96) -> 772764.96 | T21: =IFERROR(__xludf.DUMMYFUNCTION("""COMPUTED_VALUE"""),456104.88000000006) -> 456104.88 | U21: =IFERROR(__xludf.DUMMYFUNCTION("""COMPUTED_VALUE"""),316660.0799999999) -> 316660.08 | V21: =IFERROR(__xludf.DUMMYFUNCTION("""COMPUTED_VALUE"""),"Vegetables") -> Vegetables | W21: =IFERROR(__xludf.DUMMYFUNCTION("""COMPUTED_VALUE"""),"Europe") -> Europe | X21: =IFERROR(__xludf.DUMMYFUNCTION("""COMPUTED_VALUE"""),"Eastern Europe") -> Eastern Europe | Y21: =IFERROR(__xludf.DUMMYFUNCTION("""COMPUTED_VALUE"""),0.40977541217707375) -> 0.40977541 | Z21: =IFERROR(__xludf.DUMMYFUNCTION("""COMPUTED_VALUE"""),14.0) -> 14 | AA21: =IFERROR(__xludf.DUMMYFUNCTION("""COMPUTED_VALUE"""),4.0) -> 4
A22: =IFERROR(__xludf.DUMMYFUNCTION("""COMPUTED_VALUE"""),2.32196319E8) -> 232196319 | B22: =IFERROR(__xludf.DUMMYFUNCTION("""COMPUTED_VALUE"""),42923.0) -> 42923 | C22: =IFERROR(__xludf.DUMMYFUNCTION("""COMPUTED_VALUE"""),7.0) -> 7 | D22: =IFERROR(__xludf.DUMMYFUNCTION("""COMPUTED_VALUE"""),7.0) -> 7 | E22: =IFERROR(__xludf.DUMMYFUNCTION("""COMPUTED_VALUE"""),2017.0) -> 2017 | F22: =IFERROR(__xludf.DUMMYFUNCTION("""COMPUTED_VALUE"""),42923.0) -> 42923 | G22: =IFERROR(__xludf.DUMMYFUNCTION("""COMPUTED_VALUE"""),42833.0) -> 42833 | H22: =IFERROR(__xludf.DUMMYFUNCTION("""COMPUTED_VALUE"""),8.0) -> 8 | I22: =IFERROR(__xludf.DUMMYFUNCTION("""COMPUTED_VALUE"""),4.0) -> 4 | J22: =IFERROR(__xludf.DUMMYFUNCTION("""COMPUTED_VALUE"""),2017.0) -> 2017 | K22: =IFERROR(__xludf.DUMMYFUNCTION("""COMPUTED_VALUE"""),42951.0) -> 42951 | L22: =IFERROR(__xludf.DUMMYFUNCTION("""COMPUTED_VALUE"""),"L") -> L | M22: =IFERROR(__xludf.DUMMYFUNCTION("""COMPUTED_VALUE"""),"POL") -> POL | N22: =IFERROR(__xludf.DUMMYFUNCTION("""COMPUTED_VALUE"""),7940.0) -> 7940 | O22: =IFERROR(__xludf.DUMMYFUNCTION("""COMPUTED_VALUE"""),"Offline") -> Offline | P22: =IFERROR(__xludf.DUMMYFUNCTION("""COMPUTED_VALUE"""),905.0) -> 905 | Q22: =IFERROR(__xludf.DUMMYFUNCTION("""COMPUTED_VALUE"""),668.27) -> 668.27 | R22: =IFERROR(__xludf.DUMMYFUNCTION("""COMPUTED_VALUE"""),502.54) -> 502.54 | S22: =IFERROR(__xludf.DUMMYFUNCTION("""COMPUTED_VALUE"""),604784.35) -> 604784.35 | T22: =IFERROR(__xludf.DUMMYFUNCTION("""COMPUTED_VALUE"""),454798.7) -> 454798.7 | U22: =IFERROR(__xludf.DUMMYFUNCTION("""COMPUTED_VALUE"""),149985.64999999997) -> 149985.65 | V22: =IFERROR(__xludf.DUMMYFUNCTION("""COMPUTED_VALUE"""),"Household") -> Household | W22: =IFERROR(__xludf.DUMMYFUNCTION("""COMPUTED_VALUE"""),"Europe") -> Europe | X22: =IFERROR(__xludf.DUMMYFUNCTION("""COMPUTED_VALUE"""),"Eastern Europe") -> Eastern Europe | Y22: =IFERROR(__xludf.DUMMYFUNCTION("""COMPUTED_VALUE"""),0.24799856345489094) -> 0.24799856 | Z22: =IFERROR(__xludf.DUMMYFUNCTION("""COMPUTED_VALUE"""),28.0) -> 28 | AA22: =IFERROR(__xludf.DUMMYFUNCTION("""COMPUTED_VALUE"""),6.0) -> 6
A23: =IFERROR(__xludf.DUMMYFUNCTION("""COMPUTED_VALUE"""),2.33811223E8) -> 233811223 | B23: =IFERROR(__xludf.DUMMYFUNCTION("""COMPUTED_VALUE"""),"7/20/2017") -> 7/20/2017 | C23: =IFERROR(__xludf.DUMMYFUNCTION("""COMPUTED_VALUE"""),7.0) -> 7 | D23: =IFERROR(__xludf.DUMMYFUNCTION("""COMPUTED_VALUE"""),20.0) -> 20 | E23: =IFERROR(__xludf.DUMMYFUNCTION("""COMPUTED_VALUE"""),2017.0) -> 2017 | F23: =IFERROR(__xludf.DUMMYFUNCTION("""COMPUTED_VALUE"""),42936.0) -> 42936 | G23: =IFERROR(__xludf.DUMMYFUNCTION("""COMPUTED_VALUE"""),"7/20/2017") -> 7/20/2017 | H23: =IFERROR(__xludf.DUMMYFUNCTION("""COMPUTED_VALUE"""),7.0) -> 7 | I23: =IFERROR(__xludf.DUMMYFUNCTION("""COMPUTED_VALUE"""),20.0) -> 20 | J23: =IFERROR(__xludf.DUMMYFUNCTION("""COMPUTED_VALUE"""),2017.0) -> 2017 | K23: =IFERROR(__xludf.DUMMYFUNCTION("""COMPUTED_VALUE"""),42936.0) -> 42936 | L23: =IFERROR(__xludf.DUMMYFUNCTION("""COMPUTED_VALUE"""),"C") -> C | M23: =IFERROR(__xludf.DUMMYFUNCTION("""COMPUTED_VALUE"""),"CHE") -> CHE | N23: =IFERROR(__xludf.DUMMYFUNCTION("""COMPUTED_VALUE"""),8293.0) -> 8293 | O23: =IFERROR(__xludf.DUMMYFUNCTION("""COMPUTED_VALUE"""),"Online") -> Online | P23: =IFERROR(__xludf.DUMMYFUNCTION("""COMPUTED_VALUE"""),8792.0) -> 8792 | Q23: =IFERROR(__xludf.DUMMYFUNCTION("""COMPUTED_VALUE"""),437.2) -> 437.2 | R23: =IFERROR(__xludf.DUMMYFUNCTION("""COMPUTED_VALUE"""),263.33) -> 263.33 | S23: =IFERROR(__xludf.DUMMYFUNCTION("""COMPUTED_VALUE"""),3843862.4) -> 3843862.4 | T23: =IFERROR(__xludf.DUMMYFUNCTION("""COMPUTED_VALUE"""),2315197.36) -> 2315197.4 | U23: =IFERROR(__xludf.DUMMYFUNCTION("""COMPUTED_VALUE"""),1528665.04) -> 1528665 | V23: =IFERROR(__xludf.DUMMYFUNCTION("""COMPUTED_VALUE"""),"Cosmetics") -> Cosmetics | W23: =IFERROR(__xludf.DUMMYFUNCTION("""COMPUTED_VALUE"""),"Europe") -> Europe | X23: =IFERROR(__xludf.DUMMYFUNCTION("""COMPUTED_VALUE"""),"Western Europe") -> Western Europe | Y23: =IFERROR(__xludf.DUMMYFUNCTION("""COMPUTED_VALUE"""),0.39768984446477584) -> 0.39768984 | Z23: =IFERROR(__xludf.DUMMYFUNCTION("""COMPUTED_VALUE"""),0.0) -> 0 | AA23: =IFERROR(__xludf.DUMMYFUNCTION("""COMPUTED_VALUE"""),5.0) -> 5
A24: =IFERROR(__xludf.DUMMYFUNCTION("""COMPUTED_VALUE"""),2.39386355E8) -> 239386355 | B24: =IFERROR(__xludf.DUMMYFUNCTION("""COMPUTED_VALUE"""),42828.0) -> 42828 | C24: =IFERROR(__xludf.DUMMYFUNCTION("""COMPUTED_VALUE"""),3.0) -> 3 | D24: =IFERROR(__xludf.DUMMYFUNCTION("""COMPUTED_VALUE"""),4.0) -> 4 | E24: =IFERROR(__xludf.DUMMYFUNCTION("""COMPUTED_VALUE"""),2017.0) -> 2017 | F24: =IFERROR(__xludf.DUMMYFUNCTION("""COMPUTED_VALUE"""),42798.0) -> 42798 | G24: =IFERROR(__xludf.DUMMYFUNCTION("""COMPUTED_VALUE"""),"4/20/2017") -> 4/20/2017 | H24: =IFERROR(__xludf.DUMMYFUNCTION("""COMPUTED_VALUE"""),4.0) -> 4 | I24: =IFERROR(__xludf.DUMMYFUNCTION("""COMPUTED_VALUE"""),20.0) -> 20 | J24: =IFERROR(__xludf.DUMMYFUNCTION("""COMPUTED_VALUE"""),2017.0) -> 2017 | K24: =IFERROR(__xludf.DUMMYFUNCTION("""COMPUTED_VALUE"""),42845.0) -> 42845 | L24: =IFERROR(__xludf.DUMMYFUNCTION("""COMPUTED_VALUE"""),"L") -> L | M24: =IFERROR(__xludf.DUMMYFUNCTION("""COMPUTED_VALUE"""),"SMR") -> SMR | N24: =IFERROR(__xludf.DUMMYFUNCTION("""COMPUTED_VALUE"""),8681.0) -> 8681 | O24: =IFERROR(__xludf.DUMMYFUNCTION("""COMPUTED_VALUE"""),"Offline") -> Offline | P24: =IFERROR(__xludf.DUMMYFUNCTION("""COMPUTED_VALUE"""),8597.0) -> 8597 | Q24: =IFERROR(__xludf.DUMMYFUNCTION("""COMPUTED_VALUE"""),651.21) -> 651.21 | R24: =IFERROR(__xludf.DUMMYFUNCTION("""COMPUTED_VALUE"""),524.96) -> 524.96 | S24: =IFERROR(__xludf.DUMMYFUNCTION("""COMPUTED_VALUE"""),5598452.37) -> 5598452.4 | T24: =IFERROR(__xludf.DUMMYFUNCTION("""COMPUTED_VALUE"""),4513081.12) -> 4513081.1 | U24: =IFERROR(__xludf.DUMMYFUNCTION("""COMPUTED_VALUE"""),1085371.25) -> 1085371.2 | V24: =IFERROR(__xludf.DUMMYFUNCTION("""COMPUTED_VALUE"""),"Office Supplies") -> Office Supplies | W24: =IFERROR(__xludf.DUMMYFUNCTION("""COMPUTED_VALUE"""),"Europe") -> Europe | X24: =IFERROR(__xludf.DUMMYFUNCTION("""COMPUTED_VALUE"""),"Southern Europe") -> Southern Europe | Y24: =IFERROR(__xludf.DUMMYFUNCTION("""COMPUTED_VALUE"""),0.19386987300563566) -> 0.19386987 | Z24: =IFERROR(__xludf.DUMMYFUNCTION("""COMPUTED_VALUE"""),47.0) -> 47 | AA24: =IFERROR(__xludf.DUMMYFUNCTION("""COMPUTED_VALUE"""),7.0) -> 7
A25: =IFERROR(__xludf.DUMMYFUNCTION("""COMPUTED_VALUE"""),2.41392648E8) -> 241392648 | B25: =IFERROR(__xludf.DUMMYFUNCTION("""COMPUTED_VALUE"""),"2/22/2017") -> 2/22/2017 | C25: =IFERROR(__xludf.DUMMYFUNCTION("""COMPUTED_VALUE"""),2.0) -> 2 | D25: =IFERROR(__xludf.DUMMYFUNCTION("""COMPUTED_VALUE"""),22.0) -> 22 | E25: =IFERROR(__xludf.DUMMYFUNCTION("""COMPUTED_VALUE"""),2017.0) -> 2017 | F25: =IFERROR(__xludf.DUMMYFUNCTION("""COMPUTED_VALUE"""),42788.0) -> 42788 | G25: =IFERROR(__xludf.DUMMYFUNCTION("""COMPUTED_VALUE"""),"3/16/2017") -> 3/16/2017 | H25: =IFERROR(__xludf.DUMMYFUNCTION("""COMPUTED_VALUE"""),3.0) -> 3 | I25: =IFERROR(__xludf.DUMMYFUNCTION("""COMPUTED_VALUE"""),16.0) -> 16 | J25: =IFERROR(__xludf.DUMMYFUNCTION("""COMPUTED_VALUE"""),2017.0) -> 2017 | K25: =IFERROR(__xludf.DUMMYFUNCTION("""COMPUTED_VALUE"""),42810.0) -> 42810 | L25: =IFERROR(__xludf.DUMMYFUNCTION("""COMPUTED_VALUE"""),"H") -> H | M25: =IFERROR(__xludf.DUMMYFUNCTION("""COMPUTED_VALUE"""),"MKD") -> MKD | N25: =IFERROR(__xludf.DUMMYFUNCTION("""COMPUTED_VALUE"""),7940.0) -> 7940 | O25: =IFERROR(__xludf.DUMMYFUNCTION("""COMPUTED_VALUE"""),"Online") -> Online | P25: =IFERROR(__xludf.DUMMYFUNCTION("""COMPUTED_VALUE"""),2304.0) -> 2304 | Q25: =IFERROR(__xludf.DUMMYFUNCTION("""COMPUTED_VALUE"""),668.27) -> 668.27 | R25: =IFERROR(__xludf.DUMMYFUNCTION("""COMPUTED_VALUE"""),502.54) -> 502.54 | S25: =IFERROR(__xludf.DUMMYFUNCTION("""COMPUTED_VALUE"""),1539694.08) -> 1539694.1 | T25: =IFERROR(__xludf.DUMMYFUNCTION("""COMPUTED_VALUE"""),1157852.1600000001) -> 1157852.2 | U25: =IFERROR(__xludf.DUMMYFUNCTION("""COMPUTED_VALUE"""),381841.9199999999) -> 381841.92 | V25: =IFERROR(__xludf.DUMMYFUNCTION("""COMPUTED_VALUE"""),"Household") -> Household | W25: =IFERROR(__xludf.DUMMYFUNCTION("""COMPUTED_VALUE"""),"Europe") -> Europe | X25: =IFERROR(__xludf.DUMMYFUNCTION("""COMPUTED_VALUE"""),"Southern Europe") -> Southern Europe | Y25: =IFERROR(__xludf.DUMMYFUNCTION("""COMPUTED_VALUE"""),0.24799856345489094) -> 0.24799856 | Z25: =IFERROR(__xludf.DUMMYFUNCTION("""COMPUTED_VALUE"""),22.0) -> 22 | AA25: =IFERROR(__xludf.DUMMYFUNCTION("""COMPUTED_VALUE"""),4.0) -> 4
A26: =IFERROR(__xludf.DUMMYFUNCTION("""COMPUTED_VALUE"""),2.43684327E8) -> 243684327 | B26: =IFERROR(__xludf.DUMMYFUNCTION("""COMPUTED_VALUE"""),"5/23/2017") -> 5/23/2017 | C26: =IFERROR(__xludf.DUMMYFUNCTION("""COMPUTED_VALUE"""),5.0) -> 5 | D26: =IFERROR(__xludf.DUMMYFUNCTION("""COMPUTED_VALUE"""),23.0) -> 23 | E26: =IFERROR(__xludf.DUMMYFUNCTION("""COMPUTED_VALUE"""),2017.0) -> 2017 | F26: =IFERROR(__xludf.DUMMYFUNCTION("""COMPUTED_VALUE"""),42878.0) -> 42878 | G26: =IFERROR(__xludf.DUMMYFUNCTION("""COMPUTED_VALUE"""),"5/30/2017") -> 5/30/2017 | H26: =IFERROR(__xludf.DUMMYFUNCTION("""COMPUTED_VALUE"""),5.0) -> 5 | I26: =IFERROR(__xludf.DUMMYFUNCTION("""COMPUTED_VALUE"""),30.0) -> 30 | J26: =IFERROR(__xludf.DUMMYFUNCTION("""COMPUTED_VALUE"""),2017.0) -> 2017 | K26: =IFERROR(__xludf.DUMMYFUNCTION("""COMPUTED_VALUE"""),42885.0) -> 42885 | L26: =IFERROR(__xludf.DUMMYFUNCTION("""COMPUTED_VALUE"""),"H") -> H | M26: =IFERROR(__xludf.DUMMYFUNCTION("""COMPUTED_VALUE"""),"IRL") -> IRL | N26: =IFERROR(__xludf.DUMMYFUNCTION("""COMPUTED_VALUE"""),7331.0) -> 7331 | O26: =IFERROR(__xludf.DUMMYFUNCTION("""COMPUTED_VALUE"""),"Online") -> Online | P26: =IFERROR(__xludf.DUMMYFUNCTION("""COMPUTED_VALUE"""),462.0) -> 462 | Q26: =IFERROR(__xludf.DUMMYFUNCTION("""COMPUTED_VALUE"""),255.28) -> 255.28 | R26: =IFERROR(__xludf.DUMMYFUNCTION("""COMPUTED_VALUE"""),159.42) -> 159.42 | S26: =IFERROR(__xludf.DUMMYFUNCTION("""COMPUTED_VALUE"""),117939.36) -> 117939.36 | T26: =IFERROR(__xludf.DUMMYFUNCTION("""COMPUTED_VALUE"""),73652.04) -> 73652.04 | U26: =IFERROR(__xludf.DUMMYFUNCTION("""COMPUTED_VALUE"""),44287.32000000001) -> 44287.32 | V26: =IFERROR(__xludf.DUMMYFUNCTION("""COMPUTED_VALUE"""),"Baby Food") -> Baby Food | W26: =IFERROR(__xludf.DUMMYFUNCTION("""COMPUTED_VALUE"""),"Europe") -> Europe | X26: =IFERROR(__xludf.DUMMYFUNCTION("""COMPUTED_VALUE"""),"Northern Europe") -> Northern Europe | Y26: =IFERROR(__xludf.DUMMYFUNCTION("""COMPUTED_VALUE"""),0.37550924475086184) -> 0.37550924 | Z26: =IFERROR(__xludf.DUMMYFUNCTION("""COMPUTED_VALUE"""),7.0) -> 7 | AA26: =IFERROR(__xludf.DUMMYFUNCTION("""COMPUTED_VALUE"""),3.0) -> 3
A27: =IFERROR(__xludf.DUMMYFUNCTION("""COMPUTED_VALUE"""),2.52541625E8) -> 252541625 | B27: =IFERROR(__xludf.DUMMYFUNCTION("""COMPUTED_VALUE"""),42984.0) -> 42984 | C27: =IFERROR(__xludf.DUMMYFUNCTION("""COMPUTED_VALUE"""),6.0) -> 6 | D27: =IFERROR(__xludf.DUMMYFUNCTION("""COMPUTED_VALUE"""),9.0) -> 9 | E27: =IFERROR(__xludf.DUMMYFUNCTION("""COMPUTED_VALUE"""),2017.0) -> 2017 | F27: =IFERROR(__xludf.DUMMYFUNCTION("""COMPUTED_VALUE"""),42895.0) -> 42895 | G27: =IFERROR(__xludf.DUMMYFUNCTION("""COMPUTED_VALUE"""),42862.0) -> 42862 | H27: =IFERROR(__xludf.DUMMYFUNCTION("""COMPUTED_VALUE"""),7.0) -> 7 | I27: =IFERROR(__xludf.DUMMYFUNCTION("""COMPUTED_VALUE"""),5.0) -> 5 | J27: =IFERROR(__xludf.DUMMYFUNCTION("""COMPUTED_VALUE"""),2017.0) -> 2017 | K27: =IFERROR(__xludf.DUMMYFUNCTION("""COMPUTED_VALUE"""),42921.0) -> 42921 | L27: =IFERROR(__xludf.DUMMYFUNCTION("""COMPUTED_VALUE"""),"C") -> C | M27: =IFERROR(__xludf.DUMMYFUNCTION("""COMPUTED_VALUE"""),"Desconhecido") -> Desconhecido | N27: =IFERROR(__xludf.DUMMYFUNCTION("""COMPUTED_VALUE"""),7331.0) -> 7331 | O27: =IFERROR(__xludf.DUMMYFUNCTION("""COMPUTED_VALUE"""),"Offline") -> Offline | P27: =IFERROR(__xludf.DUMMYFUNCTION("""COMPUTED_VALUE"""),1534.0) -> 1534 | Q27: =IFERROR(__xludf.DUMMYFUNCTION("""COMPUTED_VALUE"""),255.28) -> 255.28 | R27: =IFERROR(__xludf.DUMMYFUNCTION("""COMPUTED_VALUE"""),159.42) -> 159.42 | S27: =IFERROR(__xludf.DUMMYFUNCTION("""COMPUTED_VALUE"""),391599.52) -> 391599.52 | T27: =IFERROR(__xludf.DUMMYFUNCTION("""COMPUTED_VALUE"""),244550.27999999997) -> 244550.28 | U27: =IFERROR(__xludf.DUMMYFUNCTION("""COMPUTED_VALUE"""),147049.24000000005) -> 147049.24 | V27: =IFERROR(__xludf.DUMMYFUNCTION("""COMPUTED_VALUE"""),"Baby Food") -> Baby Food | W27: =IFERROR(__xludf.DUMMYFUNCTION("""COMPUTED_VALUE"""),"Desconhecido") -> Desconhecido | X27: =IFERROR(__xludf.DUMMYFUNCTION("""COMPUTED_VALUE"""),"Desconhecido") -> Desconhecido | Y27: =IFERROR(__xludf.DUMMYFUNCTION("""COMPUTED_VALUE"""),0.3755092447508619) -> 0.37550924 | Z27: =IFERROR(__xludf.DUMMYFUNCTION("""COMPUTED_VALUE"""),26.0) -> 26 | AA27: =IFERROR(__xludf.DUMMYFUNCTION("""COMPUTED_VALUE"""),6.0) -> 6
A28: =IFERROR(__xludf.DUMMYFUNCTION("""COMPUTED_VALUE"""),2.59032571E8) -> 259032571 | B28: =IFERROR(__xludf.DUMMYFUNCTION("""COMPUTED_VALUE"""),42983.0) -> 42983 | C28: =IFERROR(__xludf.DUMMYFUNCTION("""COMPUTED_VALUE"""),5.0) -> 5 | D28: =IFERROR(__xludf.DUMMYFUNCTION("""COMPUTED_VALUE"""),9.0) -> 9 | E28: =IFERROR(__xludf.DUMMYFUNCTION("""COMPUTED_VALUE"""),2017.0) -> 2017 | F28: =IFERROR(__xludf.DUMMYFUNCTION("""COMPUTED_VALUE"""),42864.0) -> 42864 | G28: =IFERROR(__xludf.DUMMYFUNCTION("""COMPUTED_VALUE"""),"5/13/2017") -> 5/13/2017 | H28: =IFERROR(__xludf.DUMMYFUNCTION("""COMPUTED_VALUE"""),5.0) -> 5 | I28: =IFERROR(__xludf.DUMMYFUNCTION("""COMPUTED_VALUE"""),13.0) -> 13 | J28: =IFERROR(__xludf.DUMMYFUNCTION("""COMPUTED_VALUE"""),2017.0) -> 2017 | K28: =IFERROR(__xludf.DUMMYFUNCTION("""COMPUTED_VALUE"""),42868.0) -> 42868 | L28: =IFERROR(__xludf.DUMMYFUNCTION("""COMPUTED_VALUE"""),"L") -> L | M28: =IFERROR(__xludf.DUMMYFUNCTION("""COMPUTED_VALUE"""),"BEL") -> BEL | N28: =IFERROR(__xludf.DUMMYFUNCTION("""COMPUTED_VALUE"""),5988.0) -> 5988 | O28: =IFERROR(__xludf.DUMMYFUNCTION("""COMPUTED_VALUE"""),"Online") -> Online | P28: =IFERROR(__xludf.DUMMYFUNCTION("""COMPUTED_VALUE"""),2349.0) -> 2349 | Q28: =IFERROR(__xludf.DUMMYFUNCTION("""COMPUTED_VALUE"""),154.06) -> 154.06 | R28: =IFERROR(__xludf.DUMMYFUNCTION("""COMPUTED_VALUE"""),90.93) -> 90.93 | S28: =IFERROR(__xludf.DUMMYFUNCTION("""COMPUTED_VALUE"""),361886.94) -> 361886.94 | T28: =IFERROR(__xludf.DUMMYFUNCTION("""COMPUTED_VALUE"""),213594.57) -> 213594.57 | U28: =IFERROR(__xludf.DUMMYFUNCTION("""COMPUTED_VALUE"""),148292.37) -> 148292.37 | V28: =IFERROR(__xludf.DUMMYFUNCTION("""COMPUTED_VALUE"""),"Vegetables") -> Vegetables | W28: =IFERROR(__xludf.DUMMYFUNCTION("""COMPUTED_VALUE"""),"Europe") -> Europe | X28: =IFERROR(__xludf.DUMMYFUNCTION("""COMPUTED_VALUE"""),"Western Europe") -> Western Europe | Y28: =IFERROR(__xludf.DUMMYFUNCTION("""COMPUTED_VALUE"""),0.40977541217707386) -> 0.40977541 | Z28: =IFERROR(__xludf.DUMMYFUNCTION("""COMPUTED_VALUE"""),4.0) -> 4 | AA28: =IFERROR(__xludf.DUMMYFUNCTION("""COMPUTED_VALUE"""),3.0) -> 3
A29: =IFERROR(__xludf.DUMMYFUNCTION("""COMPUTED_VALUE"""),2.74694526E8) -> 274694526 | B29: =IFERROR(__xludf.DUMMYFUNCTION("""COMPUTED_VALUE"""),"4/13/2017") -> 4/13/2017 | C29: =IFERROR(__xludf.DUMMYFUNCTION("""COMPUTED_VALUE"""),4.0) -> 4 | D29: =IFERROR(__xludf.DUMMYFUNCTION("""COMPUTED_VALUE"""),13.0) -> 13 | E29: =IFERROR(__xludf.DUMMYFUNCTION("""COMPUTED_VALUE"""),2017.0) -> 2017 | F29: =IFERROR(__xludf.DUMMYFUNCTION("""COMPUTED_VALUE"""),42838.0) -> 42838 | G29: =IFERROR(__xludf.DUMMYFUNCTION("""COMPUTED_VALUE"""),43044.0) -> 43044 | H29: =IFERROR(__xludf.DUMMYFUNCTION("""COMPUTED_VALUE"""),5.0) -> 5 | I29: =IFERROR(__xludf.DUMMYFUNCTION("""COMPUTED_VALUE"""),11.0) -> 11 | J29: =IFERROR(__xludf.DUMMYFUNCTION("""COMPUTED_VALUE"""),2017.0) -> 2017 | K29: =IFERROR(__xludf.DUMMYFUNCTION("""COMPUTED_VALUE"""),42866.0) -> 42866 | L29: =IFERROR(__xludf.DUMMYFUNCTION("""COMPUTED_VALUE"""),"C") -> C | M29: =IFERROR(__xludf.DUMMYFUNCTION("""COMPUTED_VALUE"""),"MLT") -> MLT | N29: =IFERROR(__xludf.DUMMYFUNCTION("""COMPUTED_VALUE"""),3127.0) -> 3127 | O29: =IFERROR(__xludf.DUMMYFUNCTION("""COMPUTED_VALUE"""),"Offline") -> Offline | P29: =IFERROR(__xludf.DUMMYFUNCTION("""COMPUTED_VALUE"""),7069.0) -> 7069 | Q29: =IFERROR(__xludf.DUMMYFUNCTION("""COMPUTED_VALUE"""),81.73) -> 81.73 | R29: =IFERROR(__xludf.DUMMYFUNCTION("""COMPUTED_VALUE"""),56.67) -> 56.67 | S29: =IFERROR(__xludf.DUMMYFUNCTION("""COMPUTED_VALUE"""),577749.37) -> 577749.37 | T29: =IFERROR(__xludf.DUMMYFUNCTION("""COMPUTED_VALUE"""),400600.23000000004) -> 400600.23 | U29: =IFERROR(__xludf.DUMMYFUNCTION("""COMPUTED_VALUE"""),177149.13999999996) -> 177149.14 | V29: =IFERROR(__xludf.DUMMYFUNCTION("""COMPUTED_VALUE"""),"Personal Care") -> Personal Care | W29: =IFERROR(__xludf.DUMMYFUNCTION("""COMPUTED_VALUE"""),"Europe") -> Europe | X29: =IFERROR(__xludf.DUMMYFUNCTION("""COMPUTED_VALUE"""),"Southern Europe") -> Southern Europe | Y29: =IFERROR(__xludf.DUMMYFUNCTION("""COMPUTED_VALUE"""),0.30661935641747207) -> 0.30661936 | Z29: =IFERROR(__xludf.DUMMYFUNCTION("""COMPUTED_VALUE"""),28.0) -> 28 | AA29: =IFERROR(__xludf.DUMMYFUNCTION("""COMPUTED_VALUE"""),5.0) -> 5
A30: =IFERROR(__xludf.DUMMYFUNCTION("""COMPUTED_VALUE"""),2.91179597E8) -> 291179597 | B30: =IFERROR(__xludf.DUMMYFUNCTION("""COMPUTED_VALUE"""),"2/13/2017") -> 2/13/2017 | C30: =IFERROR(__xludf.DUMMYFUNCTION("""COMPUTED_VALUE"""),2.0) -> 2 | D30: =IFERROR(__xludf.DUMMYFUNCTION("""COMPUTED_VALUE"""),13.0) -> 13 | E30: =IFERROR(__xludf.DUMMYFUNCTION("""COMPUTED_VALUE"""),2017.0) -> 2017 | F30: =IFERROR(__xludf.DUMMYFUNCTION("""COMPUTED_VALUE"""),42779.0) -> 42779 | G30: =IFERROR(__xludf.DUMMYFUNCTION("""COMPUTED_VALUE"""),"2/20/2017") -> 2/20/2017 | H30: =IFERROR(__xludf.DUMMYFUNCTION("""COMPUTED_VALUE"""),2.0) -> 2 | I30: =IFERROR(__xludf.DUMMYFUNCTION("""COMPUTED_VALUE"""),20.0) -> 20 | J30: =IFERROR(__xludf.DUMMYFUNCTION("""COMPUTED_VALUE"""),2017.0) -> 2017 | K30: =IFERROR(__xludf.DUMMYFUNCTION("""COMPUTED_VALUE"""),42786.0) -> 42786 | L30: =IFERROR(__xludf.DUMMYFUNCTION("""COMPUTED_VALUE"""),"H") -> H | M30: =IFERROR(__xludf.DUMMYFUNCTION("""COMPUTED_VALUE"""),"LIE") -> LIE | N30: =IFERROR(__xludf.DUMMYFUNCTION("""COMPUTED_VALUE"""),7940.0) -> 7940 | O30: =IFERROR(__xludf.DUMMYFUNCTION("""COMPUTED_VALUE"""),"Online") -> Online | P30: =IFERROR(__xludf.DUMMYFUNCTION("""COMPUTED_VALUE"""),5368.0) -> 5368 | Q30: =IFERROR(__xludf.DUMMYFUNCTION("""COMPUTED_VALUE"""),668.27) -> 668.27 | R30: =IFERROR(__xludf.DUMMYFUNCTION("""COMPUTED_VALUE"""),502.54) -> 502.54 | S30: =IFERROR(__xludf.DUMMYFUNCTION("""COMPUTED_VALUE"""),3587273.36) -> 3587273.4 | T30: =IFERROR(__xludf.DUMMYFUNCTION("""COMPUTED_VALUE"""),2697634.72) -> 2697634.7 | U30: =IFERROR(__xludf.DUMMYFUNCTION("""COMPUTED_VALUE"""),889638.6399999997) -> 889638.64 | V30: =IFERROR(__xludf.DUMMYFUNCTION("""COMPUTED_VALUE"""),"Household") -> Household | W30: =IFERROR(__xludf.DUMMYFUNCTION("""COMPUTED_VALUE"""),"Europe") -> Europe | X30: =IFERROR(__xludf.DUMMYFUNCTION("""COMPUTED_VALUE"""),"Western Europe") -> Western Europe | Y30: =IFERROR(__xludf.DUMMYFUNCTION("""COMPUTED_VALUE"""),0.2479985634548909) -> 0.24799856 | Z30: =IFERROR(__xludf.DUMMYFUNCTION("""COMPUTED_VALUE"""),7.0) -> 7 | AA30: =IFERROR(__xludf.DUMMYFUNCTION("""COMPUTED_VALUE"""),2.0) -> 2
A31: =IFERROR(__xludf.DUMMYFUNCTION("""COMPUTED_VALUE"""),2.91611325E8) -> 291611325 | B31: =IFERROR(__xludf.DUMMYFUNCTION("""COMPUTED_VALUE"""),42737.0) -> 42737 | C31: =IFERROR(__xludf.DUMMYFUNCTION("""COMPUTED_VALUE"""),2.0) -> 2 | D31: =IFERROR(__xludf.DUMMYFUNCTION("""COMPUTED_VALUE"""),1.0) -> 1 | E31: =IFERROR(__xludf.DUMMYFUNCTION("""COMPUTED_VALUE"""),2017.0) -> 2017 | F31: =IFERROR(__xludf.DUMMYFUNCTION("""COMPUTED_VALUE"""),42767.0) -> 42767 | G31: =IFERROR(__xludf.DUMMYFUNCTION("""COMPUTED_VALUE"""),43010.0) -> 43010 | H31: =IFERROR(__xludf.DUMMYFUNCTION("""COMPUTED_VALUE"""),2.0) -> 2 | I31: =IFERROR(__xludf.DUMMYFUNCTION("""COMPUTED_VALUE"""),10.0) -> 10 | J31: =IFERROR(__xludf.DUMMYFUNCTION("""COMPUTED_VALUE"""),2017.0) -> 2017 | K31: =IFERROR(__xludf.DUMMYFUNCTION("""COMPUTED_VALUE"""),42776.0) -> 42776 | L31: =IFERROR(__xludf.DUMMYFUNCTION("""COMPUTED_VALUE"""),"M") -> M | M31: =IFERROR(__xludf.DUMMYFUNCTION("""COMPUTED_VALUE"""),"HUN") -> HUN | N31: =IFERROR(__xludf.DUMMYFUNCTION("""COMPUTED_VALUE"""),8969.0) -> 8969 | O31: =IFERROR(__xludf.DUMMYFUNCTION("""COMPUTED_VALUE"""),"Offline") -> Offline | P31: =IFERROR(__xludf.DUMMYFUNCTION("""COMPUTED_VALUE"""),3126.0) -> 3126 | Q31: =IFERROR(__xludf.DUMMYFUNCTION("""COMPUTED_VALUE"""),152.58) -> 152.58 | R31: =IFERROR(__xludf.DUMMYFUNCTION("""COMPUTED_VALUE"""),97.44) -> 97.44 | S31: =IFERROR(__xludf.DUMMYFUNCTION("""COMPUTED_VALUE"""),476965.08) -> 476965.08 | T31: =IFERROR(__xludf.DUMMYFUNCTION("""COMPUTED_VALUE"""),304597.44) -> 304597.44 | U31: =IFERROR(__xludf.DUMMYFUNCTION("""COMPUTED_VALUE"""),172367.64) -> 172367.64 | V31: =IFERROR(__xludf.DUMMYFUNCTION("""COMPUTED_VALUE"""),"Snacks") -> Snacks | W31: =IFERROR(__xludf.DUMMYFUNCTION("""COMPUTED_VALUE"""),"Europe") -> Europe | X31: =IFERROR(__xludf.DUMMYFUNCTION("""COMPUTED_VALUE"""),"Eastern Europe") -> Eastern Europe | Y31: =IFERROR(__xludf.DUMMYFUNCTION("""COMPUTED_VALUE"""),0.3613841918993315) -> 0.36138419 | Z31: =IFERROR(__xludf.DUMMYFUNCTION("""COMPUTED_VALUE"""),9.0) -> 9 | AA31: =IFERROR(__xludf.DUMMYFUNCTION("""COMPUTED_VALUE"""),4.0) -> 4
A32: =IFERROR(__xludf.DUMMYFUNCTION("""COMPUTED_VALUE"""),3.09285581E8) -> 309285581 | B32: =IFERROR(__xludf.DUMMYFUNCTION("""COMPUTED_VALUE"""),"2/26/2017") -> 2/26/2017 | C32: =IFERROR(__xludf.DUMMYFUNCTION("""COMPUTED_VALUE"""),2.0) -> 2 | D32: =IFERROR(__xludf.DUMMYFUNCTION("""COMPUTED_VALUE"""),26.0) -> 26 | E32: =IFERROR(__xludf.DUMMYFUNCTION("""COMPUTED_VALUE"""),2017.0) -> 2017 | F32: =IFERROR(__xludf.DUMMYFUNCTION("""COMPUTED_VALUE"""),42792.0) -> 42792 | G32: =IFERROR(__xludf.DUMMYFUNCTION("""COMPUTED_VALUE"""),"4/17/2017") -> 4/17/2017 | H32: =IFERROR(__xludf.DUMMYFUNCTION("""COMPUTED_VALUE"""),4.0) -> 4 | I32: =IFERROR(__xludf.DUMMYFUNCTION("""COMPUTED_VALUE"""),17.0) -> 17 | J32: =IFERROR(__xludf.DUMMYFUNCTION("""COMPUTED_VALUE"""),2017.0) -> 2017 | K32: =IFERROR(__xludf.DUMMYFUNCTION("""COMPUTED_VALUE"""),42842.0) -> 42842 | L32: =IFERROR(__xludf.DUMMYFUNCTION("""COMPUTED_VALUE"""),"H") -> H | M32: =IFERROR(__xludf.DUMMYFUNCTION("""COMPUTED_VALUE"""),"IRL") -> IRL | N32: =IFERROR(__xludf.DUMMYFUNCTION("""COMPUTED_VALUE"""),3127.0) -> 3127 | O32: =IFERROR(__xludf.DUMMYFUNCTION("""COMPUTED_VALUE"""),"Offline") -> Offline | P32: =IFERROR(__xludf.DUMMYFUNCTION("""COMPUTED_VALUE"""),3331.0) -> 3331 | Q32: =IFERROR(__xludf.DUMMYFUNCTION("""COMPUTED_VALUE"""),81.73) -> 81.73 | R32: =IFERROR(__xludf.DUMMYFUNCTION("""COMPUTED_VALUE"""),56.67) -> 56.67 | S32: =IFERROR(__xludf.DUMMYFUNCTION("""COMPUTED_VALUE"""),272242.63) -> 272242.63 | T32: =IFERROR(__xludf.DUMMYFUNCTION("""COMPUTED_VALUE"""),188767.77000000002) -> 188767.77 | U32: =IFERROR(__xludf.DUMMYFUNCTION("""COMPUTED_VALUE"""),83474.85999999999) -> 83474.86 | V32: =IFERROR(__xludf.DUMMYFUNCTION("""COMPUTED_VALUE"""),"Personal Care") -> Personal Care | W32: =IFERROR(__xludf.DUMMYFUNCTION("""COMPUTED_VALUE"""),"Europe") -> Europe | X32: =IFERROR(__xludf.DUMMYFUNCTION("""COMPUTED_VALUE"""),"Northern Europe") -> Northern Europe | Y32: =IFERROR(__xludf.DUMMYFUNCTION("""COMPUTED_VALUE"""),0.3066193564174721) -> 0.30661936 | Z32: =IFERROR(__xludf.DUMMYFUNCTION("""COMPUTED_VALUE"""),50.0) -> 50 | AA32: =IFERROR(__xludf.DUMMYFUNCTION("""COMPUTED_VALUE"""),1.0) -> 1
A33: =IFERROR(__xludf.DUMMYFUNCTION("""COMPUTED_VALUE"""),3.11956632E8) -> 311956632 | B33: =IFERROR(__xludf.DUMMYFUNCTION("""COMPUTED_VALUE"""),42826.0) -> 42826 | C33: =IFERROR(__xludf.DUMMYFUNCTION("""COMPUTED_VALUE"""),1.0) -> 1 | D33: =IFERROR(__xludf.DUMMYFUNCTION("""COMPUTED_VALUE"""),4.0) -> 4 | E33: =IFERROR(__xludf.DUMMYFUNCTION("""COMPUTED_VALUE"""),2017.0) -> 2017 | F33: =IFERROR(__xludf.DUMMYFUNCTION("""COMPUTED_VALUE"""),42739.0) -> 42739 | G33: =IFERROR(__xludf.DUMMYFUNCTION("""COMPUTED_VALUE"""),43009.0) -> 43009 | H33: =IFERROR(__xludf.DUMMYFUNCTION("""COMPUTED_VALUE"""),1.0) -> 1 | I33: =IFERROR(__xludf.DUMMYFUNCTION("""COMPUTED_VALUE"""),10.0) -> 10 | J33: =IFERROR(__xludf.DUMMYFUNCTION("""COMPUTED_VALUE"""),2017.0) -> 2017 | K33: =IFERROR(__xludf.DUMMYFUNCTION("""COMPUTED_VALUE"""),42745.0) -> 42745 | L33: =IFERROR(__xludf.DUMMYFUNCTION("""COMPUTED_VALUE"""),"C") -> C | M33: =IFERROR(__xludf.DUMMYFUNCTION("""COMPUTED_VALUE"""),"EST") -> EST | N33: =IFERROR(__xludf.DUMMYFUNCTION("""COMPUTED_VALUE"""),8293.0) -> 8293 | O33: =IFERROR(__xludf.DUMMYFUNCTION("""COMPUTED_VALUE"""),"Offline") -> Offline | P33: =IFERROR(__xludf.DUMMYFUNCTION("""COMPUTED_VALUE"""),3755.0) -> 3755 | Q33: =IFERROR(__xludf.DUMMYFUNCTION("""COMPUTED_VALUE"""),437.2) -> 437.2 | R33: =IFERROR(__xludf.DUMMYFUNCTION("""COMPUTED_VALUE"""),263.33) -> 263.33 | S33: =IFERROR(__xludf.DUMMYFUNCTION("""COMPUTED_VALUE"""),1641686.0) -> 1641686 | T33: =IFERROR(__xludf.DUMMYFUNCTION("""COMPUTED_VALUE"""),988804.1499999999) -> 988804.15 | U33: =IFERROR(__xludf.DUMMYFUNCTION("""COMPUTED_VALUE"""),652881.8500000001) -> 652881.85 | V33: =IFERROR(__xludf.DUMMYFUNCTION("""COMPUTED_VALUE"""),"Cosmetics") -> Cosmetics | W33: =IFERROR(__xludf.DUMMYFUNCTION("""COMPUTED_VALUE"""),"Europe") -> Europe | X33: =IFERROR(__xludf.DUMMYFUNCTION("""COMPUTED_VALUE"""),"Northern Europe") -> Northern Europe | Y33: =IFERROR(__xludf.DUMMYFUNCTION("""COMPUTED_VALUE"""),0.3976898444647759) -> 0.39768984 | Z33: =IFERROR(__xludf.DUMMYFUNCTION("""COMPUTED_VALUE"""),6.0) -> 6 | AA33: =IFERROR(__xludf.DUMMYFUNCTION("""COMPUTED_VALUE"""),4.0) -> 4
A34: =IFERROR(__xludf.DUMMYFUNCTION("""COMPUTED_VALUE"""),3.17006051E8) -> 317006051 | B34: =IFERROR(__xludf.DUMMYFUNCTION("""COMPUTED_VALUE"""),"4/30/2017") -> 4/30/2017 | C34: =IFERROR(__xludf.DUMMYFUNCTION("""COMPUTED_VALUE"""),4.0) -> 4 | D34: =IFERROR(__xludf.DUMMYFUNCTION("""COMPUTED_VALUE"""),30.0) -> 30 | E34: =IFERROR(__xludf.DUMMYFUNCTION("""COMPUTED_VALUE"""),2017.0) -> 2017 | F34: =IFERROR(__xludf.DUMMYFUNCTION("""COMPUTED_VALUE"""),42855.0) -> 42855 | G34: =IFERROR(__xludf.DUMMYFUNCTION("""COMPUTED_VALUE"""),42861.0) -> 42861 | H34: =IFERROR(__xludf.DUMMYFUNCTION("""COMPUTED_VALUE"""),6.0) -> 6 | I34: =IFERROR(__xludf.DUMMYFUNCTION("""COMPUTED_VALUE"""),5.0) -> 5 | J34: =IFERROR(__xludf.DUMMYFUNCTION("""COMPUTED_VALUE"""),2017.0) -> 2017 | K34: =IFERROR(__xludf.DUMMYFUNCTION("""COMPUTED_VALUE"""),42891.0) -> 42891 | L34: =IFERROR(__xludf.DUMMYFUNCTION("""COMPUTED_VALUE"""),"H") -> H | M34: =IFERROR(__xludf.DUMMYFUNCTION("""COMPUTED_VALUE"""),"GRC") -> GRC | N34: =IFERROR(__xludf.DUMMYFUNCTION("""COMPUTED_VALUE"""),1270.0) -> 1270 | O34: =IFERROR(__xludf.DUMMYFUNCTION("""COMPUTED_VALUE"""),"Offline") -> Offline | P34: =IFERROR(__xludf.DUMMYFUNCTION("""COMPUTED_VALUE"""),7990.0) -> 7990 | Q34: =IFERROR(__xludf.DUMMYFUNCTION("""COMPUTED_VALUE"""),47.45) -> 47.45 | R34: =IFERROR(__xludf.DUMMYFUNCTION("""COMPUTED_VALUE"""),31.79) -> 31.79 | S34: =IFERROR(__xludf.DUMMYFUNCTION("""COMPUTED_VALUE"""),379125.5) -> 379125.5 | T34: =IFERROR(__xludf.DUMMYFUNCTION("""COMPUTED_VALUE"""),254002.1) -> 254002.1 | U34: =IFERROR(__xludf.DUMMYFUNCTION("""COMPUTED_VALUE"""),125123.4) -> 125123.4 | V34: =IFERROR(__xludf.DUMMYFUNCTION("""COMPUTED_VALUE"""),"Beverages") -> Beverages | W34: =IFERROR(__xludf.DUMMYFUNCTION("""COMPUTED_VALUE"""),"Europe") -> Europe | X34: =IFERROR(__xludf.DUMMYFUNCTION("""COMPUTED_VALUE"""),"Southern Europe") -> Southern Europe | Y34: =IFERROR(__xludf.DUMMYFUNCTION("""COMPUTED_VALUE"""),0.33003161222339306) -> 0.33003161 | Z34: =IFERROR(__xludf.DUMMYFUNCTION("""COMPUTED_VALUE"""),36.0) -> 36 | AA34: =IFERROR(__xludf.DUMMYFUNCTION("""COMPUTED_VALUE"""),1.0) -> 1
A35: =IFERROR(__xludf.DUMMYFUNCTION("""COMPUTED_VALUE"""),3.3330444E8) -> 333304440 | B35: =IFERROR(__xludf.DUMMYFUNCTION("""COMPUTED_VALUE"""),43045.0) -> 43045 | C35: =IFERROR(__xludf.DUMMYFUNCTION("""COMPUTED_VALUE"""),6.0) -> 6 | D35: =IFERROR(__xludf.DUMMYFUNCTION("""COMPUTED_VALUE"""),11.0) -> 11 | E35: =IFERROR(__xludf.DUMMYFUNCTION("""COMPUTED_VALUE"""),2017.0) -> 2017 | F35: =IFERROR(__xludf.DUMMYFUNCTION("""COMPUTED_VALUE"""),42897.0) -> 42897 | G35: =IFERROR(__xludf.DUMMYFUNCTION("""COMPUTED_VALUE"""),42862.0) -> 42862 | H35: =IFERROR(__xludf.DUMMYFUNCTION("""COMPUTED_VALUE"""),7.0) -> 7 | I35: =IFERROR(__xludf.DUMMYFUNCTION("""COMPUTED_VALUE"""),5.0) -> 5 | J35: =IFERROR(__xludf.DUMMYFUNCTION("""COMPUTED_VALUE"""),2017.0) -> 2017 | K35: =IFERROR(__xludf.DUMMYFUNCTION("""COMPUTED_VALUE"""),42921.0) -> 42921 | L35: =IFERROR(__xludf.DUMMYFUNCTION("""COMPUTED_VALUE"""),"L") -> L | M35: =IFERROR(__xludf.DUMMYFUNCTION("""COMPUTED_VALUE"""),"CYP") -> CYP | N35: =IFERROR(__xludf.DUMMYFUNCTION("""COMPUTED_VALUE"""),8875.0) -> 8875 | O35: =IFERROR(__xludf.DUMMYFUNCTION("""COMPUTED_VALUE"""),"Online") -> Online | P35: =IFERROR(__xludf.DUMMYFUNCTION("""COMPUTED_VALUE"""),1046.0) -> 1046 | Q35: =IFERROR(__xludf.DUMMYFUNCTION("""COMPUTED_VALUE"""),421.89) -> 421.89 | R35: =IFERROR(__xludf.DUMMYFUNCTION("""COMPUTED_VALUE"""),364.69) -> 364.69 | S35: =IFERROR(__xludf.DUMMYFUNCTION("""COMPUTED_VALUE"""),441296.94) -> 441296.94 | T35: =IFERROR(__xludf.DUMMYFUNCTION("""COMPUTED_VALUE"""),381465.74) -> 381465.74 | U35: =IFERROR(__xludf.DUMMYFUNCTION("""COMPUTED_VALUE"""),59831.20000000001) -> 59831.2 | V35: =IFERROR(__xludf.DUMMYFUNCTION("""COMPUTED_VALUE"""),"Meat") -> Meat | W35: =IFERROR(__xludf.DUMMYFUNCTION("""COMPUTED_VALUE"""),"Asia") -> Asia | X35: =IFERROR(__xludf.DUMMYFUNCTION("""COMPUTED_VALUE"""),"Western Asia") -> Western Asia | Y35: =IFERROR(__xludf.DUMMYFUNCTION("""COMPUTED_VALUE"""),0.13558036455000122) -> 0.13558036 | Z35: =IFERROR(__xludf.DUMMYFUNCTION("""COMPUTED_VALUE"""),24.0) -> 24 | AA35: =IFERROR(__xludf.DUMMYFUNCTION("""COMPUTED_VALUE"""),1.0) -> 1
A36: =IFERROR(__xludf.DUMMYFUNCTION("""COMPUTED_VALUE"""),3.41398274E8) -> 341398274 | B36: =IFERROR(__xludf.DUMMYFUNCTION("""COMPUTED_VALUE"""),"1/22/2017") -> 1/22/2017 | C36: =IFERROR(__xludf.DUMMYFUNCTION("""COMPUTED_VALUE"""),1.0) -> 1 | D36: =IFERROR(__xludf.DUMMYFUNCTION("""COMPUTED_VALUE"""),22.0) -> 22 | E36: =IFERROR(__xludf.DUMMYFUNCTION("""COMPUTED_VALUE"""),2017.0) -> 2017 | F36: =IFERROR(__xludf.DUMMYFUNCTION("""COMPUTED_VALUE"""),42757.0) -> 42757 | G36: =IFERROR(__xludf.DUMMYFUNCTION("""COMPUTED_VALUE"""),42919.0) -> 42919 | H36: =IFERROR(__xludf.DUMMYFUNCTION("""COMPUTED_VALUE"""),3.0) -> 3 | I36: =IFERROR(__xludf.DUMMYFUNCTION("""COMPUTED_VALUE"""),7.0) -> 7 | J36: =IFERROR(__xludf.DUMMYFUNCTION("""COMPUTED_VALUE"""),2017.0) -> 2017 | K36: =IFERROR(__xludf.DUMMYFUNCTION("""COMPUTED_VALUE"""),42801.0) -> 42801 | L36: =IFERROR(__xludf.DUMMYFUNCTION("""COMPUTED_VALUE"""),"L") -> L | M36: =IFERROR(__xludf.DUMMYFUNCTION("""COMPUTED_VALUE"""),"GEO") -> GEO | N36: =IFERROR(__xludf.DUMMYFUNCTION("""COMPUTED_VALUE"""),8969.0) -> 8969 | O36: =IFERROR(__xludf.DUMMYFUNCTION("""COMPUTED_VALUE"""),"Offline") -> Offline | P36: =IFERROR(__xludf.DUMMYFUNCTION("""COMPUTED_VALUE"""),6191.0) -> 6191 | Q36: =IFERROR(__xludf.DUMMYFUNCTION("""COMPUTED_VALUE"""),152.58) -> 152.58 | R36: =IFERROR(__xludf.DUMMYFUNCTION("""COMPUTED_VALUE"""),97.44) -> 97.44 | S36: =IFERROR(__xludf.DUMMYFUNCTION("""COMPUTED_VALUE"""),944622.78) -> 944622.78 | T36: =IFERROR(__xludf.DUMMYFUNCTION("""COMPUTED_VALUE"""),603251.04) -> 603251.04 | U36: =IFERROR(__xludf.DUMMYFUNCTION("""COMPUTED_VALUE"""),341371.74) -> 341371.74 | V36: =IFERROR(__xludf.DUMMYFUNCTION("""COMPUTED_VALUE"""),"Snacks") -> Snacks | W36: =IFERROR(__xludf.DUMMYFUNCTION("""COMPUTED_VALUE"""),"Asia") -> Asia | X36: =IFERROR(__xludf.DUMMYFUNCTION("""COMPUTED_VALUE"""),"Western Asia") -> Western Asia | Y36: =IFERROR(__xludf.DUMMYFUNCTION("""COMPUTED_VALUE"""),0.36138419189933146) -> 0.36138419 | Z36: =IFERROR(__xludf.DUMMYFUNCTION("""COMPUTED_VALUE"""),44.0) -> 44 | AA36: =IFERROR(__xludf.DUMMYFUNCTION("""COMPUTED_VALUE"""),1.0) -> 1
A37: =IFERROR(__xludf.DUMMYFUNCTION("""COMPUTED_VALUE"""),3.43730294E8) -> 343730294 | B37: =IFERROR(__xludf.DUMMYFUNCTION("""COMPUTED_VALUE"""),42740.0) -> 42740 | C37: =IFERROR(__xludf.DUMMYFUNCTION("""COMPUTED_VALUE"""),5.0) -> 5 | D37: =IFERROR(__xludf.DUMMYFUNCTION("""COMPUTED_VALUE"""),1.0) -> 1 | E37: =IFERROR(__xludf.DUMMYFUNCTION("""COMPUTED_VALUE"""),2017.0) -> 2017 | F37: =IFERROR(__xludf.DUMMYFUNCTION("""COMPUTED_VALUE"""),42856.0) -> 42856 | G37: =IFERROR(__xludf.DUMMYFUNCTION("""COMPUTED_VALUE"""),"5/28/2017") -> 5/28/2017 | H37: =IFERROR(__xludf.DUMMYFUNCTION("""COMPUTED_VALUE"""),5.0) -> 5 | I37: =IFERROR(__xludf.DUMMYFUNCTION("""COMPUTED_VALUE"""),28.0) -> 28 | J37: =IFERROR(__xludf.DUMMYFUNCTION("""COMPUTED_VALUE"""),2017.0) -> 2017 | K37: =IFERROR(__xludf.DUMMYFUNCTION("""COMPUTED_VALUE"""),42883.0) -> 42883 | L37: =IFERROR(__xludf.DUMMYFUNCTION("""COMPUTED_VALUE"""),"L") -> L | M37: =IFERROR(__xludf.DUMMYFUNCTION("""COMPUTED_VALUE"""),"LVA") -> LVA | N37: =IFERROR(__xludf.DUMMYFUNCTION("""COMPUTED_VALUE"""),8681.0) -> 8681 | O37: =IFERROR(__xludf.DUMMYFUNCTION("""COMPUTED_VALUE"""),"Online") -> Online | P37: =IFERROR(__xludf.DUMMYFUNCTION("""COMPUTED_VALUE"""),6287.0) -> 6287 | Q37: =IFERROR(__xludf.DUMMYFUNCTION("""COMPUTED_VALUE"""),651.21) -> 651.21 | R37: =IFERROR(__xludf.DUMMYFUNCTION("""COMPUTED_VALUE"""),524.96) -> 524.96 | S37: =IFERROR(__xludf.DUMMYFUNCTION("""COMPUTED_VALUE"""),4094157.27) -> 4094157.3 | T37: =IFERROR(__xludf.DUMMYFUNCTION("""COMPUTED_VALUE"""),3300423.52) -> 3300423.5 | U37: =IFERROR(__xludf.DUMMYFUNCTION("""COMPUTED_VALUE"""),793733.75) -> 793733.75 | V37: =IFERROR(__xludf.DUMMYFUNCTION("""COMPUTED_VALUE"""),"Office Supplies") -> Office Supplies | W37: =IFERROR(__xludf.DUMMYFUNCTION("""COMPUTED_VALUE"""),"Europe") -> Europe | X37: =IFERROR(__xludf.DUMMYFUNCTION("""COMPUTED_VALUE"""),"Northern Europe") -> Northern Europe | Y37: =IFERROR(__xludf.DUMMYFUNCTION("""COMPUTED_VALUE"""),0.19386987300563566) -> 0.19386987 | Z37: =IFERROR(__xludf.DUMMYFUNCTION("""COMPUTED_VALUE"""),27.0) -> 27 | AA37: =IFERROR(__xludf.DUMMYFUNCTION("""COMPUTED_VALUE"""),2.0) -> 2
A38: =IFERROR(__xludf.DUMMYFUNCTION("""COMPUTED_VALUE"""),3.52342545E8) -> 352342545 | B38: =IFERROR(__xludf.DUMMYFUNCTION("""COMPUTED_VALUE"""),"2/19/2017") -> 2/19/2017 | C38: =IFERROR(__xludf.DUMMYFUNCTION("""COMPUTED_VALUE"""),2.0) -> 2 | D38: =IFERROR(__xludf.DUMMYFUNCTION("""COMPUTED_VALUE"""),19.0) -> 19 | E38: =IFERROR(__xludf.DUMMYFUNCTION("""COMPUTED_VALUE"""),2017.0) -> 2017 | F38: =IFERROR(__xludf.DUMMYFUNCTION("""COMPUTED_VALUE"""),42785.0) -> 42785 | G38: =IFERROR(__xludf.DUMMYFUNCTION("""COMPUTED_VALUE"""),"3/27/2017") -> 3/27/2017 | H38: =IFERROR(__xludf.DUMMYFUNCTION("""COMPUTED_VALUE"""),3.0) -> 3 | I38: =IFERROR(__xludf.DUMMYFUNCTION("""COMPUTED_VALUE"""),27.0) -> 27 | J38: =IFERROR(__xludf.DUMMYFUNCTION("""COMPUTED_VALUE"""),2017.0) -> 2017 | K38: =IFERROR(__xludf.DUMMYFUNCTION("""COMPUTED_VALUE"""),42821.0) -> 42821 | L38: =IFERROR(__xludf.DUMMYFUNCTION("""COMPUTED_VALUE"""),"M") -> M | M38: =IFERROR(__xludf.DUMMYFUNCTION("""COMPUTED_VALUE"""),"ESP") -> ESP | N38: =IFERROR(__xludf.DUMMYFUNCTION("""COMPUTED_VALUE"""),8969.0) -> 8969 | O38: =IFERROR(__xludf.DUMMYFUNCTION("""COMPUTED_VALUE"""),"Offline") -> Offline | P38: =IFERROR(__xludf.DUMMYFUNCTION("""COMPUTED_VALUE"""),4844.0) -> 4844 | Q38: =IFERROR(__xludf.DUMMYFUNCTION("""COMPUTED_VALUE"""),152.58) -> 152.58 | R38: =IFERROR(__xludf.DUMMYFUNCTION("""COMPUTED_VALUE"""),97.44) -> 97.44 | S38: =IFERROR(__xludf.DUMMYFUNCTION("""COMPUTED_VALUE"""),739097.52) -> 739097.52 | T38: =IFERROR(__xludf.DUMMYFUNCTION("""COMPUTED_VALUE"""),471999.36) -> 471999.36 | U38: =IFERROR(__xludf.DUMMYFUNCTION("""COMPUTED_VALUE"""),267098.16000000003) -> 267098.16 | V38: =IFERROR(__xludf.DUMMYFUNCTION("""COMPUTED_VALUE"""),"Snacks") -> Snacks | W38: =IFERROR(__xludf.DUMMYFUNCTION("""COMPUTED_VALUE"""),"Europe") -> Europe | X38: =IFERROR(__xludf.DUMMYFUNCTION("""COMPUTED_VALUE"""),"Southern Europe") -> Southern Europe | Y38: =IFERROR(__xludf.DUMMYFUNCTION("""COMPUTED_VALUE"""),0.3613841918993315) -> 0.36138419 | Z38: =IFERROR(__xludf.DUMMYFUNCTION("""COMPUTED_VALUE"""),36.0) -> 36 | AA38: =IFERROR(__xludf.DUMMYFUNCTION("""COMPUTED_VALUE"""),1.0) -> 1
A39: =IFERROR(__xludf.DUMMYFUNCTION("""COMPUTED_VALUE"""),3.61311852E8) -> 361311852 | B39: =IFERROR(__xludf.DUMMYFUNCTION("""COMPUTED_VALUE"""),42887.0) -> 42887 | C39: =IFERROR(__xludf.DUMMYFUNCTION("""COMPUTED_VALUE"""),1.0) -> 1 | D39: =IFERROR(__xludf.DUMMYFUNCTION("""COMPUTED_VALUE"""),6.0) -> 6 | E39: =IFERROR(__xludf.DUMMYFUNCTION("""COMPUTED_VALUE"""),2017.0) -> 2017 | F39: =IFERROR(__xludf.DUMMYFUNCTION("""COMPUTED_VALUE"""),42741.0) -> 42741 | G39: =IFERROR(__xludf.DUMMYFUNCTION("""COMPUTED_VALUE"""),"2/15/2017") -> 2/15/2017 | H39: =IFERROR(__xludf.DUMMYFUNCTION("""COMPUTED_VALUE"""),2.0) -> 2 | I39: =IFERROR(__xludf.DUMMYFUNCTION("""COMPUTED_VALUE"""),15.0) -> 15 | J39: =IFERROR(__xludf.DUMMYFUNCTION("""COMPUTED_VALUE"""),2017.0) -> 2017 | K39: =IFERROR(__xludf.DUMMYFUNCTION("""COMPUTED_VALUE"""),42781.0) -> 42781 | L39: =IFERROR(__xludf.DUMMYFUNCTION("""COMPUTED_VALUE"""),"L") -> L | M39: =IFERROR(__xludf.DUMMYFUNCTION("""COMPUTED_VALUE"""),"DEU") -> DEU | N39: =IFERROR(__xludf.DUMMYFUNCTION("""COMPUTED_VALUE"""),7331.0) -> 7331 | O39: =IFERROR(__xludf.DUMMYFUNCTION("""COMPUTED_VALUE"""),"Offline") -> Offline | P39: =IFERROR(__xludf.DUMMYFUNCTION("""COMPUTED_VALUE"""),9061.0) -> 9061 | Q39: =IFERROR(__xludf.DUMMYFUNCTION("""COMPUTED_VALUE"""),255.28) -> 255.28 | R39: =IFERROR(__xludf.DUMMYFUNCTION("""COMPUTED_VALUE"""),159.42) -> 159.42 | S39: =IFERROR(__xludf.DUMMYFUNCTION("""COMPUTED_VALUE"""),2313092.08) -> 2313092.1 | T39: =IFERROR(__xludf.DUMMYFUNCTION("""COMPUTED_VALUE"""),1444504.6199999999) -> 1444504.6 | U39: =IFERROR(__xludf.DUMMYFUNCTION("""COMPUTED_VALUE"""),868587.4600000002) -> 868587.46 | V39: =IFERROR(__xludf.DUMMYFUNCTION("""COMPUTED_VALUE"""),"Baby Food") -> Baby Food | W39: =IFERROR(__xludf.DUMMYFUNCTION("""COMPUTED_VALUE"""),"Europe") -> Europe | X39: =IFERROR(__xludf.DUMMYFUNCTION("""COMPUTED_VALUE"""),"Western Europe") -> Western Europe | Y39: =IFERROR(__xludf.DUMMYFUNCTION("""COMPUTED_VALUE"""),0.3755092447508619) -> 0.37550924 | Z39: =IFERROR(__xludf.DUMMYFUNCTION("""COMPUTED_VALUE"""),40.0) -> 40 | AA39: =IFERROR(__xludf.DUMMYFUNCTION("""COMPUTED_VALUE"""),6.0) -> 6
A40: =IFERROR(__xludf.DUMMYFUNCTION("""COMPUTED_VALUE"""),3.80379998E8) -> 380379998 | B40: =IFERROR(__xludf.DUMMYFUNCTION("""COMPUTED_VALUE"""),"7/14/2017") -> 7/14/2017 | C40: =IFERROR(__xludf.DUMMYFUNCTION("""COMPUTED_VALUE"""),7.0) -> 7 | D40: =IFERROR(__xludf.DUMMYFUNCTION("""COMPUTED_VALUE"""),14.0) -> 14 | E40: =IFERROR(__xludf.DUMMYFUNCTION("""COMPUTED_VALUE"""),2017.0) -> 2017 | F40: =IFERROR(__xludf.DUMMYFUNCTION("""COMPUTED_VALUE"""),42930.0) -> 42930 | G40: =IFERROR(__xludf.DUMMYFUNCTION("""COMPUTED_VALUE"""),"7/16/2017") -> 7/16/2017 | H40: =IFERROR(__xludf.DUMMYFUNCTION("""COMPUTED_VALUE"""),7.0) -> 7 | I40: =IFERROR(__xludf.DUMMYFUNCTION("""COMPUTED_VALUE"""),16.0) -> 16 | J40: =IFERROR(__xludf.DUMMYFUNCTION("""COMPUTED_VALUE"""),2017.0) -> 2017 | K40: =IFERROR(__xludf.DUMMYFUNCTION("""COMPUTED_VALUE"""),42932.0) -> 42932 | L40: =IFERROR(__xludf.DUMMYFUNCTION("""COMPUTED_VALUE"""),"C") -> C | M40: =IFERROR(__xludf.DUMMYFUNCTION("""COMPUTED_VALUE"""),"ALB") -> ALB | N40: =IFERROR(__xludf.DUMMYFUNCTION("""COMPUTED_VALUE"""),7940.0) -> 7940 | O40: =IFERROR(__xludf.DUMMYFUNCTION("""COMPUTED_VALUE"""),"Online") -> Online | P40: =IFERROR(__xludf.DUMMYFUNCTION("""COMPUTED_VALUE"""),1749.0) -> 1749 | Q40: =IFERROR(__xludf.DUMMYFUNCTION("""COMPUTED_VALUE"""),668.27) -> 668.27 | R40: =IFERROR(__xludf.DUMMYFUNCTION("""COMPUTED_VALUE"""),502.54) -> 502.54 | S40: =IFERROR(__xludf.DUMMYFUNCTION("""COMPUTED_VALUE"""),1168804.23) -> 1168804.2 | T40: =IFERROR(__xludf.DUMMYFUNCTION("""COMPUTED_VALUE"""),878942.4600000001) -> 878942.46 | U40: =IFERROR(__xludf.DUMMYFUNCTION("""COMPUTED_VALUE"""),289861.7699999999) -> 289861.77 | V40: =IFERROR(__xludf.DUMMYFUNCTION("""COMPUTED_VALUE"""),"Household") -> Household | W40: =IFERROR(__xludf.DUMMYFUNCTION("""COMPUTED_VALUE"""),"Europe") -> Europe | X40: =IFERROR(__xludf.DUMMYFUNCTION("""COMPUTED_VALUE"""),"Southern Europe") -> Southern Europe | Y40: =IFERROR(__xludf.DUMMYFUNCTION("""COMPUTED_VALUE"""),0.2479985634548909) -> 0.24799856 | Z40: =IFERROR(__xludf.DUMMYFUNCTION("""COMPUTED_VALUE"""),2.0) -> 2 | AA40: =IFERROR(__xludf.DUMMYFUNCTION("""COMPUTED_VALUE"""),6.0) -> 6
A41: =IFERROR(__xludf.DUMMYFUNCTION("""COMPUTED_VALUE"""),3.91026866E8) -> 391026866 | B41: =IFERROR(__xludf.DUMMYFUNCTION("""COMPUTED_VALUE"""),42795.0) -> 42795 | C41: =IFERROR(__xludf.DUMMYFUNCTION("""COMPUTED_VALUE"""),1.0) -> 1 | D41: =IFERROR(__xludf.DUMMYFUNCTION("""COMPUTED_VALUE"""),3.0) -> 3 | E41: =IFERROR(__xludf.DUMMYFUNCTION("""COMPUTED_VALUE"""),2017.0) -> 2017 | F41: =IFERROR(__xludf.DUMMYFUNCTION("""COMPUTED_VALUE"""),42738.0) -> 42738 | G41: =IFERROR(__xludf.DUMMYFUNCTION("""COMPUTED_VALUE"""),42948.0) -> 42948 | H41: =IFERROR(__xludf.DUMMYFUNCTION("""COMPUTED_VALUE"""),1.0) -> 1 | I41: =IFERROR(__xludf.DUMMYFUNCTION("""COMPUTED_VALUE"""),8.0) -> 8 | J41: =IFERROR(__xludf.DUMMYFUNCTION("""COMPUTED_VALUE"""),2017.0) -> 2017 | K41: =IFERROR(__xludf.DUMMYFUNCTION("""COMPUTED_VALUE"""),42743.0) -> 42743 | L41: =IFERROR(__xludf.DUMMYFUNCTION("""COMPUTED_VALUE"""),"C") -> C | M41: =IFERROR(__xludf.DUMMYFUNCTION("""COMPUTED_VALUE"""),"ESP") -> ESP | N41: =IFERROR(__xludf.DUMMYFUNCTION("""COMPUTED_VALUE"""),8293.0) -> 8293 | O41: =IFERROR(__xludf.DUMMYFUNCTION("""COMPUTED_VALUE"""),"Offline") -> Offline | P41: =IFERROR(__xludf.DUMMYFUNCTION("""COMPUTED_VALUE"""),2394.0) -> 2394 | Q41: =IFERROR(__xludf.DUMMYFUNCTION("""COMPUTED_VALUE"""),437.2) -> 437.2 | R41: =IFERROR(__xludf.DUMMYFUNCTION("""COMPUTED_VALUE"""),263.33) -> 263.33 | S41: =IFERROR(__xludf.DUMMYFUNCTION("""COMPUTED_VALUE"""),1046656.7999999999) -> 1046656.8 | T41: =IFERROR(__xludf.DUMMYFUNCTION("""COMPUTED_VALUE"""),630412.02) -> 630412.02 | U41: =IFERROR(__xludf.DUMMYFUNCTION("""COMPUTED_VALUE"""),416244.7799999999) -> 416244.78 | V41: =IFERROR(__xludf.DUMMYFUNCTION("""COMPUTED_VALUE"""),"Cosmetics") -> Cosmetics | W41: =IFERROR(__xludf.DUMMYFUNCTION("""COMPUTED_VALUE"""),"Europe") -> Europe | X41: =IFERROR(__xludf.DUMMYFUNCTION("""COMPUTED_VALUE"""),"Southern Europe") -> Southern Europe | Y41: =IFERROR(__xludf.DUMMYFUNCTION("""COMPUTED_VALUE"""),0.3976898444647758) -> 0.39768984 | Z41: =IFERROR(__xludf.DUMMYFUNCTION("""COMPUTED_VALUE"""),5.0) -> 5 | AA41: =IFERROR(__xludf.DUMMYFUNCTION("""COMPUTED_VALUE"""),3.0) -> 3
A42: =IFERROR(__xludf.DUMMYFUNCTION("""COMPUTED_VALUE"""),3.93709933E8) -> 393709933 | B42: =IFERROR(__xludf.DUMMYFUNCTION("""COMPUTED_VALUE"""),43072.0) -> 43072 | C42: =IFERROR(__xludf.DUMMYFUNCTION("""COMPUTED_VALUE"""),3.0) -> 3 | D42: =IFERROR(__xludf.DUMMYFUNCTION("""COMPUTED_VALUE"""),12.0) -> 12 | E42: =IFERROR(__xludf.DUMMYFUNCTION("""COMPUTED_VALUE"""),2017.0) -> 2017 | F42: =IFERROR(__xludf.DUMMYFUNCTION("""COMPUTED_VALUE"""),42806.0) -> 42806 | G42: =IFERROR(__xludf.DUMMYFUNCTION("""COMPUTED_VALUE"""),"4/25/2017") -> 4/25/2017 | H42: =IFERROR(__xludf.DUMMYFUNCTION("""COMPUTED_VALUE"""),4.0) -> 4 | I42: =IFERROR(__xludf.DUMMYFUNCTION("""COMPUTED_VALUE"""),25.0) -> 25 | J42: =IFERROR(__xludf.DUMMYFUNCTION("""COMPUTED_VALUE"""),2017.0) -> 2017 | K42: =IFERROR(__xludf.DUMMYFUNCTION("""COMPUTED_VALUE"""),42850.0) -> 42850 | L42: =IFERROR(__xludf.DUMMYFUNCTION("""COMPUTED_VALUE"""),"C") -> C | M42: =IFERROR(__xludf.DUMMYFUNCTION("""COMPUTED_VALUE"""),"FRA") -> FRA | N42: =IFERROR(__xludf.DUMMYFUNCTION("""COMPUTED_VALUE"""),4594.0) -> 4594 | O42: =IFERROR(__xludf.DUMMYFUNCTION("""COMPUTED_VALUE"""),"Offline") -> Offline | P42: =IFERROR(__xludf.DUMMYFUNCTION("""COMPUTED_VALUE"""),6373.0) -> 6373 | Q42: =IFERROR(__xludf.DUMMYFUNCTION("""COMPUTED_VALUE"""),9.33) -> 9.33 | R42: =IFERROR(__xludf.DUMMYFUNCTION("""COMPUTED_VALUE"""),6.92) -> 6.92 | S42: =IFERROR(__xludf.DUMMYFUNCTION("""COMPUTED_VALUE"""),59460.090000000004) -> 59460.09 | T42: =IFERROR(__xludf.DUMMYFUNCTION("""COMPUTED_VALUE"""),44101.159999999996) -> 44101.16 | U42: =IFERROR(__xludf.DUMMYFUNCTION("""COMPUTED_VALUE"""),15358.930000000008) -> 15358.93 | V42: =IFERROR(__xludf.DUMMYFUNCTION("""COMPUTED_VALUE"""),"Fruits") -> Fruits | W42: =IFERROR(__xludf.DUMMYFUNCTION("""COMPUTED_VALUE"""),"Europe") -> Europe | X42: =IFERROR(__xludf.DUMMYFUNCTION("""COMPUTED_VALUE"""),"Western Europe") -> Western Europe | Y42: =IFERROR(__xludf.DUMMYFUNCTION("""COMPUTED_VALUE"""),0.2583065380493034) -> 0.25830654 | Z42: =IFERROR(__xludf.DUMMYFUNCTION("""COMPUTED_VALUE"""),44.0) -> 44 | AA42: =IFERROR(__xludf.DUMMYFUNCTION("""COMPUTED_VALUE"""),1.0) -> 1
A43: =IFERROR(__xludf.DUMMYFUNCTION("""COMPUTED_VALUE"""),4.10514724E8) -> 410514724 | B43: =IFERROR(__xludf.DUMMYFUNCTION("""COMPUTED_VALUE"""),42738.0) -> 42738 | C43: =IFERROR(__xludf.DUMMYFUNCTION("""COMPUTED_VALUE"""),3.0) -> 3 | D43: =IFERROR(__xludf.DUMMYFUNCTION("""COMPUTED_VALUE"""),1.0) -> 1 | E43: =IFERROR(__xludf.DUMMYFUNCTION("""COMPUTED_VALUE"""),2017.0) -> 2017 | F43: =IFERROR(__xludf.DUMMYFUNCTION("""COMPUTED_VALUE"""),42795.0) -> 42795 | G43: =IFERROR(__xludf.DUMMYFUNCTION("""COMPUTED_VALUE"""),43012.0) -> 43012 | H43: =IFERROR(__xludf.DUMMYFUNCTION("""COMPUTED_VALUE"""),4.0) -> 4 | I43: =IFERROR(__xludf.DUMMYFUNCTION("""COMPUTED_VALUE"""),10.0) -> 10 | J43: =IFERROR(__xludf.DUMMYFUNCTION("""COMPUTED_VALUE"""),2017.0) -> 2017 | K43: =IFERROR(__xludf.DUMMYFUNCTION("""COMPUTED_VALUE"""),42835.0) -> 42835 | L43: =IFERROR(__xludf.DUMMYFUNCTION("""COMPUTED_VALUE"""),"C") -> C | M43: =IFERROR(__xludf.DUMMYFUNCTION("""COMPUTED_VALUE"""),"SRB") -> SRB | N43: =IFERROR(__xludf.DUMMYFUNCTION("""COMPUTED_VALUE"""),8681.0) -> 8681 | O43: =IFERROR(__xludf.DUMMYFUNCTION("""COMPUTED_VALUE"""),"Offline") -> Offline | P43: =IFERROR(__xludf.DUMMYFUNCTION("""COMPUTED_VALUE"""),9284.0) -> 9284 | Q43: =IFERROR(__xludf.DUMMYFUNCTION("""COMPUTED_VALUE"""),651.21) -> 651.21 | R43: =IFERROR(__xludf.DUMMYFUNCTION("""COMPUTED_VALUE"""),524.96) -> 524.96 | S43: =IFERROR(__xludf.DUMMYFUNCTION("""COMPUTED_VALUE"""),6045833.640000001) -> 6045833.6 | T43: =IFERROR(__xludf.DUMMYFUNCTION("""COMPUTED_VALUE"""),4873728.640000001) -> 4873728.6 | U43: =IFERROR(__xludf.DUMMYFUNCTION("""COMPUTED_VALUE"""),1172105.0) -> 1172105 | V43: =IFERROR(__xludf.DUMMYFUNCTION("""COMPUTED_VALUE"""),"Office Supplies") -> Office Supplies | W43: =IFERROR(__xludf.DUMMYFUNCTION("""COMPUTED_VALUE"""),"Europe") -> Europe | X43: =IFERROR(__xludf.DUMMYFUNCTION("""COMPUTED_VALUE"""),"Southern Europe") -> Southern Europe | Y43: =IFERROR(__xludf.DUMMYFUNCTION("""COMPUTED_VALUE"""),0.19386987300563566) -> 0.19386987 | Z43: =IFERROR(__xludf.DUMMYFUNCTION("""COMPUTED_VALUE"""),40.0) -> 40 | AA43: =IFERROR(__xludf.DUMMYFUNCTION("""COMPUTED_VALUE"""),4.0) -> 4
A44: =IFERROR(__xludf.DUMMYFUNCTION("""COMPUTED_VALUE"""),4.14579665E8) -> 414579665 | B44: =IFERROR(__xludf.DUMMYFUNCTION("""COMPUTED_VALUE"""),"6/20/2017") -> 6/20/2017 | C44: =IFERROR(__xludf.DUMMYFUNCTION("""COMPUTED_VALUE"""),6.0) -> 6 | D44: =IFERROR(__xludf.DUMMYFUNCTION("""COMPUTED_VALUE"""),20.0) -> 20 | E44: =IFERROR(__xludf.DUMMYFUNCTION("""COMPUTED_VALUE"""),2017.0) -> 2017 | F44: =IFERROR(__xludf.DUMMYFUNCTION("""COMPUTED_VALUE"""),42906.0) -> 42906 | G44: =IFERROR(__xludf.DUMMYFUNCTION("""COMPUTED_VALUE"""),43015.0) -> 43015 | H44: =IFERROR(__xludf.DUMMYFUNCTION("""COMPUTED_VALUE"""),7.0) -> 7 | I44: =IFERROR(__xludf.DUMMYFUNCTION("""COMPUTED_VALUE"""),10.0) -> 10 | J44: =IFERROR(__xludf.DUMMYFUNCTION("""COMPUTED_VALUE"""),2017.0) -> 2017 | K44: =IFERROR(__xludf.DUMMYFUNCTION("""COMPUTED_VALUE"""),42926.0) -> 42926 | L44: =IFERROR(__xludf.DUMMYFUNCTION("""COMPUTED_VALUE"""),"H") -> H | M44: =IFERROR(__xludf.DUMMYFUNCTION("""COMPUTED_VALUE"""),"FIN") -> FIN | N44: =IFERROR(__xludf.DUMMYFUNCTION("""COMPUTED_VALUE"""),8969.0) -> 8969 | O44: =IFERROR(__xludf.DUMMYFUNCTION("""COMPUTED_VALUE"""),"Online") -> Online | P44: =IFERROR(__xludf.DUMMYFUNCTION("""COMPUTED_VALUE"""),2191.0) -> 2191 | Q44: =IFERROR(__xludf.DUMMYFUNCTION("""COMPUTED_VALUE"""),152.58) -> 152.58 | R44: =IFERROR(__xludf.DUMMYFUNCTION("""COMPUTED_VALUE"""),97.44) -> 97.44 | S44: =IFERROR(__xludf.DUMMYFUNCTION("""COMPUTED_VALUE"""),334302.78) -> 334302.78 | T44: =IFERROR(__xludf.DUMMYFUNCTION("""COMPUTED_VALUE"""),213491.04) -> 213491.04 | U44: =IFERROR(__xludf.DUMMYFUNCTION("""COMPUTED_VALUE"""),120811.74000000002) -> 120811.74 | V44: =IFERROR(__xludf.DUMMYFUNCTION("""COMPUTED_VALUE"""),"Snacks") -> Snacks | W44: =IFERROR(__xludf.DUMMYFUNCTION("""COMPUTED_VALUE"""),"Europe") -> Europe | X44: =IFERROR(__xludf.DUMMYFUNCTION("""COMPUTED_VALUE"""),"Northern Europe") -> Northern Europe | Y44: =IFERROR(__xludf.DUMMYFUNCTION("""COMPUTED_VALUE"""),0.3613841918993315) -> 0.36138419 | Z44: =IFERROR(__xludf.DUMMYFUNCTION("""COMPUTED_VALUE"""),20.0) -> 20 | AA44: =IFERROR(__xludf.DUMMYFUNCTION("""COMPUTED_VALUE"""),3.0) -> 3
A45: =IFERROR(__xludf.DUMMYFUNCTION("""COMPUTED_VALUE"""),4.39204919E8) -> 439204919 | B45: =IFERROR(__xludf.DUMMYFUNCTION("""COMPUTED_VALUE"""),43041.0) -> 43041 | C45: =IFERROR(__xludf.DUMMYFUNCTION("""COMPUTED_VALUE"""),2.0) -> 2 | D45: =IFERROR(__xludf.DUMMYFUNCTION("""COMPUTED_VALUE"""),11.0) -> 11 | E45: =IFERROR(__xludf.DUMMYFUNCTION("""COMPUTED_VALUE"""),2017.0) -> 2017 | F45: =IFERROR(__xludf.DUMMYFUNCTION("""COMPUTED_VALUE"""),42777.0) -> 42777 | G45: =IFERROR(__xludf.DUMMYFUNCTION("""COMPUTED_VALUE"""),"2/19/2017") -> 2/19/2017 | H45: =IFERROR(__xludf.DUMMYFUNCTION("""COMPUTED_VALUE"""),2.0) -> 2 | I45: =IFERROR(__xludf.DUMMYFUNCTION("""COMPUTED_VALUE"""),19.0) -> 19 | J45: =IFERROR(__xludf.DUMMYFUNCTION("""COMPUTED_VALUE"""),2017.0) -> 2017 | K45: =IFERROR(__xludf.DUMMYFUNCTION("""COMPUTED_VALUE"""),42785.0) -> 42785 | L45: =IFERROR(__xludf.DUMMYFUNCTION("""COMPUTED_VALUE"""),"L") -> L | M45: =IFERROR(__xludf.DUMMYFUNCTION("""COMPUTED_VALUE"""),"ISL") -> ISL | N45: =IFERROR(__xludf.DUMMYFUNCTION("""COMPUTED_VALUE"""),1270.0) -> 1270 | O45: =IFERROR(__xludf.DUMMYFUNCTION("""COMPUTED_VALUE"""),"Online") -> Online | P45: =IFERROR(__xludf.DUMMYFUNCTION("""COMPUTED_VALUE"""),9350.0) -> 9350 | Q45: =IFERROR(__xludf.DUMMYFUNCTION("""COMPUTED_VALUE"""),47.45) -> 47.45 | R45: =IFERROR(__xludf.DUMMYFUNCTION("""COMPUTED_VALUE"""),31.79) -> 31.79 | S45: =IFERROR(__xludf.DUMMYFUNCTION("""COMPUTED_VALUE"""),443657.5) -> 443657.5 | T45: =IFERROR(__xludf.DUMMYFUNCTION("""COMPUTED_VALUE"""),297236.5) -> 297236.5 | U45: =IFERROR(__xludf.DUMMYFUNCTION("""COMPUTED_VALUE"""),146421.0) -> 146421 | V45: =IFERROR(__xludf.DUMMYFUNCTION("""COMPUTED_VALUE"""),"Beverages") -> Beverages | W45: =IFERROR(__xludf.DUMMYFUNCTION("""COMPUTED_VALUE"""),"Europe") -> Europe | X45: =IFERROR(__xludf.DUMMYFUNCTION("""COMPUTED_VALUE"""),"Northern Europe") -> Northern Europe | Y45: =IFERROR(__xludf.DUMMYFUNCTION("""COMPUTED_VALUE"""),0.33003161222339306) -> 0.33003161 | Z45: =IFERROR(__xludf.DUMMYFUNCTION("""COMPUTED_VALUE"""),8.0) -> 8 | AA45: =IFERROR(__xludf.DUMMYFUNCTION("""COMPUTED_VALUE"""),7.0) -> 7
A46: =IFERROR(__xludf.DUMMYFUNCTION("""COMPUTED_VALUE"""),4.60693061E8) -> 460693061 | B46: =IFERROR(__xludf.DUMMYFUNCTION("""COMPUTED_VALUE"""),"1/28/2017") -> 1/28/2017 | C46: =IFERROR(__xludf.DUMMYFUNCTION("""COMPUTED_VALUE"""),1.0) -> 1 | D46: =IFERROR(__xludf.DUMMYFUNCTION("""COMPUTED_VALUE"""),28.0) -> 28 | E46: =IFERROR(__xludf.DUMMYFUNCTION("""COMPUTED_VALUE"""),2017.0) -> 2017 | F46: =IFERROR(__xludf.DUMMYFUNCTION("""COMPUTED_VALUE"""),42763.0) -> 42763 | G46: =IFERROR(__xludf.DUMMYFUNCTION("""COMPUTED_VALUE"""),"2/25/2017") -> 2/25/2017 | H46: =IFERROR(__xludf.DUMMYFUNCTION("""COMPUTED_VALUE"""),2.0) -> 2 | I46: =IFERROR(__xludf.DUMMYFUNCTION("""COMPUTED_VALUE"""),25.0) -> 25 | J46: =IFERROR(__xludf.DUMMYFUNCTION("""COMPUTED_VALUE"""),2017.0) -> 2017 | K46: =IFERROR(__xludf.DUMMYFUNCTION("""COMPUTED_VALUE"""),42791.0) -> 42791 | L46: =IFERROR(__xludf.DUMMYFUNCTION("""COMPUTED_VALUE"""),"C") -> C | M46: =IFERROR(__xludf.DUMMYFUNCTION("""COMPUTED_VALUE"""),"GEO") -> GEO | N46: =IFERROR(__xludf.DUMMYFUNCTION("""COMPUTED_VALUE"""),4594.0) -> 4594 | O46: =IFERROR(__xludf.DUMMYFUNCTION("""COMPUTED_VALUE"""),"Offline") -> Offline | P46: =IFERROR(__xludf.DUMMYFUNCTION("""COMPUTED_VALUE"""),8169.0) -> 8169 | Q46: =IFERROR(__xludf.DUMMYFUNCTION("""COMPUTED_VALUE"""),9.33) -> 9.33 | R46: =IFERROR(__xludf.DUMMYFUNCTION("""COMPUTED_VALUE"""),6.92) -> 6.92 | S46: =IFERROR(__xludf.DUMMYFUNCTION("""COMPUTED_VALUE"""),76216.77) -> 76216.77 | T46: =IFERROR(__xludf.DUMMYFUNCTION("""COMPUTED_VALUE"""),56529.479999999996) -> 56529.48 | U46: =IFERROR(__xludf.DUMMYFUNCTION("""COMPUTED_VALUE"""),19687.290000000008) -> 19687.29 | V46: =IFERROR(__xludf.DUMMYFUNCTION("""COMPUTED_VALUE"""),"Fruits") -> Fruits | W46: =IFERROR(__xludf.DUMMYFUNCTION("""COMPUTED_VALUE"""),"Asia") -> Asia | X46: =IFERROR(__xludf.DUMMYFUNCTION("""COMPUTED_VALUE"""),"Western Asia") -> Western Asia | Y46: =IFERROR(__xludf.DUMMYFUNCTION("""COMPUTED_VALUE"""),0.2583065380493034) -> 0.25830654 | Z46: =IFERROR(__xludf.DUMMYFUNCTION("""COMPUTED_VALUE"""),28.0) -> 28 | AA46: =IFERROR(__xludf.DUMMYFUNCTION("""COMPUTED_VALUE"""),7.0) -> 7
A47: =IFERROR(__xludf.DUMMYFUNCTION("""COMPUTED_VALUE"""),4.76453721E8) -> 476453721 | B47: =IFERROR(__xludf.DUMMYFUNCTION("""COMPUTED_VALUE"""),"7/22/2017") -> 7/22/2017 | C47: =IFERROR(__xludf.DUMMYFUNCTION("""COMPUTED_VALUE"""),7.0) -> 7 | D47: =IFERROR(__xludf.DUMMYFUNCTION("""COMPUTED_VALUE"""),22.0) -> 22 | E47: =IFERROR(__xludf.DUMMYFUNCTION("""COMPUTED_VALUE"""),2017.0) -> 2017 | F47: =IFERROR(__xludf.DUMMYFUNCTION("""COMPUTED_VALUE"""),42938.0) -> 42938 | G47: =IFERROR(__xludf.DUMMYFUNCTION("""COMPUTED_VALUE"""),43016.0) -> 43016 | H47: =IFERROR(__xludf.DUMMYFUNCTION("""COMPUTED_VALUE"""),8.0) -> 8 | I47: =IFERROR(__xludf.DUMMYFUNCTION("""COMPUTED_VALUE"""),10.0) -> 10 | J47: =IFERROR(__xludf.DUMMYFUNCTION("""COMPUTED_VALUE"""),2017.0) -> 2017 | K47: =IFERROR(__xludf.DUMMYFUNCTION("""COMPUTED_VALUE"""),42957.0) -> 42957 | L47: =IFERROR(__xludf.DUMMYFUNCTION("""COMPUTED_VALUE"""),"C") -> C | M47: =IFERROR(__xludf.DUMMYFUNCTION("""COMPUTED_VALUE"""),"SMR") -> SMR | N47: =IFERROR(__xludf.DUMMYFUNCTION("""COMPUTED_VALUE"""),8969.0) -> 8969 | O47: =IFERROR(__xludf.DUMMYFUNCTION("""COMPUTED_VALUE"""),"Offline") -> Offline | P47: =IFERROR(__xludf.DUMMYFUNCTION("""COMPUTED_VALUE"""),2099.0) -> 2099 | Q47: =IFERROR(__xludf.DUMMYFUNCTION("""COMPUTED_VALUE"""),152.58) -> 152.58 | R47: =IFERROR(__xludf.DUMMYFUNCTION("""COMPUTED_VALUE"""),97.44) -> 97.44 | S47: =IFERROR(__xludf.DUMMYFUNCTION("""COMPUTED_VALUE"""),320265.42000000004) -> 320265.42 | T47: =IFERROR(__xludf.DUMMYFUNCTION("""COMPUTED_VALUE"""),204526.56) -> 204526.56 | U47: =IFERROR(__xludf.DUMMYFUNCTION("""COMPUTED_VALUE"""),115738.86000000004) -> 115738.86 | V47: =IFERROR(__xludf.DUMMYFUNCTION("""COMPUTED_VALUE"""),"Snacks") -> Snacks | W47: =IFERROR(__xludf.DUMMYFUNCTION("""COMPUTED_VALUE"""),"Europe") -> Europe | X47: =IFERROR(__xludf.DUMMYFUNCTION("""COMPUTED_VALUE"""),"Southern Europe") -> Southern Europe | Y47: =IFERROR(__xludf.DUMMYFUNCTION("""COMPUTED_VALUE"""),0.3613841918993316) -> 0.36138419 | Z47: =IFERROR(__xludf.DUMMYFUNCTION("""COMPUTED_VALUE"""),19.0) -> 19 | AA47: =IFERROR(__xludf.DUMMYFUNCTION("""COMPUTED_VALUE"""),7.0) -> 7
A48: =IFERROR(__xludf.DUMMYFUNCTION("""COMPUTED_VALUE"""),4.7699145E8) -> 476991450 | B48: =IFERROR(__xludf.DUMMYFUNCTION("""COMPUTED_VALUE"""),43042.0) -> 43042 | C48: =IFERROR(__xludf.DUMMYFUNCTION("""COMPUTED_VALUE"""),3.0) -> 3 | D48: =IFERROR(__xludf.DUMMYFUNCTION("""COMPUTED_VALUE"""),11.0) -> 11 | E48: =IFERROR(__xludf.DUMMYFUNCTION("""COMPUTED_VALUE"""),2017.0) -> 2017 | F48: =IFERROR(__xludf.DUMMYFUNCTION("""COMPUTED_VALUE"""),42805.0) -> 42805 | G48: =IFERROR(__xludf.DUMMYFUNCTION("""COMPUTED_VALUE"""),"3/27/2017") -> 3/27/2017 | H48: =IFERROR(__xludf.DUMMYFUNCTION("""COMPUTED_VALUE"""),3.0) -> 3 | I48: =IFERROR(__xludf.DUMMYFUNCTION("""COMPUTED_VALUE"""),27.0) -> 27 | J48: =IFERROR(__xludf.DUMMYFUNCTION("""COMPUTED_VALUE"""),2017.0) -> 2017 | K48: =IFERROR(__xludf.DUMMYFUNCTION("""COMPUTED_VALUE"""),42821.0) -> 42821 | L48: =IFERROR(__xludf.DUMMYFUNCTION("""COMPUTED_VALUE"""),"L") -> L | M48: =IFERROR(__xludf.DUMMYFUNCTION("""COMPUTED_VALUE"""),"BGR") -> BGR | N48: =IFERROR(__xludf.DUMMYFUNCTION("""COMPUTED_VALUE"""),8969.0) -> 8969 | O48: =IFERROR(__xludf.DUMMYFUNCTION("""COMPUTED_VALUE"""),"Offline") -> Offline | P48: =IFERROR(__xludf.DUMMYFUNCTION("""COMPUTED_VALUE"""),1225.0) -> 1225 | Q48: =IFERROR(__xludf.DUMMYFUNCTION("""COMPUTED_VALUE"""),152.58) -> 152.58 | R48: =IFERROR(__xludf.DUMMYFUNCTION("""COMPUTED_VALUE"""),97.44) -> 97.44 | S48: =IFERROR(__xludf.DUMMYFUNCTION("""COMPUTED_VALUE"""),186910.50000000003) -> 186910.5 | T48: =IFERROR(__xludf.DUMMYFUNCTION("""COMPUTED_VALUE"""),119364.0) -> 119364 | U48: =IFERROR(__xludf.DUMMYFUNCTION("""COMPUTED_VALUE"""),67546.50000000003) -> 67546.5 | V48: =IFERROR(__xludf.DUMMYFUNCTION("""COMPUTED_VALUE"""),"Snacks") -> Snacks | W48: =IFERROR(__xludf.DUMMYFUNCTION("""COMPUTED_VALUE"""),"Europe") -> Europe | X48: =IFERROR(__xludf.DUMMYFUNCTION("""COMPUTED_VALUE"""),"Eastern Europe") -> Eastern Europe | Y48: =IFERROR(__xludf.DUMMYFUNCTION("""COMPUTED_VALUE"""),0.3613841918993316) -> 0.36138419 | Z48: =IFERROR(__xludf.DUMMYFUNCTION("""COMPUTED_VALUE"""),16.0) -> 16 | AA48: =IFERROR(__xludf.DUMMYFUNCTION("""COMPUTED_VALUE"""),7.0) -> 7
A49: =IFERROR(__xludf.DUMMYFUNCTION("""COMPUTED_VALUE"""),4.80652987E8) -> 480652987 | B49: =IFERROR(__xludf.DUMMYFUNCTION("""COMPUTED_VALUE"""),"3/23/2017") -> 3/23/2017 | C49: =IFERROR(__xludf.DUMMYFUNCTION("""COMPUTED_VALUE"""),3.0) -> 3 | D49: =IFERROR(__xludf.DUMMYFUNCTION("""COMPUTED_VALUE"""),23.0) -> 23 | E49: =IFERROR(__xludf.DUMMYFUNCTION("""COMPUTED_VALUE"""),2017.0) -> 2017 | F49: =IFERROR(__xludf.DUMMYFUNCTION("""COMPUTED_VALUE"""),42817.0) -> 42817 | G49: =IFERROR(__xludf.DUMMYFUNCTION("""COMPUTED_VALUE"""),42859.0) -> 42859 | H49: =IFERROR(__xludf.DUMMYFUNCTION("""COMPUTED_VALUE"""),4.0) -> 4 | I49: =IFERROR(__xludf.DUMMYFUNCTION("""COMPUTED_VALUE"""),5.0) -> 5 | J49: =IFERROR(__xludf.DUMMYFUNCTION("""COMPUTED_VALUE"""),2017.0) -> 2017 | K49: =IFERROR(__xludf.DUMMYFUNCTION("""COMPUTED_VALUE"""),42830.0) -> 42830 | L49: =IFERROR(__xludf.DUMMYFUNCTION("""COMPUTED_VALUE"""),"L") -> L | M49: =IFERROR(__xludf.DUMMYFUNCTION("""COMPUTED_VALUE"""),"ITA") -> ITA | N49: =IFERROR(__xludf.DUMMYFUNCTION("""COMPUTED_VALUE"""),7331.0) -> 7331 | O49: =IFERROR(__xludf.DUMMYFUNCTION("""COMPUTED_VALUE"""),"Offline") -> Offline | P49: =IFERROR(__xludf.DUMMYFUNCTION("""COMPUTED_VALUE"""),4755.0) -> 4755 | Q49: =IFERROR(__xludf.DUMMYFUNCTION("""COMPUTED_VALUE"""),255.28) -> 255.28 | R49: =IFERROR(__xludf.DUMMYFUNCTION("""COMPUTED_VALUE"""),159.42) -> 159.42 | S49: =IFERROR(__xludf.DUMMYFUNCTION("""COMPUTED_VALUE"""),1213856.4) -> 1213856.4 | T49: =IFERROR(__xludf.DUMMYFUNCTION("""COMPUTED_VALUE"""),758042.1) -> 758042.1 | U49: =IFERROR(__xludf.DUMMYFUNCTION("""COMPUTED_VALUE"""),455814.29999999993) -> 455814.3 | V49: =IFERROR(__xludf.DUMMYFUNCTION("""COMPUTED_VALUE"""),"Baby Food") -> Baby Food | W49: =IFERROR(__xludf.DUMMYFUNCTION("""COMPUTED_VALUE"""),"Europe") -> Europe | X49: =IFERROR(__xludf.DUMMYFUNCTION("""COMPUTED_VALUE"""),"Southern Europe") -> Southern Europe | Y49: =IFERROR(__xludf.DUMMYFUNCTION("""COMPUTED_VALUE"""),0.3755092447508618) -> 0.37550924 | Z49: =IFERROR(__xludf.DUMMYFUNCTION("""COMPUTED_VALUE"""),13.0) -> 13 | AA49: =IFERROR(__xludf.DUMMYFUNCTION("""COMPUTED_VALUE"""),5.0) -> 5
A50: =IFERROR(__xludf.DUMMYFUNCTION("""COMPUTED_VALUE"""),4.83655774E8) -> 483655774 | B50: =IFERROR(__xludf.DUMMYFUNCTION("""COMPUTED_VALUE"""),"7/18/2017") -> 7/18/2017 | C50: =IFERROR(__xludf.DUMMYFUNCTION("""COMPUTED_VALUE"""),7.0) -> 7 | D50: =IFERROR(__xludf.DUMMYFUNCTION("""COMPUTED_VALUE"""),18.0) -> 18 | E50: =IFERROR(__xludf.DUMMYFUNCTION("""COMPUTED_VALUE"""),2017.0) -> 2017 | F50: =IFERROR(__xludf.DUMMYFUNCTION("""COMPUTED_VALUE"""),42934.0) -> 42934 | G50: =IFERROR(__xludf.DUMMYFUNCTION("""COMPUTED_VALUE"""),42863.0) -> 42863 | H50: =IFERROR(__xludf.DUMMYFUNCTION("""COMPUTED_VALUE"""),8.0) -> 8 | I50: =IFERROR(__xludf.DUMMYFUNCTION("""COMPUTED_VALUE"""),5.0) -> 5 | J50: =IFERROR(__xludf.DUMMYFUNCTION("""COMPUTED_VALUE"""),2017.0) -> 2017 | K50: =IFERROR(__xludf.DUMMYFUNCTION("""COMPUTED_VALUE"""),42952.0) -> 42952 | L50: =IFERROR(__xludf.DUMMYFUNCTION("""COMPUTED_VALUE"""),"H") -> H | M50: =IFERROR(__xludf.DUMMYFUNCTION("""COMPUTED_VALUE"""),"Desconhecido") -> Desconhecido | N50: =IFERROR(__xludf.DUMMYFUNCTION("""COMPUTED_VALUE"""),2103.0) -> 2103 | O50: =IFERROR(__xludf.DUMMYFUNCTION("""COMPUTED_VALUE"""),"Offline") -> Offline | P50: =IFERROR(__xludf.DUMMYFUNCTION("""COMPUTED_VALUE"""),3346.0) -> 3346 | Q50: =IFERROR(__xludf.DUMMYFUNCTION("""COMPUTED_VALUE"""),205.7) -> 205.7 | R50: =IFERROR(__xludf.DUMMYFUNCTION("""COMPUTED_VALUE"""),117.11) -> 117.11 | S50: =IFERROR(__xludf.DUMMYFUNCTION("""COMPUTED_VALUE"""),688272.2) -> 688272.2 | T50: =IFERROR(__xludf.DUMMYFUNCTION("""COMPUTED_VALUE"""),391850.06) -> 391850.06 | U50: =IFERROR(__xludf.DUMMYFUNCTION("""COMPUTED_VALUE"""),296422.13999999996) -> 296422.14 | V50: =IFERROR(__xludf.DUMMYFUNCTION("""COMPUTED_VALUE"""),"Cereal") -> Cereal | W50: =IFERROR(__xludf.DUMMYFUNCTION("""COMPUTED_VALUE"""),"Desconhecido") -> Desconhecido | X50: =IFERROR(__xludf.DUMMYFUNCTION("""COMPUTED_VALUE"""),"Desconhecido") -> Desconhecido | Y50: =IFERROR(__xludf.DUMMYFUNCTION("""COMPUTED_VALUE"""),0.4306757413709285) -> 0.43067574 | Z50: =IFERROR(__xludf.DUMMYFUNCTION("""COMPUTED_VALUE"""),18.0) -> 18 | AA50: =IFERROR(__xludf.DUMMYFUNCTION("""COMPUTED_VALUE"""),3.0) -> 3
A51: =IFERROR(__xludf.DUMMYFUNCTION("""COMPUTED_VALUE"""),4.85929429E8) -> 485929429 | B51: =IFERROR(__xludf.DUMMYFUNCTION("""COMPUTED_VALUE"""),"4/17/2017") -> 4/17/2017 | C51: =IFERROR(__xludf.DUMMYFUNCTION("""COMPUTED_VALUE"""),4.0) -> 4 | D51: =IFERROR(__xludf.DUMMYFUNCTION("""COMPUTED_VALUE"""),17.0) -> 17 | E51: =IFERROR(__xludf.DUMMYFUNCTION("""COMPUTED_VALUE"""),2017.0) -> 2017 | F51: =IFERROR(__xludf.DUMMYFUNCTION("""COMPUTED_VALUE"""),42842.0) -> 42842 | G51: =IFERROR(__xludf.DUMMYFUNCTION("""COMPUTED_VALUE"""),"5/19/2017") -> 5/19/2017 | H51: =IFERROR(__xludf.DUMMYFUNCTION("""COMPUTED_VALUE"""),5.0) -> 5 | I51: =IFERROR(__xludf.DUMMYFUNCTION("""COMPUTED_VALUE"""),19.0) -> 19 | J51: =IFERROR(__xludf.DUMMYFUNCTION("""COMPUTED_VALUE"""),2017.0) -> 2017 | K51: =IFERROR(__xludf.DUMMYFUNCTION("""COMPUTED_VALUE"""),42874.0) -> 42874 | L51: =IFERROR(__xludf.DUMMYFUNCTION("""COMPUTED_VALUE"""),"C") -> C | M51: =IFERROR(__xludf.DUMMYFUNCTION("""COMPUTED_VALUE"""),"UKR") -> UKR | N51: =IFERROR(__xludf.DUMMYFUNCTION("""COMPUTED_VALUE"""),3127.0) -> 3127 | O51: =IFERROR(__xludf.DUMMYFUNCTION("""COMPUTED_VALUE"""),"Offline") -> Offline | P51: =IFERROR(__xludf.DUMMYFUNCTION("""COMPUTED_VALUE"""),6171.0) -> 6171 | Q51: =IFERROR(__xludf.DUMMYFUNCTION("""COMPUTED_VALUE"""),81.73) -> 81.73 | R51: =IFERROR(__xludf.DUMMYFUNCTION("""COMPUTED_VALUE"""),56.67) -> 56.67 | S51: =IFERROR(__xludf.DUMMYFUNCTION("""COMPUTED_VALUE"""),504355.83) -> 504355.83 | T51: =IFERROR(__xludf.DUMMYFUNCTION("""COMPUTED_VALUE"""),349710.57) -> 349710.57 | U51: =IFERROR(__xludf.DUMMYFUNCTION("""COMPUTED_VALUE"""),154645.26) -> 154645.26 | V51: =IFERROR(__xludf.DUMMYFUNCTION("""COMPUTED_VALUE"""),"Personal Care") -> Personal Care | W51: =IFERROR(__xludf.DUMMYFUNCTION("""COMPUTED_VALUE"""),"Europe") -> Europe | X51: =IFERROR(__xludf.DUMMYFUNCTION("""COMPUTED_VALUE"""),"Eastern Europe") -> Eastern Europe | Y51: =IFERROR(__xludf.DUMMYFUNCTION("""COMPUTED_VALUE"""),0.3066193564174722) -> 0.30661936 | Z51: =IFERROR(__xludf.DUMMYFUNCTION("""COMPUTED_VALUE"""),32.0) -> 32 | AA51: =IFERROR(__xludf.DUMMYFUNCTION("""COMPUTED_VALUE"""),2.0) -> 2
A52: =IFERROR(__xludf.DUMMYFUNCTION("""COMPUTED_VALUE"""),5.13802516E8) -> 513802516 | B52: =IFERROR(__xludf.DUMMYFUNCTION("""COMPUTED_VALUE"""),42773.0) -> 42773 | C52: =IFERROR(__xludf.DUMMYFUNCTION("""COMPUTED_VALUE"""),7.0) -> 7 | D52: =IFERROR(__xludf.DUMMYFUNCTION("""COMPUTED_VALUE"""),2.0) -> 2 | E52: =IFERROR(__xludf.DUMMYFUNCTION("""COMPUTED_VALUE"""),2017.0) -> 2017 | F52: =IFERROR(__xludf.DUMMYFUNCTION("""COMPUTED_VALUE"""),42918.0) -> 42918 | G52: =IFERROR(__xludf.DUMMYFUNCTION("""COMPUTED_VALUE"""),42924.0) -> 42924 | H52: =IFERROR(__xludf.DUMMYFUNCTION("""COMPUTED_VALUE"""),8.0) -> 8 | I52: =IFERROR(__xludf.DUMMYFUNCTION("""COMPUTED_VALUE"""),7.0) -> 7 | J52: =IFERROR(__xludf.DUMMYFUNCTION("""COMPUTED_VALUE"""),2017.0) -> 2017 | K52: =IFERROR(__xludf.DUMMYFUNCTION("""COMPUTED_VALUE"""),42954.0) -> 42954 | L52: =IFERROR(__xludf.DUMMYFUNCTION("""COMPUTED_VALUE"""),"L") -> L | M52: =IFERROR(__xludf.DUMMYFUNCTION("""COMPUTED_VALUE"""),"ESP") -> ESP | N52: =IFERROR(__xludf.DUMMYFUNCTION("""COMPUTED_VALUE"""),8681.0) -> 8681 | O52: =IFERROR(__xludf.DUMMYFUNCTION("""COMPUTED_VALUE"""),"Online") -> Online | P52: =IFERROR(__xludf.DUMMYFUNCTION("""COMPUTED_VALUE"""),4437.0) -> 4437 | Q52: =IFERROR(__xludf.DUMMYFUNCTION("""COMPUTED_VALUE"""),651.21) -> 651.21 | R52: =IFERROR(__xludf.DUMMYFUNCTION("""COMPUTED_VALUE"""),524.96) -> 524.96 | S52: =IFERROR(__xludf.DUMMYFUNCTION("""COMPUTED_VALUE"""),2889418.77) -> 2889418.8 | T52: =IFERROR(__xludf.DUMMYFUNCTION("""COMPUTED_VALUE"""),2329247.52) -> 2329247.5 | U52: =IFERROR(__xludf.DUMMYFUNCTION("""COMPUTED_VALUE"""),560171.25) -> 560171.25 | V52: =IFERROR(__xludf.DUMMYFUNCTION("""COMPUTED_VALUE"""),"Office Supplies") -> Office Supplies | W52: =IFERROR(__xludf.DUMMYFUNCTION("""COMPUTED_VALUE"""),"Europe") -> Europe | X52: =IFERROR(__xludf.DUMMYFUNCTION("""COMPUTED_VALUE"""),"Southern Europe") -> Southern Europe | Y52: =IFERROR(__xludf.DUMMYFUNCTION("""COMPUTED_VALUE"""),0.19386987300563566) -> 0.19386987 | Z52: =IFERROR(__xludf.DUMMYFUNCTION("""COMPUTED_VALUE"""),36.0) -> 36 | AA52: =IFERROR(__xludf.DUMMYFUNCTION("""COMPUTED_VALUE"""),1.0) -> 1
